Workbook

Sheet Enero
A1: n | C1: 45992 | D1: 45871 | E1: 45872 | F1: 45873 | G1: 45874 | H1: 45875 | I1: 45876 | J1: 45877 | K1: 45878 | L1: 45879 | M1: 45880 | N1: 45881 | O1: 45882 | P1: 45883 | Q1: 45884 | R1: 45885 | S1: 45886 | T1: 45887 | U1: 45888 | V1: 45889 | W1: 45890 | X1: 45891 | Y1: 45892 | Z1: 45893 | AA1: 45894 | AB1: 45895 | AC1: 45896 | AD1: 45897 | AE1: 45898 | AF1: 45899 | AG1: 45900 | AH1: Totales
A4: Ingresos
A5: Transbank | C5: =338308+252796+1158748 -> 1749852 | D5: =85094 -> 85094 | E5: =916940+66163+409746+62276 -> 1455125 | F5: =165710+665914+1146843+66462 -> 2044929 | G5: 1241627 | H5: =328154+28299+22320 -> 378773 | I5: =42064+731212+610411+25807 -> 1409494 | J5: =929067+562920+20526 -> 1512513 | K5: =761874+492440+12575+18335 -> 1285224 | L5: =590744+1150349+82663+6500+28700 -> 1858956 | M5: =164012+2005743+34456+541161 -> 2745372 | N5: =18633+308395+1111972 -> 1439000 | O5: =232286+45936 -> 278222 | P5: =18135+971916+62673+532669 -> 1585393 | Q5: =385159+603857+33805 -> 1022821 | R5: =833270+548534+9906+11693 -> 1403403 | S5: =92071+1216512+611996+38064 -> 1958643 | T5: =1710791+113993+444009+139202+21483 -> 2429478 | U5: =1301009+347355 -> 1648364 | V5: =294445+37402+90642 -> 422489 | W5: =98537+895436+564681+24594 -> 1583248 | X5: =110105+22250+1105+837440+524121 -> 1495021 | Y5: =99841+415619+4270+133323+13920 -> 666973 | Z5: =40226+43245+606190+33979+585213 -> 1308853 | AA5: =133521+125252+34476+1296338+513560 -> 2103147 | AB5: =264553+912968 -> 1177521 | AC5: =132560+122866 -> 255426 | AD5: =689243+673607+39659+57992 -> 1460501 | AE5: =612490+406077+30073+48348+135414 -> 1232402 | AF5: =526085+883898+78917 -> 1488900 | AG5: =1035920+102124+597956+86411+129436+32186 -> 1984033 | AH5: =SUM(C5:AG5) -> 42710797
A6: Transferencias | C6: 0 | D6: 28400 | E6: =35090+6200 -> 41290 | F6: 0 | G6: 29600 | H6: =8200+30400 -> 38600 | I6: 0 | J6: 0 | K6: 0 | L6: 0 | M6: 0 | N6: 25990 | O6: 0 | P6: 0 | Q6: 0 | R6: 0 | S6: 0 | T6: 0 | U6: 0 | V6: 0 | W6: 0 | X6: 0 | Y6: 30500 | Z6: 0 | AA6: 0 | AB6: 0 | AC6: 25690 | AD6: 0 | AE6: 0 | AF6: 0 | AG6: 0 | AH6: =SUM(C6:AG6) -> 220070
A7: Efectivo | C7: 0 | D7: 0 | E7: 0 | F7: 0 | G7: 0 | H7: 0 | I7: 0 | J7: 0 | K7: 0 | L7: 0 | M7: 0 | N7: 0 | O7: 380000 | P7: 0 | Q7: 0 | R7: 0 | S7: 0 | T7: 0 | U7: 0 | V7: 0 | W7: 0 | X7: 0 | Y7: 0 | Z7: 0 | AA7: 0 | AB7: 0 | AC7: 0 | AD7: 0 | AE7: 0 | AF7: 0 | AG7: 0 | AH7: =SUM(C7:AG7) -> 380000
A8: Uber | C8: 0 | D8: 0 | E8: 0 | F8: 0 | G8: 0 | H8: =481480+464285 -> 945765 | I8: 0 | J8: 0 | K8: 0 | L8: 0 | M8: 0 | N8: 0 | O8: =481617+103191 -> 584808 | P8: 0 | Q8: 0 | R8: 0 | S8: 0 | T8: 0 | U8: 0 | V8: 321048 | W8: 0 | X8: 0 | Y8: 0 | Z8: 0 | AA8: 0 | AB8: 0 | AC8: =168900+366611 -> 535511 | AD8: 0 | AE8: 0 | AF8: 0 | AG8: 0 | AH8: =SUM(C8:AG8) -> 2387132
A9: Total bruto | C9: =SUM(C5:C8) -> 1749852 | D9: =SUM(D5:D8) -> 113494 | E9: =SUM(E5:E8) -> 1496415 | F9: =SUM(F5:F8) -> 2044929 | G9: =SUM(G5:G8) -> 1271227 | H9: =SUM(H5:H8) -> 1363138 | I9: =SUM(I5:I8) -> 1409494 | J9: =SUM(J5:J8) -> 1512513 | ... AH9: =SUM(AH5:AH8) -> 45697999
A10: Total neto | AH10: =AH9-AH78 -> 39294269
A12: Materia prima | B12: =AH12/$AH$10 -> 0.31442746 | C12: =sum(C13:C29) -> 0 | D12: =sum(D13:D29) -> 1438566 | E12: =sum(E13:E29) -> 69320 | F12: =sum(F13:F29) -> 76500 | G12: =sum(G14:G29) -> 871050 | H12: =sum(H13:H29) -> 1042424 | I12: =sum(I13:I29) -> 257328 | J12: =sum(J13:J29) -> 102887 | K12: =sum(K13:K29) -> 397169 | L12: =sum(L13:L29) -> 99976 | M12: =sum(M13:M29) -> 72460 | N12: =sum(N13:N29) -> 859478 | O12: =sum(O13:O29) -> 1052873 | ... AH12: =sum(AH13:AH29) -> 12355197
A13: MP | B13: =AH13/$AH$10 -> 0.030696283 | C13: 0 | D13: =116000+58240+7200+11600 -> 193040 | E13: 69320 | F13: 0 | G13: 0 | H13: =12990 -> 12990 | I13: 6000 | J13: 0 | K13: 0 | L13: =90026+9950 -> 99976 | M13: 48480 | N13: 4500 | O13: 0 | P13: 0 | Q13: 0 | R13: 0 | S13: 21300 | T13: 0 | U13: 0 | V13: =77350+44300 -> 121650 | W13: =153986+49980 -> 203966 | X13: 0 | Y13: =52230 -> 52230 | Z13: =152897+13000 -> 165897 | AA13: 0 | AB13: 0 | AC13: =99008+3831 -> 102839 | AD13: 0 | AE13: =94000 -> 94000 | AF13: 10000 | AG13: 0 | AH13: =SUM(C13:AG13) -> 1206188
A14: Hod Food | B14: =AH14/$AH$10 -> 0.068520552 | C14: 0 | D14: 0 | E14: 0 | F14: 0 | G14: 736104 | H14: 0 | I14: 0 | J14: 0 | K14: 0 | L14: 0 | M14: 0 | N14: 324858 | O14: 0 | P14: 0 | Q14: 0 | R14: 0 | S14: 0 | T14: 0 | U14: 561478 | V14: 0 | W14: 0 | X14: 0 | Y14: 0 | Z14: 0 | AA14: 0 | AB14: 0 | AC14: 1070025 | AD14: 0 | AE14: 0 | AF14: 0 | AG14: 0 | AH14: =SUM(C14:AG14) -> 2692465
A15: Seitan | B15: =AH15/$AH$10 -> 0.0039187903 | C15: 0 | D15: 153986 | E15: 0 | F15: 0 | G15: 0 | H15: 0 | I15: 0 | J15: 0 | K15: 0 | L15: 0 | M15: 0 | N15: 0 | O15: 0 | P15: 0 | Q15: 0 | R15: 0 | S15: 0 | T15: 0 | U15: 0 | V15: 0 | W15: 0 | X15: 0 | Y15: 0 | Z15: 0 | AA15: 0 | AB15: 0 | AC15: 0 | AD15: 0 | AE15: 0 | AF15: 0 | AG15: 0 | AH15: =SUM(C15:AG15) -> 153986
A16: Palta | B16: =AH16/$AH$10 -> 0.045196311 | C16: 0 | D16: 830025 | E16: 0 | F16: 0 | G16: 0 | H16: 0 | I16: 0 | J16: 0 | K16: 0 | L16: 0 | M16: 0 | N16: 521220 | O16: 0 | P16: 0 | Q16: 0 | R16: 0 | S16: 0 | T16: 0 | U16: 0 | V16: 0 | W16: 0 | X16: 0 | Y16: 0 | Z16: 424711 | AA16: 0 | AB16: 0 | AC16: 0 | AD16: 0 | AE16: 0 | AF16: 0 | AG16: 0 | AH16: =SUM(C16:AG16) -> 1775956
A17: Carivo | B17: =AH17/$AH$10 -> 0.060522439 | C17: 0 | D17: 0 | E17: 0 | F17: 0 | G17: 0 | H17: 827125 | I17: 0 | J17: 0 | K17: 0 | L17: 0 | M17: 0 | N17: 0 | O17: 759110 | P17: 0 | Q17: 0 | R17: 0 | S17: 0 | T17: 0 | U17: 0 | V17: 791950 | W17: 0 | X17: 0 | Y17: 0 | Z17: 0 | AA17: 0 | AB17: 0 | AC17: 0 | AD17: 0 | AE17: 0 | AF17: 0 | AG17: 0 | AH17: =SUM(C17:AG17) -> 2378185
A18: Shen | B18: =AH18/$AH$10 -> 0.018412863 | C18: 0 | D18: 0 | E18: 0 | F18: 76500 | G18: 0 | H18: 0 | I18: 0 | J18: 0 | K18: 206720 | L18: 0 | M18: 0 | N18: 0 | O18: 0 | P18: 159460 | Q18: 0 | R18: 0 | S18: 0 | T18: 0 | U18: 0 | V18: 0 | W18: 159460 | X18: 0 | Y18: 0 | Z18: 0 | AA18: 0 | AB18: 0 | AC18: 121380 | AD18: 0 | AE18: 0 | AF18: 0 | AG18: 0 | AH18: =SUM(C18:AG18) -> 723520
A19: Mozzen | B19: =AH19/$AH$10 -> 0.0094686836 | C19: 0 | D19: 0 | E19: 0 | F19: 0 | G19: 0 | H19: 0 | I19: 0 | J19: 0 | K19: 0 | L19: 0 | M19: 0 | N19: 0 | O19: 191185 | P19: 0 | Q19: 0 | R19: 0 | S19: 0 | T19: 0 | U19: 0 | V19: 0 | W19: 0 | X19: 0 | Y19: 0 | Z19: 0 | AA19: 0 | AB19: 0 | AC19: 0 | AD19: 180880 | AE19: 0 | AF19: 0 | AG19: 0 | AH19: =SUM(C19:AG19) -> 372065
A20: Café y Té | B20: =AH20/$AH$10 -> 0 | C20: 0 | D20: 0 | E20: 0 | F20: 0 | G20: 0 | H20: 0 | I20: 0 | J20: 0 | K20: 0 | L20: 0 | M20: 0 | N20: 0 | O20: 0 | P20: 0 | Q20: 0 | R20: 0 | S20: 0 | T20: 0 | U20: 0 | V20: 0 | W20: 0 | X20: 0 | Y20: 0 | Z20: 0 | AA20: 0 | AB20: 0 | AC20: 0 | AD20: 0 | AE20: 0 | AF20: 0 | AG20: 0 | AH20: =SUM(C20:AG20) -> 0
A21: Leche de soya | B21: =AH21/$AH$10 -> 0.0060447492 | C21: 0 | D21: 0 | E21: 0 | F21: 0 | G21: 134946 | H21: 0 | I21: 0 | J21: 0 | K21: 0 | L21: 0 | M21: 0 | N21: 0 | O21: 102578 | P21: 0 | Q21: 0 | R21: 0 | S21: 0 | T21: 0 | U21: 0 | V21: 0 | W21: 0 | X21: 0 | Y21: 0 | Z21: 0 | AA21: 0 | AB21: 0 | AC21: 0 | AD21: 0 | AE21: 0 | AF21: 0 | AG21: 0 | AH21: =SUM(C21:AG21) -> 237524
A22: Bebestibles | B22: =AH22/$AH$10 -> 0.0056767057 | C22: 0 | D22: 0 | E22: 0 | F22: 0 | G22: 0 | H22: =23205+2200 -> 25405 | I22: 0 | J22: 0 | K22: 0 | L22: 0 | M22: 19480 | N22: 0 | O22: 0 | P22: 46410 | Q22: 0 | R22: 0 | S22: 0 | T22: 0 | U22: 0 | V22: 23205 | W22: 0 | X22: 0 | Y22: =61152+46410 -> 107562 | Z22: 0 | AA22: 0 | AB22: 0 | AC22: 0 | AD22: 0 | AE22: 1000 | AF22: 0 | AG22: 0 | AH22: =SUM(C22:AG22) -> 223062
A23: Brugga | B23: =AH23/$AH$10 -> 0.01758913 | C23: 0 | D23: 0 | E23: 0 | F23: 0 | G23: 0 | H23: 0 | I23: 251328 | J23: 0 | K23: 0 | L23: 0 | M23: 0 | N23: 0 | O23: 0 | P23: 0 | Q23: 0 | R23: 0 | S23: 0 | T23: 0 | U23: 0 | V23: 157080 | W23: 0 | X23: 0 | Y23: 0 | Z23: 0 | AA23: 0 | AB23: 0 | AC23: 0 | AD23: 0 | AE23: 0 | AF23: 282744 | AG23: 0 | AH23: =SUM(C23:AG23) -> 691152
A24: Colación | B24: =AH24/$AH$10 -> 0.0099126415 | C24: 0 | D24: =12000+37778 -> 49778 | E24: 0 | F24: 0 | G24: 0 | H24: 47187 | I24: 0 | J24: 28887 | K24: 0 | L24: 0 | M24: 4500 | N24: 8900 | O24: 0 | P24: 0 | Q24: 0 | R24: 44636 | S24: 0 | T24: 0 | U24: 8000 | V24: 39940 | W24: 0 | X24: 0 | Y24: 51856 | Z24: 6700 | AA24: 0 | AB24: =12570 -> 12570 | AC24: 86556 | AD24: 0 | AE24: 0 | AF24: 0 | AG24: 0 | AH24: =SUM(C24:AG24) -> 389510
A25: Empaques y desechables | B25: =AH25/$AH$10 -> 0.017401062 | C25: 0 | D25: =199057+8000+4680 -> 211737 | E25: 0 | F25: 0 | G25: 0 | H25: 39720 | I25: 0 | J25: 0 | K25: 12839 | L25: 0 | M25: 0 | N25: 0 | O25: 0 | P25: 167879 | Q25: 0 | R25: 27400 | S25: 0 | T25: 0 | U25: 0 | V25: =68019+13070 -> 81089 | W25: 0 | X25: 0 | Y25: 0 | Z25: 0 | AA25: 0 | AB25: 0 | AC25: 0 | AD25: 0 | AE25: 143098 | AF25: 0 | AG25: 0 | AH25: =SUM(C25:AG25) -> 683762
A26: Soyas sachet | B26: =AH26/$AH$10 -> 0.004580668 | C26: 0 | D26: 0 | E26: 0 | F26: 0 | G26: 0 | H26: 89997 | I26: 0 | J26: 0 | K26: 0 | L26: 0 | M26: 0 | N26: 0 | O26: 0 | P26: 0 | Q26: 0 | R26: 0 | S26: 0 | T26: 0 | U26: 0 | V26: 0 | W26: 0 | X26: 89997 | Y26: 0 | Z26: 0 | AA26: 0 | AB26: 0 | AC26: 0 | AD26: 0 | AE26: 0 | AF26: 0 | AG26: 0 | AH26: =SUM(C26:AG26) -> 179994
A27: Servilletas | B27: =AH27/$AH$10 -> 0 | C27: 0 | D27: 0 | E27: 0 | F27: 0 | G27: 0 | H27: 0 | I27: 0 | J27: 0 | K27: 0 | L27: 0 | M27: 0 | N27: 0 | O27: 0 | P27: 0 | Q27: 0 | R27: 0 | S27: 0 | T27: 0 | U27: 0 | V27: 0 | W27: 0 | X27: 0 | Y27: 0 | Z27: 0 | AA27: 0 | AB27: 0 | AC27: 0 | AD27: 0 | AE27: 0 | AF27: 0 | AG27: 0 | AH27: =SUM(C27:AG27) -> 0
A28: Limpieza e higiene | B28: =AH28/$AH$10 -> 0 | C28: 0 | D28: 0 | E28: 0 | F28: 0 | G28: 0 | H28: 0 | I28: 0 | J28: 0 | K28: 0 | L28: 0 | M28: 0 | N28: 0 | O28: 0 | P28: 0 | Q28: 0 | R28: 0 | S28: 0 | T28: 0 | U28: 0 | V28: 0 | W28: 0 | X28: 0 | Y28: 0 | Z28: 0 | AA28: 0 | AB28: 0 | AC28: 0 | AD28: 0 | AE28: 0 | AF28: 0 | AG28: 0 | AH28: =SUM(C28:AG28) -> 0
A29: Postres | B29: =AH29/$AH$10 -> 0.016486577 | C29: 0 | D29: 0 | E29: 0 | F29: 0 | G29: 0 | H29: 0 | I29: 0 | J29: 74000 | K29: 177610 | L29: 0 | M29: 0 | N29: 0 | O29: 0 | P29: 0 | Q29: 0 | R29: 0 | S29: 0 | T29: 0 | U29: 0 | V29: 0 | W29: 235218 | X29: 0 | Y29: 0 | Z29: =74000+13000 -> 87000 | AA29: 0 | AB29: 0 | AC29: 0 | AD29: 0 | AE29: 74000 | AF29: 0 | AG29: 0 | AH29: =SUM(C29:AG29) -> 647828
A31: Gastos FV | B31: =AH31/$AH$10 -> 0.2216496 | C31: =sum(C32+C51+C61) -> 0 | D31: =sum(D32+D51+D61) -> 614000 | E31: =sum(E32+E51+E61) -> 58245 | F31: =sum(F32+F51+F61) -> 0 | G31: =sum(G32+G51+G61) -> 276088 | H31: =sum(H32+H51+H61) -> 210771 | I31: =sum(I32+I51+I61) -> 1945512 | J31: =sum(J32+J51+J61) -> 100000 | ... AH31: =sum(AH32+AH51+AH61) -> 8709559
A32: Operaciones | B32: =AH32/$AH$10 -> 0.16157361 | C32: =sum(C33:C50) -> 0 | D32: =sum(D33:D50) -> 0 | E32: =sum(E33:E50) -> 0 | F32: =sum(F33:F50) -> 0 | G32: =sum(G33:G50) -> 167310 | H32: =sum(H33:H50) -> 121071 | I32: =sum(I33:I50) -> 1945512 | J32: =sum(J33:J50) -> 100000 | ... AH32: =sum(AH33:AH50) -> 6348917
A33: Electricidad | B33: =AH33/$AH$10 -> 0.0040682777 | C33: 0 | D33: 0 | E33: 0 | F33: 0 | G33: 0 | H33: 0 | I33: 0 | J33: 0 | K33: 0 | L33: 0 | M33: 0 | N33: 0 | O33: 0 | P33: 0 | Q33: 0 | R33: 159860 | S33: 0 | T33: 0 | U33: 0 | V33: 0 | W33: 0 | X33: 0 | Y33: 0 | Z33: 0 | AA33: 0 | AB33: 0 | AC33: 0 | AD33: 0 | AE33: 0 | AF33: 0 | AG33: 0 | AH33: =SUM(C33:AG33) -> 159860
A34: Agua | B34: =AH34/$AH$10 -> 0.0035797841 | C34: 0 | D34: 0 | E34: 0 | F34: 0 | G34: 0 | H34: 0 | I34: 0 | J34: 0 | K34: 0 | L34: 0 | M34: 0 | N34: 0 | O34: 0 | P34: 0 | Q34: 0 | R34: 140665 | S34: 0 | T34: 0 | U34: 0 | V34: 0 | W34: 0 | X34: 0 | Y34: 0 | Z34: 0 | AA34: 0 | AB34: 0 | AC34: 0 | AD34: 0 | AE34: 0 | AF34: 0 | AG34: 0 | AH34: =SUM(C34:AG34) -> 140665
A35: Gas | B35: =AH35/$AH$10 -> 0.0094866251 | C35: 0 | D35: 0 | E35: 0 | F35: 0 | G35: 0 | H35: 0 | I35: 0 | J35: 0 | K35: 0 | L35: 0 | M35: 0 | N35: 0 | O35: 0 | P35: 0 | Q35: 0 | R35: 372770 | S35: 0 | T35: 0 | U35: 0 | V35: 0 | W35: 0 | X35: 0 | Y35: 0 | Z35: 0 | AA35: 0 | AB35: 0 | AC35: 0 | AD35: 0 | AE35: 0 | AF35: 0 | AG35: 0 | AH35: =SUM(C35:AG35) -> 372770
A36: Restaurantpe | B36: =AH36/$AH$10 -> 0 | C36: 0 | D36: 0 | E36: 0 | F36: 0 | G36: 0 | H36: 0 | I36: 0 | J36: 0 | K36: 0 | L36: 0 | M36: 0 | N36: 0 | O36: 0 | P36: 0 | Q36: 0 | R36: 0 | S36: 0 | T36: 0 | U36: 0 | V36: 0 | W36: 0 | X36: 0 | Y36: 0 | Z36: 0 | AA36: 0 | AB36: 0 | AC36: 0 | AD36: 0 | AE36: 0 | AF36: 0 | AG36: 0 | AH36: =SUM(C36:AG36) -> 0
A37: Toteat | B37: =AH37/$AH$10 -> 0.0052056192 | C37: 0 | D37: 0 | E37: 0 | F37: 0 | G37: 0 | H37: 109554 | I37: 0 | J37: 0 | K37: 0 | L37: 0 | M37: 94997 | N37: 0 | O37: 0 | P37: 0 | Q37: 0 | R37: 0 | S37: 0 | T37: 0 | U37: 0 | V37: 0 | W37: 0 | X37: 0 | Y37: 0 | Z37: 0 | AA37: 0 | AB37: 0 | AC37: 0 | AD37: 0 | AE37: 0 | AF37: 0 | AG37: 0 | AH37: =SUM(C37:AG37) -> 204551
A38: Alarma | B38: =AH38/$AH$10 -> 0.0012152917 | C38: 0 | D38: 0 | E38: 0 | F38: 0 | G38: 0 | H38: 0 | I38: 0 | J38: 0 | K38: 0 | L38: 0 | M38: 0 | N38: 0 | O38: 0 | P38: 0 | Q38: 0 | R38: 0 | S38: 0 | T38: 0 | U38: 0 | V38: 0 | W38: 0 | X38: 0 | Y38: 0 | Z38: 0 | AA38: 0 | AB38: 0 | AC38: 0 | AD38: 47754 | AE38: 0 | AF38: 0 | AG38: 0 | AH38: =SUM(C38:AG38) -> 47754
A39: VTR | B39: =AH39/$AH$10 -> 0.00029309618 | C39: 0 | D39: 0 | E39: 0 | F39: 0 | G39: 0 | H39: 11517 | I39: 0 | J39: 0 | K39: 0 | L39: 0 | M39: 0 | N39: 0 | O39: 0 | P39: 0 | Q39: 0 | R39: 0 | S39: 0 | T39: 0 | U39: 0 | V39: 0 | W39: 0 | X39: 0 | Y39: 0 | Z39: 0 | AA39: 0 | AB39: 0 | AC39: 0 | AD39: 0 | AE39: 0 | AF39: 0 | AG39: 0 | AH39: =SUM(C39:AG39) -> 11517
A40: Bodega | B40: =AH40/$AH$10 -> 0.0076347011 | C40: 0 | D40: 0 | E40: 0 | F40: 0 | G40: 0 | H40: 0 | I40: 0 | J40: 0 | K40: 0 | L40: 0 | M40: 0 | N40: 0 | O40: 0 | P40: 0 | Q40: 0 | R40: 0 | S40: 0 | T40: 300000 | U40: 0 | V40: 0 | W40: 0 | X40: 0 | Y40: 0 | Z40: 0 | AA40: 0 | AB40: 0 | AC40: 0 | AD40: 0 | AE40: 0 | AF40: 0 | AG40: 0 | AH40: =SUM(C40:AG40) -> 300000
A41: Arriendo | B41: =AH41/$AH$10 -> 0.046512177 | C41: 0 | D41: 0 | E41: 0 | F41: 0 | G41: 0 | H41: 0 | I41: 1827662 | J41: 0 | K41: 0 | L41: 0 | M41: 0 | N41: 0 | O41: 0 | P41: 0 | Q41: 0 | R41: 0 | S41: 0 | T41: 0 | U41: 0 | V41: 0 | W41: 0 | X41: 0 | Y41: 0 | Z41: 0 | AA41: 0 | AB41: 0 | AC41: 0 | AD41: 0 | AE41: 0 | AF41: 0 | AG41: 0 | AH41: =SUM(C41:AG41) -> 1827662
A42: Funmigacion | B42: =AH42/$AH$10 -> 0.0029991651 | C42: 0 | D42: 0 | E42: 0 | F42: 0 | G42: 0 | H42: 0 | I42: 117850 | J42: 0 | K42: 0 | L42: 0 | M42: 0 | N42: 0 | O42: 0 | P42: 0 | Q42: 0 | R42: 0 | S42: 0 | T42: 0 | U42: 0 | V42: 0 | W42: 0 | X42: 0 | Y42: 0 | Z42: 0 | AA42: 0 | AB42: 0 | AC42: 0 | AD42: 0 | AE42: 0 | AF42: 0 | AG42: 0 | AH42: =SUM(C42:AG42) -> 117850
A43: Reposición de vasos | B43: =AH43/$AH$10 -> 0 | C43: 0 | D43: 0 | E43: 0 | F43: 0 | G43: 0 | H43: 0 | I43: 0 | J43: 0 | K43: 0 | L43: 0 | M43: 0 | N43: 0 | O43: 0 | P43: 0 | Q43: 0 | R43: 0 | S43: 0 | T43: 0 | U43: 0 | V43: 0 | W43: 0 | X43: 0 | Y43: 0 | Z43: 0 | AA43: 0 | AB43: 0 | AC43: 0 | AD43: 0 | AE43: 0 | AF43: 0 | AG43: 0 | AH43: =SUM(C43:AG43) -> 0
A44: Reposición Articulos cocina | B44: =AH44/$AH$10 -> 0.0047640535 | C44: 0 | D44: 0 | E44: 0 | F44: 0 | G44: 0 | H44: 0 | I44: 0 | J44: 100000 | K44: 0 | L44: 87200 | M44: 0 | N44: 0 | O44: 0 | P44: 0 | Q44: 0 | R44: 0 | S44: 0 | T44: 0 | U44: 0 | V44: 0 | W44: 0 | X44: 0 | Y44: 0 | Z44: 0 | AA44: 0 | AB44: 0 | AC44: 0 | AD44: 0 | AE44: 0 | AF44: 0 | AG44: 0 | AH44: =SUM(C44:AG44) -> 187200
... A50: Fee | B50: =AH50/$AH$10 -> 0.069098168 | C50: 0 | D50: 0 | E50: 0 | F50: 0 | G50: 0 | H50: 0 | I50: 0 | J50: 0 | K50: 0 | L50: 0 | M50: 2715162 | N50: 0 | O50: 0 | P50: 0 | Q50: 0 | R50: 0 | S50: 0 | T50: 0 | U50: 0 | V50: 0 | W50: 0 | X50: 0 | Y50: 0 | Z50: 0 | AA50: 0 | AB50: 0 | AC50: 0 | AD50: 0 | AE50: 0 | AF50: 0 | AG50: 0 | AH50: =SUM(C50:AG50) -> 2715162
A51: Administración y finanzas | B51: =AH51/$AH$10 -> 0.015455053 | C51: =sum(C52:C59) -> 0 | D51: =sum(D52:D59) -> 14000 | E51: =sum(E52:E59) -> 0 | F51: =sum(F52:F59) -> 0 | G51: =sum(G52:G59) -> 0 | H51: =sum(H52:H59) -> 42100 | I51: =sum(I52:I59) -> 0 | J51: =sum(J52:J59) -> 0 | ... AE51: =sum(AE52:AE59) -> 0 | AF51: =SUM(AF52:AF59) -> 347220 | AG51: =sum(AG52:AG59) -> 27900 | AH51: =SUM(AH52:AH59) -> 607295
A52: Comisiones cuenta corriente | B52: =AH52/$AH$10 -> 0.00010037087 | C52: 0 | D52: 0 | E52: 0 | F52: 0 | G52: 0 | H52: 0 | I52: 0 | J52: 0 | K52: 3944 | L52: 0 | M52: 0 | N52: 0 | O52: 0 | P52: 0 | Q52: 0 | R52: 0 | S52: 0 | T52: 0 | U52: 0 | V52: 0 | W52: 0 | X52: 0 | Y52: 0 | Z52: 0 | AA52: 0 | AB52: 0 | AC52: 0 | AD52: 0 | AE52: 0 | AF52: 0 | AG52: 0 | AH52: =SUM(C52:AG52) -> 3944
A53: Contadora | B53: =AH53/$AH$10 -> 0.0015269402 | C53: 0 | D53: 0 | E53: 0 | F53: 0 | G53: 0 | H53: 0 | I53: 0 | J53: 0 | K53: 0 | L53: 0 | M53: 0 | N53: 0 | O53: 0 | P53: 0 | Q53: 0 | R53: 0 | S53: 0 | T53: 0 | U53: 0 | V53: 0 | W53: 0 | X53: 0 | Y53: 0 | Z53: 0 | AA53: 0 | AB53: 0 | AC53: 0 | AD53: 60000 | AE53: 0 | AF53: 0 | AG53: 0 | AH53: =SUM(C53:AG53) -> 60000
A54: Patentes comerciales | B54: =AH54/$AH$10 -> 0.0088364031 | C54: 0 | D54: 0 | E54: 0 | F54: 0 | G54: 0 | H54: 0 | I54: 0 | J54: 0 | K54: 0 | L54: 0 | M54: 0 | N54: 0 | O54: 0 | P54: 0 | Q54: 0 | R54: 0 | S54: 0 | T54: 0 | U54: 0 | V54: 0 | W54: 0 | X54: 0 | Y54: 0 | Z54: 0 | AA54: 0 | AB54: 0 | AC54: 0 | AD54: 0 | AE54: 0 | AF54: 347220 | AG54: 0 | AH54: =SUM(C54:AG54) -> 347220
A55: Insumos de oficina | B55: =AH55/$AH$10 -> 0.0025914975 | C55: 0 | D55: 14000 | E55: 0 | F55: 0 | G55: 0 | H55: 0 | I55: 0 | J55: 0 | K55: 0 | L55: 0 | M55: 0 | N55: 0 | O55: 0 | P55: 0 | Q55: 0 | R55: 0 | S55: 0 | T55: 9500 | U55: 0 | V55: 0 | W55: 10400 | X55: 0 | Y55: 0 | Z55: 0 | AA55: 0 | AB55: 8490 | AC55: 59441 | AD55: 0 | AE55: 0 | AF55: 0 | AG55: 0 | AH55: =SUM(C55:AG55) -> 101831
A56: Wasabil | B56: =AH56/$AH$10 -> 0 | C56: 0 | D56: 0 | E56: 0 | F56: 0 | G56: 0 | H56: 0 | I56: 0 | J56: 0 | K56: 0 | L56: 0 | M56: 0 | N56: 0 | O56: 0 | P56: 0 | Q56: 0 | R56: 0 | S56: 0 | T56: 0 | U56: 0 | V56: 0 | W56: 0 | X56: 0 | Y56: 0 | Z56: 0 | AA56: 0 | AB56: 0 | AC56: 0 | AD56: 0 | AE56: 0 | AF56: 0 | AG56: 0 | AH56: =SUM(C56:AG56) -> 0
A57: Devolución clientes | B57: =AH57/$AH$10 -> 0.0023998411 | C57: 0 | D57: 0 | E57: 0 | F57: 0 | G57: 0 | H57: 42100 | I57: 0 | J57: 0 | K57: 0 | L57: 0 | M57: 0 | N57: 0 | O57: 0 | P57: 24300 | Q57: 0 | R57: 0 | S57: 0 | T57: 0 | U57: 0 | V57: 0 | W57: 0 | X57: 0 | Y57: 0 | Z57: 0 | AA57: 0 | AB57: 0 | AC57: 0 | AD57: 0 | AE57: 0 | AF57: 0 | AG57: 27900 | AH57: =SUM(C57:AG57) -> 94300
A58: Reuniones ejecutivas | B58: =AH58/$AH$10 -> 0 | C58: 0 | D58: 0 | E58: 0 | F58: 0 | G58: 0 | H58: 0 | I58: 0 | J58: 0 | K58: 0 | L58: 0 | M58: 0 | N58: 0 | O58: 0 | P58: 0 | Q58: 0 | R58: 0 | S58: 0 | T58: 0 | U58: 0 | V58: 0 | W58: 0 | X58: 0 | Y58: 0 | Z58: 0 | AA58: 0 | AB58: 0 | AC58: 0 | AD58: 0 | AE58: 0 | AF58: 0 | AG58: 0 | AH58: =SUM(C58:AG58) -> 0
A59: Certificados | B59: =AH59/$AH$10 -> 0 | C59: 0 | D59: 0 | E59: 0 | F59: 0 | G59: 0 | H59: 0 | I59: 0 | J59: 0 | K59: 0 | L59: 0 | M59: 0 | N59: 0 | O59: 0 | P59: 0 | Q59: 0 | R59: 0 | S59: 0 | T59: 0 | U59: 0 | V59: 0 | W59: 0 | X59: 0 | Y59: 0 | Z59: 0 | AA59: 0 | AB59: 0 | AC59: 0 | AD59: 0 | AE59: 0 | AF59: 0 | AG59: 0 | AH59: =SUM(C59:AG59) -> 0
A61: Marketing | B61: =AH61/$AH$10 -> 0.044620934 | C61: =sum(C62:C71) -> 0 | D61: =sum(D62:D71) -> 600000 | E61: =sum(E62:E71) -> 58245 | F61: =sum(F62:F71) -> 0 | G61: =sum(G62:G71) -> 108778 | H61: =sum(H62:H71) -> 47600 | I61: =sum(I62:I71) -> 0 | J61: =sum(J62:J71) -> 0 | ... AG61: =sum(AG62:AG71) -> 600000 | AH61: =SUM(AH62:AH71) -> 1753347
A62: Mercat | B62: =AH62/$AH$10 -> 0.0055352092 | C62: 0 | D62: 0 | E62: 0 | F62: 0 | G62: 108778 | H62: 0 | I62: 0 | J62: 0 | K62: 0 | L62: 0 | M62: 0 | N62: 0 | O62: 0 | P62: 0 | Q62: 0 | R62: 0 | S62: 0 | T62: 0 | U62: 0 | V62: 0 | W62: 0 | X62: 0 | Y62: 0 | Z62: 0 | AA62: 0 | AB62: 0 | AC62: 0 | AD62: 108724 | AE62: 0 | AF62: 0 | AG62: 0 | AH62: =SUM(C62:AG62) -> 217502
A63: Brevo | B63: =AH63/$AH$10 -> 0.0014822772 | C63: 0 | D63: 0 | E63: 58245 | F63: 0 | G63: 0 | H63: 0 | I63: 0 | J63: 0 | K63: 0 | L63: 0 | M63: 0 | N63: 0 | O63: 0 | P63: 0 | Q63: 0 | R63: 0 | S63: 0 | T63: 0 | U63: 0 | V63: 0 | W63: 0 | X63: 0 | Y63: 0 | Z63: 0 | AA63: 0 | AB63: 0 | AC63: 0 | AD63: 0 | AE63: 0 | AF63: 0 | AG63: 0 | AH63: =SUM(C63:AG63) -> 58245
A64: Fiweex | B64: =AH64/$AH$10 -> 0.0012113726 | C64: 0 | D64: 0 | E64: 0 | F64: 0 | G64: 0 | H64: 47600 | I64: 0 | J64: 0 | K64: 0 | L64: 0 | M64: 0 | N64: 0 | O64: 0 | P64: 0 | Q64: 0 | R64: 0 | S64: 0 | T64: 0 | U64: 0 | V64: 0 | W64: 0 | X64: 0 | Y64: 0 | Z64: 0 | AA64: 0 | AB64: 0 | AC64: 0 | AD64: 0 | AE64: 0 | AF64: 0 | AG64: 0 | AH64: =SUM(C64:AG64) -> 47600
A65: Fujifilm instax | B65: =AH65/$AH$10 -> 0.0030538805 | C65: 0 | D65: 0 | E65: 0 | F65: 0 | G65: 0 | H65: 0 | I65: 0 | J65: 0 | K65: 0 | L65: 0 | M65: 0 | N65: 0 | O65: 0 | P65: 0 | Q65: 0 | R65: 0 | S65: 0 | T65: 0 | U65: 120000 | V65: 0 | W65: 0 | X65: 0 | Y65: 0 | Z65: 0 | AA65: 0 | AB65: 0 | AC65: 0 | AD65: 0 | AE65: 0 | AF65: 0 | AG65: 0 | AH65: =SUM(C65:AG65) -> 120000
A66: Resos | B66: =AH66/$AH$10 -> 0.0027993904 | C66: 0 | D66: 0 | E66: 0 | F66: 0 | G66: 0 | H66: 0 | I66: 0 | J66: 0 | K66: 0 | L66: 0 | M66: 0 | N66: 0 | O66: 0 | P66: 0 | Q66: 0 | R66: 0 | S66: 0 | T66: 0 | U66: 0 | V66: 0 | W66: 0 | X66: 0 | Y66: 0 | Z66: 0 | AA66: 0 | AB66: 0 | AC66: 110000 | AD66: 0 | AE66: 0 | AF66: 0 | AG66: 0 | AH66: =SUM(C66:AG66) -> 110000
A67: HappyCow | B67: =AH67/$AH$10 -> 0 | C67: 0 | D67: 0 | E67: 0 | F67: 0 | G67: 0 | H67: 0 | I67: 0 | J67: 0 | K67: 0 | L67: 0 | M67: 0 | N67: 0 | O67: 0 | P67: 0 | Q67: 0 | R67: 0 | S67: 0 | T67: 0 | U67: 0 | V67: 0 | W67: 0 | X67: 0 | Y67: 0 | Z67: 0 | AA67: 0 | AB67: 0 | AC67: 0 | AD67: 0 | AE67: 0 | AF67: 0 | AG67: 0 | AH67: =SUM(C67:AG67) -> 0
A68: Meta Ads | B68: =AH68/$AH$10 -> 0 | C68: 0 | D68: 0 | E68: 0 | F68: 0 | G68: 0 | H68: 0 | I68: 0 | J68: 0 | K68: 0 | L68: 0 | M68: 0 | N68: 0 | O68: 0 | P68: 0 | Q68: 0 | R68: 0 | S68: 0 | T68: 0 | U68: 0 | V68: 0 | W68: 0 | X68: 0 | Y68: 0 | Z68: 0 | AA68: 0 | AB68: 0 | AC68: 0 | AD68: 0 | AE68: 0 | AF68: 0 | AG68: 0 | AH68: =SUM(C68:AG68) -> 0
A69: Influencers | B69: =AH69/$AH$10 -> 0 | C69: 0 | D69: 0 | E69: 0 | F69: 0 | G69: 0 | H69: 0 | I69: 0 | J69: 0 | K69: 0 | L69: 0 | M69: 0 | N69: 0 | O69: 0 | P69: 0 | Q69: 0 | R69: 0 | S69: 0 | T69: 0 | U69: 0 | V69: 0 | W69: 0 | X69: 0 | Y69: 0 | Z69: 0 | AA69: 0 | AB69: 0 | AC69: 0 | AD69: 0 | AE69: 0 | AF69: 0 | AG69: 0 | AH69: =SUM(C69:AG69) -> 0
A70: Chatfuel | B70: =AH70/$AH$10 -> 0 | C70: 0 | D70: 0 | E70: 0 | F70: 0 | G70: 0 | H70: 0 | I70: 0 | J70: 0 | K70: 0 | L70: 0 | M70: 0 | N70: 0 | O70: 0 | P70: 0 | Q70: 0 | R70: 0 | S70: 0 | T70: 0 | U70: 0 | V70: 0 | W70: 0 | X70: 0 | Y70: 0 | Z70: 0 | AA70: 0 | AB70: 0 | AC70: 0 | AD70: 0 | AE70: 0 | AF70: 0 | AG70: 0 | AH70: =SUM(C70:AG70) -> 0
A71: Community manager | B71: =AH71/$AH$10 -> 0.030538805 | C71: 0 | D71: 600000 | E71: 0 | F71: 0 | G71: 0 | H71: 0 | I71: 0 | J71: 0 | K71: 0 | L71: 0 | M71: 0 | N71: 0 | O71: 0 | P71: 0 | Q71: 0 | R71: 0 | S71: 0 | T71: 0 | U71: 0 | V71: 0 | W71: 0 | X71: 0 | Y71: 0 | Z71: 0 | AA71: 0 | AB71: 0 | AC71: 0 | AD71: 0 | AE71: 0 | AF71: 0 | AG71: 600000 | AH71: =SUM(C71:AG71) -> 1200000
A73: Inversiones activos | B73: =AH73/$AH$10 -> 0 | C73: =sum(C74:C76) -> 0 | D73: =sum(D74:D76) -> 0 | E73: =sum(E74:E76) -> 0 | F73: =sum(F74:F76) -> 0 | G73: =sum(G74:G76) -> 0 | H73: =sum(H74:H76) -> 0 | I73: =sum(I74:I76) -> 0 | J73: =sum(J74:J76) -> 0 | ... AH73: =sum(AH74:AH76) -> 0
A74: Nuevas maquinaria | B74: =AH74/$AH$10 -> 0 | C74: 0 | D74: 0 | E74: 0 | F74: 0 | G74: 0 | H74: 0 | I74: 0 | J74: 0 | K74: 0 | L74: 0 | M74: 0 | N74: 0 | O74: 0 | P74: 0 | Q74: 0 | R74: 0 | S74: 0 | T74: 0 | U74: 0 | V74: 0 | W74: 0 | X74: 0 | Y74: 0 | Z74: 0 | AA74: 0 | AB74: 0 | AC74: 0 | AD74: 0 | AE74: 0 | AF74: 0 | AG74: 0 | AH74: =SUM(C74:AG74) -> 0
A75: Nueva decoración y muebles | B75: =AH75/$AH$10 -> 0 | C75: 0 | D75: 0 | E75: 0 | F75: 0 | G75: 0 | H75: 0 | I75: 0 | J75: 0 | K75: 0 | L75: 0 | M75: 0 | N75: 0 | O75: 0 | P75: 0 | Q75: 0 | R75: 0 | S75: 0 | T75: 0 | U75: 0 | V75: 0 | W75: 0 | X75: 0 | Y75: 0 | Z75: 0 | AA75: 0 | AB75: 0 | AC75: 0 | AD75: 0 | AE75: 0 | AF75: 0 | AG75: 0 | AH75: =SUM(C75:AG75) -> 0
A76: Remodelaciones | B76: =AH76/$AH$10 -> 0 | C76: 0 | D76: 0 | E76: 0 | F76: 0 | G76: 0 | H76: 0 | I76: 0 | J76: 0 | K76: 0 | L76: 0 | M76: 0 | N76: 0 | O76: 0 | P76: 0 | Q76: 0 | R76: 0 | S76: 0 | T76: 0 | U76: 0 | V76: 0 | W76: 0 | X76: 0 | Y76: 0 | Z76: 0 | AA76: 0 | AB76: 0 | AC76: 0 | AD76: 0 | AE76: 0 | AF76: 0 | AG76: 0 | AH76: =SUM(C76:AG76) -> 0
A78: Dinero temporal | B78: =AH78/$AH$10 -> 0.16296855 | C78: =sum(C79:C82) -> 0 | D78: =sum(D79:D82) -> 300163 | E78: =sum(E79:E82) -> 0 | F78: =sum(F79:F82) -> 0 | G78: =sum(G79:G82) -> 2372852 | H78: =sum(H79:H82) -> 0 | I78: =sum(I79:I82) -> 0 | J78: =sum(J79:J82) -> 395162 | ... AH78: =sum(AH79:AH82) -> 6403730
A79: Delifast | B79: =AH79/$AH$10 -> 0.036764114 | C79: 0 | D79: 300163 | E79: 0 | F79: 0 | G79: 0 | H79: 0 | I79: 0 | J79: 395162 | K79: 0 | L79: 0 | M79: 0 | N79: 0 | O79: 0 | P79: 291414 | Q79: 0 | R79: 0 | S79: 0 | T79: 0 | U79: 0 | V79: 0 | W79: 0 | X79: 0 | Y79: 242454 | Z79: 0 | AA79: 0 | AB79: 0 | AC79: 215426 | AD79: 0 | AE79: 0 | AF79: 0 | AG79: 0 | AH79: =SUM(C79:AG79) -> 1444619
A80: Uber direct | B80: =AH80/$AH$10 -> 0 | C80: 0 | D80: 0 | E80: 0 | F80: 0 | G80: 0 | H80: 0 | I80: 0 | J80: 0 | K80: 0 | L80: 0 | M80: 0 | N80: 0 | O80: 0 | P80: 0 | Q80: 0 | R80: 0 | S80: 0 | T80: 0 | U80: 0 | V80: 0 | W80: 0 | X80: 0 | Y80: 0 | Z80: 0 | AA80: 0 | AB80: 0 | AC80: 0 | AD80: 0 | AE80: 0 | AF80: 0 | AG80: 0 | AH80: =SUM(C80:AG80) -> 0
A81: Monto delivery | B81: =AH81/$AH$10 -> 0.018408537 | C81: 0 | D81: 0 | E81: 0 | F81: 0 | G81: 144050 | H81: 0 | I81: 0 | J81: 0 | K81: 0 | L81: 0 | M81: 0 | N81: 0 | O81: 198600 | P81: 0 | Q81: 0 | R81: 0 | S81: 0 | T81: 0 | U81: 0 | V81: 189700 | W81: 0 | X81: 0 | Y81: 0 | Z81: 0 | AA81: 0 | AB81: 0 | AC81: 191000 | AD81: 0 | AE81: 0 | AF81: 0 | AG81: 0 | AH81: =SUM(C81:AG81) -> 723350
A82: Propina personal | B82: =AH82/$AH$10 -> 0.1077959 | C82: 0 | D82: 0 | E82: 0 | F82: 0 | G82: 2228802 | H82: 0 | I82: 0 | J82: 0 | K82: 0 | L82: 0 | M82: 0 | N82: 932066 | O82: 0 | P82: 0 | Q82: 0 | R82: 0 | S82: 0 | T82: 0 | U82: 607416 | V82: 0 | W82: 0 | X82: 0 | Y82: 0 | Z82: 0 | AA82: 0 | AB82: 467477 | AC82: 0 | AD82: 0 | AE82: 0 | AF82: 0 | AG82: 0 | AH82: =SUM(C82:AG82) -> 4235761
A84: RRHH | B84: =AH84/$AH$10 -> 0.25636901 | C84: =sum(C85:C93) -> 0 | D84: =sum(D85:D93) -> 56603 | E84: =sum(E85:E93) -> 0 | F84: =sum(F85:F93) -> 0 | G84: =sum(G85:G93) -> 52000 | H84: =sum(H85:H93) -> 0 | I84: =sum(I85:I93) -> 0 | J84: =sum(J85:J93) -> 0 | ... AG84: =sum(AG85:AG93) -> 5819496 | AH84: =SUM(AH85:AH93) -> 10073833
A85: Turnos feriados | B85: =AH85/$AH$10 -> 0 | C85: 0 | D85: 0 | E85: 0 | F85: 0 | G85: 0 | H85: 0 | I85: 0 | J85: 0 | K85: 0 | L85: 0 | M85: 0 | N85: 0 | O85: 0 | P85: 0 | Q85: 0 | R85: 0 | S85: 0 | T85: 0 | U85: 0 | V85: 0 | W85: 0 | X85: 0 | Y85: 0 | Z85: 0 | AA85: 0 | AB85: 0 | AC85: 0 | AD85: 0 | AE85: 0 | AF85: 0 | AG85: 0 | AH85: =SUM(C85:AG85) -> 0
A86: Sueldo personal | B86: =AH86/$AH$10 -> 0.19634685 | C86: 0 | D86: 0 | E86: 0 | F86: 0 | G86: =32000+20000 -> 52000 | H86: 0 | I86: 0 | J86: 0 | K86: 0 | L86: 485810 | M86: 0 | N86: 0 | O86: 48000 | P86: 0 | Q86: =270000+270000+250000+100000+150000+170000 -> 1210000 | R86: 0 | S86: 0 | T86: 0 | U86: 0 | V86: 40000 | W86: 0 | X86: 0 | Y86: 0 | Z86: 0 | AA86: 0 | AB86: 0 | AC86: =40000+20000 -> 60000 | AD86: 0 | AE86: 0 | AF86: 0 | AG86: =3591093+424396+294007+580000+1000000+530000-600000 -> 5819496 | AH86: =SUM(C86:AG86) -> 7715306
A87: Traslados personal | B87: =AH87/$AH$10 -> 0.0011204687 | C87: 0 | D87: 0 | E87: 0 | F87: 0 | G87: 0 | H87: 0 | I87: 0 | J87: 0 | K87: 0 | L87: 0 | M87: 0 | N87: 0 | O87: 9548 | P87: 0 | Q87: 8548 | R87: 0 | S87: 0 | T87: 0 | U87: 0 | V87: 0 | W87: 0 | X87: 10548 | Y87: 0 | Z87: 0 | AA87: 3799 | AB87: 0 | AC87: 0 | AD87: 0 | AE87: 11585 | AF87: 0 | AG87: 0 | AH87: =SUM(C87:AG87) -> 44028
A88: Turnos extras | B88: =AH88/$AH$10 -> 0.0025449004 | C88: 0 | D88: 0 | E88: 0 | F88: 0 | G88: 0 | H88: 0 | I88: 0 | J88: 0 | K88: 20000 | L88: 0 | M88: 0 | N88: 20000 | O88: 0 | P88: 0 | Q88: 0 | R88: 0 | S88: 0 | T88: 0 | U88: 20000 | V88: 0 | W88: 0 | X88: 0 | Y88: 0 | Z88: 0 | AA88: 20000 | AB88: 20000 | AC88: 0 | AD88: 0 | AE88: 0 | AF88: 0 | AG88: 0 | AH88: =SUM(C88:AG88) -> 100000
A89: Bonos | B89: =AH89/$AH$10 -> 0 | C89: 0 | D89: 0 | E89: 0 | F89: 0 | G89: 0 | H89: 0 | I89: 0 | J89: 0 | K89: 0 | L89: 0 | M89: 0 | N89: 0 | O89: 0 | P89: 0 | Q89: 0 | R89: 0 | S89: 0 | T89: 0 | U89: 0 | V89: 0 | W89: 0 | X89: 0 | Y89: 0 | Z89: 0 | AA89: 0 | AB89: 0 | AC89: 0 | AD89: 0 | AE89: 0 | AF89: 0 | AG89: 0 | AH89: =SUM(C89:AG89) -> 0
A90: Previred | B90: =AH90/$AH$10 -> 0.048939605 | C90: 0 | D90: 0 | E90: 0 | F90: 0 | G90: 0 | H90: 0 | I90: 0 | J90: 0 | K90: 0 | L90: 0 | M90: 1923046 | N90: 0 | O90: 0 | P90: 0 | Q90: 0 | R90: 0 | S90: 0 | T90: 0 | U90: 0 | V90: 0 | W90: 0 | X90: 0 | Y90: 0 | Z90: 0 | AA90: 0 | AB90: 0 | AC90: 0 | AD90: 0 | AE90: 0 | AF90: 0 | AG90: 0 | AH90: =SUM(C90:AG90) -> 1923046
A91: Uniforme pesonal | B91: =AH91/$AH$10 -> 0.0054677185 | C91: 0 | D91: 0 | E91: 0 | F91: 0 | G91: 0 | H91: 0 | I91: 0 | J91: 0 | K91: 0 | L91: 0 | M91: 0 | N91: 0 | O91: 0 | P91: 0 | Q91: 0 | R91: 0 | S91: 0 | T91: 0 | U91: 0 | V91: =74100+16990 -> 91090 | W91: 0 | X91: 123760 | Y91: 0 | Z91: 0 | AA91: 0 | AB91: 0 | AC91: 0 | AD91: 0 | AE91: 0 | AF91: 0 | AG91: 0 | AH91: =SUM(C91:AG91) -> 214850
A92: Finiquitos | B92: =AH92/$AH$10 -> 0.00144049 | C92: 0 | D92: 56603 | E92: 0 | F92: 0 | G92: 0 | H92: 0 | I92: 0 | J92: 0 | K92: 0 | L92: 0 | M92: 0 | N92: 0 | O92: 0 | P92: 0 | Q92: 0 | R92: 0 | S92: 0 | T92: 0 | U92: 0 | V92: 0 | W92: 0 | X92: 0 | Y92: 0 | Z92: 0 | AA92: 0 | AB92: 0 | AC92: 0 | AD92: 0 | AE92: 0 | AF92: 0 | AG92: 0 | AH92: =SUM(C92:AG92) -> 56603
A93: Recreación | B93: =AH93/$AH$10 -> 0.00050898008 | C93: 0 | D93: 0 | E93: 0 | F93: 0 | G93: 0 | H93: 0 | I93: 0 | J93: 0 | K93: 0 | L93: 0 | M93: 0 | N93: 0 | O93: 0 | P93: 0 | Q93: 0 | R93: 0 | S93: 0 | T93: 0 | U93: 0 | V93: 0 | W93: 0 | X93: 0 | Y93: 0 | Z93: 20000 | AA93: 0 | AB93: 0 | AC93: 0 | AD93: 0 | AE93: 0 | AF93: 0 | AG93: 0 | AH93: =SUM(C93:AG93) -> 20000
A95: Impuestos fiscales | B95: =AH95/$AH$10 -> 0.1197865 | C95: =SUM(C96:C97) -> 0 | D95: =SUM(D96:D97) -> 0 | E95: =SUM(E96:E97) -> 0 | F95: =SUM(F96:F97) -> 0 | G95: =SUM(G96:G97) -> 0 | H95: =SUM(H96:H97) -> 0 | I95: =SUM(I96:I97) -> 0 | J95: =SUM(J96:J97) -> 0 | ... AH95: =SUM(AH96:AH97) -> 4706923
A96: Impuesto sobre la renta | B96: =AH96/$AH$10 -> 0 | C96: 0 | D96: 0 | E96: 0 | F96: 0 | G96: 0 | H96: 0 | I96: 0 | J96: 0 | K96: 0 | L96: 0 | M96: 0 | N96: 0 | O96: 0 | P96: 0 | Q96: 0 | R96: 0 | S96: 0 | T96: 0 | U96: 0 | V96: 0 | W96: 0 | X96: 0 | Y96: 0 | Z96: 0 | AA96: 0 | AB96: 0 | AC96: 0 | AD96: 0 | AE96: 0 | AF96: 0 | AG96: 0 | AH96: =SUM(C96:AG96) -> 0
A97: IVA | B97: =AH97/$AH$10 -> 0.1197865 | C97: 0 | D97: 0 | E97: 0 | F97: 0 | G97: 0 | H97: 0 | I97: 0 | J97: 0 | K97: 0 | L97: 0 | M97: 0 | N97: 0 | O97: 0 | P97: 0 | Q97: 0 | R97: 0 | S97: 0 | T97: 0 | U97: 0 | V97: 4706923 | W97: 0 | X97: 0 | Y97: 0 | Z97: 0 | AA97: 0 | AB97: 0 | AC97: 0 | AD97: 0 | AE97: 0 | AF97: 0 | AG97: 0 | AH97: =SUM(C97:AG97) -> 4706923
A99: Amortizaciones | AH99: =AH100+AH101 -> 1781231
A100: Préstamo | C100: 0 | D100: 0 | E100: 0 | F100: 0 | G100: 0 | H100: 0 | I100: 0 | J100: 0 | K100: 0 | L100: 0 | M100: 0 | N100: 0 | O100: 0 | P100: 0 | Q100: 0 | R100: 0 | S100: 0 | T100: 0 | U100: 0 | V100: 0 | W100: 0 | X100: 0 | Y100: 0 | Z100: 0 | AA100: 0 | AB100: 1781231 | AC100: 0 | AD100: 0 | AE100: 0 | AF100: 0 | AG100: 0 | AH100: =sum(C100:AG100) -> 1781231
C101: 0 | D101: 0 | E101: 0 | F101: 0 | G101: 0 | H101: 0 | I101: 0 | J101: 0 | K101: 0 | L101: 0 | M101: 0 | N101: 0 | O101: 0 | P101: 0 | Q101: 0 | R101: 0 | S101: 0 | T101: 0 | U101: 0 | V101: 0 | W101: 0 | X101: 0 | Y101: 0 | Z101: 0 | AA101: 0 | AB101: 0 | AC101: 0 | AD101: 0 | AE101: 0 | AF101: 0 | AG101: 0 | AH101: =sum(C101:AG101) -> 0
A103: Total egresos conciliación | C103: =C95+C84+C78+C31+C73+C12+C100+C101 -> 0 | D103: =D95+D84+D78+D31+D73+D12+D100+D101 -> 2409332 | E103: =E95+E84+E78+E31+E73+E12+E100+E101 -> 127565 | F103: =F95+F84+F78+F31+F73+F12+F100+F101 -> 76500 | G103: =G95+G84+G78+G31+G73+G12+G100+G101 -> 3571990 | H103: =H95+H84+H78+H31+H73+H12+H100+H101 -> 1253195 | I103: =I95+I84+I78+I31+I73+I12+I100+I101 -> 2202840 | J103: =J95+J84+J78+J31+J73+J12+J100+J101 -> 598049 | ... AG103: =AG95+AG84+AG78+AG31+AG73+AG12+AG100+AG101 -> 6447396 | AH103: =sum(C103:AF103) -> 37583077
A104: Total egresos operativos | C104: =C95+C84+C31+C73+C12 -> 0 | D104: =D95+D84+D31+D73+D12 -> 2109169 | E104: =E95+E84+E31+E73+E12 -> 127565 | F104: =F95+F84+F31+F73+F12 -> 76500 | G104: =G95+G84+G31+G73+G12 -> 1199138 | H104: =H95+H84+H31+H73+H12 -> 1253195 | I104: =I95+I84+I31+I73+I12 -> 2202840 | J104: =J95+J84+J31+J73+J12 -> 202887 | ... AG104: =AG95+AG84+AG31+AG73+AG12 -> 6447396 | AH104: =sum(C104:AG104) -> 35845512
A106: Rentabilidad | B106: =AH106/$AH$10 -> 0.08776743 | C106: =C9-C104 -> 1749852 | D106: =D9-D104 -> -1995675 | E106: =E9-E104 -> 1368850 | F106: =F9-F104 -> 1968429 | G106: =G9-G104 -> 72089 | H106: =H9-H104 -> 109943 | I106: =I9-I104 -> -793346 | J106: =J9-J104 -> 1309626 | ... AG106: =AG9-AG104 -> -4463363 | AH106: =AH10-AH104 -> 3448757

Sheet Febrero
C1: 46054 | D1: 46055 | E1: 46056 | F1: 46057 | G1: 46058 | H1: 46059 | I1: 46060 | J1: 46061 | K1: 46062 | L1: 46063 | M1: 46064 | N1: 46065 | O1: 46066 | P1: 46067 | Q1: 46068 | R1: 46069 | S1: 46070 | T1: 46071 | U1: 46072 | V1: 46073 | W1: 46074 | X1: 46075 | Y1: 46076 | Z1: 46077 | AA1: 46078 | AB1: 46079 | AC1: 46080 | AD1: 46081 | AH1: Totales
A4: Ingresos
A5: Transbank | C5: =725798+92172+1865686+103529 -> 2787185 | D5: =43046+328722+919735 -> 1291503 | E5: =283773+6429+109208 -> 399410 | F5: =501293+497082+36768 -> 1035143 | G5: =31387+407140+852452 -> 1290979 | H5: =16740+115287+842050+298200+66318 -> 1338595 | I5: =690028+948920+54704+101038 -> 1794690 | J5: =1879480+356821+13044+151059 -> 2400404 | K5: =16077+50420+112995+1272072 -> 1451564 | L5: =174783+22155 -> 196938 | M5: =961673+486327+62775 -> 1510775 | N5: =510510+28598+700772+44441 -> 1284321 | O5: =1066903+420475+38063+22918 -> 1548359 | P5: =1841432+542189+77838+309234+89780 -> 2860473 | Q5: =1093084+145579+5112454+154447 -> 6505564 | R5: =96056+945234+83500 -> 1124790 | S5: 0 | T5: =1088481+675658+13850+87985+59900 -> 1925874 | U5: =495288+711135+28796+31844 -> 1267063 | V5: =309673+831214+58591+59287 -> 1258765 | W5: =855924+541260 -> 1397184 | X5: =1240654+437617+152554+17647 -> 1848472 | Y5: =61266+81011+1153557+112597 -> 1408431 | Z5: =131160+27102 -> 158262 | AA5: =531477+484645+209554 -> 1225676 | AB5: =34480+639559+99842+495326 -> 1269207 | AC5: =630927+23108+278392+86988+29346 -> 1048761 | AD5: =184976+448384+922398 -> 1555758 | AE5: 0 | AF5: 0 | AG5: 0 | AH5: =SUM(C5:AG5) -> 43184146
A6: Transferencias | C6: 28250 | D6: 0 | E6: =277400+44400 -> 321800 | F6: 35050 | G6: 0 | H6: 0 | I6: 16150 | J6: 0 | K6: 0 | L6: 5900 | M6: 0 | N6: 0 | O6: 0 | P6: 24900 | Q6: 0 | R6: 0 | S6: 0 | T6: 0 | U6: 0 | V6: 0 | W6: 21500 | X6: 36960 | Y6: 0 | Z6: 41950 | AA6: 0 | AB6: 34950 | AC6: 0 | AD6: 0 | AE6: 0 | AF6: 0 | AG6: 0 | AH6: =SUM(C6:AG6) -> 567410
A7: Efectivo | C7: 0 | D7: 0 | E7: 0 | F7: 0 | G7: 0 | H7: 0 | I7: 0 | J7: 0 | K7: 0 | L7: 0 | M7: 0 | N7: 0 | O7: 0 | P7: 0 | Q7: 0 | R7: 0 | S7: 0 | T7: 0 | U7: 250000 | V7: 0 | W7: 0 | X7: 0 | Y7: 0 | Z7: 0 | AA7: 0 | AB7: 0 | AC7: 0 | AD7: 0 | AE7: 0 | AF7: 0 | AG7: 0 | AH7: =SUM(C7:AG7) -> 250000
A8: Uber | C8: 0 | D8: 0 | E8: =148415+357124 -> 505539 | F8: 0 | G8: 0 | H8: 0 | I8: 0 | J8: 0 | K8: 0 | L8: =392255+29139 -> 421394 | M8: 0 | N8: 0 | O8: 0 | P8: 0 | Q8: 0 | R8: 0 | S8: =63918+437417 -> 501335 | T8: 0 | U8: 0 | V8: 0 | W8: 0 | X8: 0 | Y8: 0 | Z8: =205876+497780 -> 703656 | AA8: 0 | AB8: 0 | AC8: 0 | AD8: 0 | AE8: 0 | AF8: 0 | AG8: 0 | AH8: =SUM(C8:AG8) -> 2131924
A9: Total bruto | C9: =SUM(C5:C8) -> 2815435 | D9: =SUM(D5:D8) -> 1291503 | E9: =SUM(E5:E8) -> 1226749 | F9: =SUM(F5:F8) -> 1070193 | G9: =SUM(G5:G8) -> 1290979 | H9: =SUM(H5:H8) -> 1338595 | I9: =SUM(I5:I8) -> 1810840 | J9: =SUM(J5:J8) -> 2400404 | ... AH9: =SUM(AH5:AH8) -> 46133480
A10: Total neto | AH10: =AH9-AH81 -> 41645305
A12: Materia prima | B12: =AH12/$AH$10 -> 0.33242864 | C12: =sum(C13:C30) -> 827960 | D12: =sum(D13:D30) -> 170940 | E12: =sum(E13:E30) -> 746417 | F12: =sum(F13:F30) -> 156836 | G12: =sum(G13:G30) -> 843785 | H12: =sum(H13:H30) -> 225690 | I12: =sum(I13:I30) -> 176918 | J12: =sum(J13:J30) -> 31250 | ... AH12: =sum(AH13:AH30) -> 13844092
A13: MP | B13: =AH13/$AH$10 -> 0.042422645 | C13: 5770 | D13: 43410 | E13: =30000 -> 30000 | F13: 21890 | G13: 77926 | H13: 25770 | I13: =25000+46410+20700 -> 92110 | J13: =5470+25780 -> 31250 | K13: =77350+171360+24156 -> 272866 | L13: 19900 | M13: =153986+84000+42000 -> 279986 | N13: 13256 | O13: 49730 | P13: =50000+57820 -> 107820 | Q13: 103320 | R13: 0 | S13: 28020 | T13: =166600+9540 -> 176140 | U13: 0 | V13: 84000 | W13: 0 | X13: 0 | Y13: 0 | Z13: 0 | AA13: =10000+17650 -> 27650 | AB13: 0 | AC13: =120190+91200 -> 211390 | AD13: =56500+8000 -> 64500 | AE13: 0 | AF13: 0 | AG13: 0 | AH13: =SUM(C13:AG13) -> 1766704
A14: Arroz | B14: =AH14/$AH$10 -> 0.011838069 | C14: 0 | D14: 116000 | E14: 0 | F14: 0 | G14: 116000 | H14: 0 | I14: 0 | J14: 0 | K14: 0 | L14: 0 | M14: 0 | N14: 0 | O14: 0 | P14: 0 | Q14: 0 | R14: 116000 | S14: 0 | T14: 0 | U14: 0 | V14: 0 | W14: 0 | X14: 0 | Y14: 0 | Z14: 145000 | AA14: 0 | AB14: 0 | AC14: 0 | AD14: 0 | AE14: 0 | AF14: 0 | AG14: 0 | AH14: =SUM(C14:AG14) -> 493000
A15: Hod Food | B15: =AH15/$AH$10 -> 0.066829646 | C15: 0 | D15: 0 | E15: 625666 | F15: 0 | G15: 0 | H15: 0 | I15: 0 | J15: 0 | K15: 0 | L15: 558624 | M15: 0 | N15: 0 | O15: 0 | P15: 0 | Q15: 0 | R15: 0 | S15: 0 | T15: 0 | U15: 919138 | V15: 0 | W15: 0 | X15: 0 | Y15: 0 | Z15: 679713 | AA15: 0 | AB15: 0 | AC15: 0 | AD15: 0 | AE15: 0 | AF15: 0 | AG15: 0 | AH15: =SUM(C15:AG15) -> 2783141
A16: Seitan | B16: =AH16/$AH$10 -> 0 | C16: 0 | D16: 0 | E16: 0 | F16: 0 | G16: 0 | H16: 0 | I16: 0 | J16: 0 | K16: 0 | L16: 0 | M16: 0 | N16: 0 | O16: 0 | P16: 0 | Q16: 0 | R16: 0 | S16: 0 | T16: 0 | U16: 0 | V16: 0 | W16: 0 | X16: 0 | Y16: 0 | Z16: 0 | AA16: 0 | AB16: 0 | AC16: 0 | AD16: 0 | AE16: 0 | AF16: 0 | AG16: 0 | AH16: =SUM(C16:AG16) -> 0
A17: Palta | B17: =AH17/$AH$10 -> 0.059100948 | C17: 0 | D17: 0 | E17: 0 | F17: 0 | G17: 649859 | H17: 0 | I17: 0 | J17: 0 | K17: 0 | L17: 0 | M17: 0 | N17: 0 | O17: 0 | P17: 0 | Q17: 0 | R17: 0 | S17: 0 | T17: 639625 | U17: 0 | V17: 0 | W17: 0 | X17: 0 | Y17: 0 | Z17: 747082 | AA17: 0 | AB17: 0 | AC17: 0 | AD17: 424711 | AE17: 0 | AF17: 0 | AG17: 0 | AH17: =SUM(C17:AG17) -> 2461277
A18: Carivo | B18: =AH18/$AH$10 -> 0.065863007 | C18: 814620 | D18: 0 | E18: 0 | F18: 0 | G18: 0 | H18: 0 | I18: 0 | J18: 0 | K18: 0 | L18: 647690 | M18: 0 | N18: 0 | O18: 0 | P18: 0 | Q18: 0 | R18: 0 | S18: 784975 | T18: 0 | U18: 0 | V18: 0 | W18: 0 | X18: 0 | Y18: 0 | Z18: 376600 | AA18: 0 | AB18: 0 | AC18: 0 | AD18: 119000 | AE18: 0 | AF18: 0 | AG18: 0 | AH18: =SUM(C18:AG18) -> 2742885
A19: Shen | B19: =AH19/$AH$10 -> 0.01062977 | C19: 0 | D19: 0 | E19: 0 | F19: 0 | G19: 0 | H19: 199920 | I19: 0 | J19: 0 | K19: 0 | L19: 0 | M19: 0 | N19: 0 | O19: 121380 | P19: 0 | Q19: 0 | R19: 0 | S19: 0 | T19: 0 | U19: 0 | V19: 0 | W19: 0 | X19: 0 | Y19: 0 | Z19: 121380 | AA19: 0 | AB19: 0 | AC19: 0 | AD19: 0 | AE19: 0 | AF19: 0 | AG19: 0 | AH19: =SUM(C19:AG19) -> 442680
A20: Mozzen | B20: =AH20/$AH$10 -> 0 | C20: 0 | D20: 0 | E20: 0 | F20: 0 | G20: 0 | H20: 0 | I20: 0 | J20: 0 | K20: 0 | L20: 0 | M20: 0 | N20: 0 | O20: 0 | P20: 0 | Q20: 0 | R20: 0 | S20: 0 | T20: 0 | U20: 0 | V20: 0 | W20: 0 | X20: 0 | Y20: 0 | Z20: 0 | AA20: 0 | AB20: 0 | AC20: 0 | AD20: 0 | AE20: 0 | AF20: 0 | AG20: 0 | AH20: =SUM(C20:AG20) -> 0
A21: Café y Té | B21: =AH21/$AH$10 -> 0 | C21: 0 | D21: 0 | E21: 0 | F21: 0 | G21: 0 | H21: 0 | I21: 0 | J21: 0 | K21: 0 | L21: 0 | M21: 0 | N21: 0 | O21: 0 | P21: 0 | Q21: 0 | R21: 0 | S21: 0 | T21: 0 | U21: 0 | V21: 0 | W21: 0 | X21: 0 | Y21: 0 | Z21: 0 | AA21: 0 | AB21: 0 | AC21: 0 | AD21: 0 | AE21: 0 | AF21: 0 | AG21: 0 | AH21: =SUM(C21:AG21) -> 0
A22: Leche de soya | B22: =AH22/$AH$10 -> 0.0060749705 | C22: 0 | D22: 0 | E22: 0 | F22: 134946 | G22: 0 | H22: 0 | I22: 0 | J22: 0 | K22: 0 | L22: 0 | M22: 0 | N22: 0 | O22: 0 | P22: 0 | Q22: 0 | R22: 0 | S22: 0 | T22: 0 | U22: 0 | V22: 0 | W22: 0 | X22: 0 | Y22: 0 | Z22: 118048 | AA22: 0 | AB22: 0 | AC22: 0 | AD22: 0 | AE22: 0 | AF22: 0 | AG22: 0 | AH22: =SUM(C22:AG22) -> 252994
A23: Bebestibles | B23: =AH23/$AH$10 -> 0.0063777417 | C23: 0 | D23: 0 | E23: 0 | F23: 0 | G23: 0 | H23: 0 | I23: 0 | J23: 0 | K23: 23000 | L23: 56089 | M23: 0 | N23: 0 | O23: 0 | P23: 0 | Q23: 0 | R23: 16501 | S23: 0 | T23: 0 | U23: 0 | V23: 0 | W23: 0 | X23: 0 | Y23: =23205+127307 -> 150512 | Z23: 19501 | AA23: 0 | AB23: 0 | AC23: 0 | AD23: 0 | AE23: 0 | AF23: 0 | AG23: 0 | AH23: =SUM(C23:AG23) -> 265603
A24: Brugga | B24: =AH24/$AH$10 -> 0.011872767 | C24: 0 | D24: 0 | E24: 0 | F24: 0 | G24: 0 | H24: 0 | I24: 0 | J24: 0 | K24: 0 | L24: 157080 | M24: 0 | N24: 157080 | O24: 0 | P24: 0 | Q24: 0 | R24: 0 | S24: 23205 | T24: 0 | U24: 0 | V24: 0 | W24: 0 | X24: 0 | Y24: 0 | Z24: 0 | AA24: 157080 | AB24: 0 | AC24: 0 | AD24: 0 | AE24: 0 | AF24: 0 | AG24: 0 | AH24: =SUM(C24:AG24) -> 494445
A25: Colación | B25: =AH25/$AH$10 -> 0.0079341957 | C25: 7570 | D25: 11530 | E25: 90751 | F25: 0 | G25: 0 | H25: 0 | I25: 84808 | J25: 0 | K25: 0 | L25: 0 | M25: 0 | N25: 0 | O25: 0 | P25: 0 | Q25: =37318 -> 37318 | R25: 0 | S25: 37160 | T25: 0 | U25: 0 | V25: 0 | W25: 0 | X25: 0 | Y25: 15180 | Z25: 0 | AA25: 0 | AB25: 46105 | AC25: 0 | AD25: 0 | AE25: 0 | AF25: 0 | AG25: 0 | AH25: =SUM(C25:AG25) -> 330422
A26: Empaques y desechables | B26: =AH26/$AH$10 -> 0.0094199334 | C26: 0 | D26: 0 | E26: 0 | F26: 0 | G26: 0 | H26: 0 | I26: 0 | J26: 0 | K26: 0 | L26: 160168 | M26: 0 | N26: 0 | O26: 0 | P26: 0 | Q26: 0 | R26: 0 | S26: 0 | T26: 160168 | U26: 0 | V26: 0 | W26: 0 | X26: 0 | Y26: 71960 | Z26: 0 | AA26: 0 | AB26: 0 | AC26: 0 | AD26: 0 | AE26: 0 | AF26: 0 | AG26: 0 | AH26: =SUM(C26:AG26) -> 392296
A27: Soyas sachet | B27: =AH27/$AH$10 -> 0.0043220718 | C27: 0 | D27: 0 | E27: 0 | F27: 0 | G27: 0 | H27: 0 | I27: 0 | J27: 0 | K27: 89997 | L27: 0 | M27: 0 | N27: 0 | O27: 0 | P27: 0 | Q27: 0 | R27: 0 | S27: 0 | T27: 0 | U27: 0 | V27: 0 | W27: 0 | X27: 0 | Y27: 0 | Z27: 89997 | AA27: 0 | AB27: 0 | AC27: 0 | AD27: 0 | AE27: 0 | AF27: 0 | AG27: 0 | AH27: =SUM(C27:AG27) -> 179994
A28: Servilletas | B28: =AH28/$AH$10 -> 0.0079551825 | C28: 0 | D28: 0 | E28: 0 | F28: 0 | G28: 0 | H28: 0 | I28: 0 | J28: 0 | K28: 0 | L28: 0 | M28: 248472 | N28: 0 | O28: 0 | P28: 0 | Q28: 0 | R28: 0 | S28: 0 | T28: 0 | U28: 0 | V28: 82824 | W28: 0 | X28: 0 | Y28: 0 | Z28: 0 | AA28: 0 | AB28: 0 | AC28: 0 | AD28: 0 | AE28: 0 | AF28: 0 | AG28: 0 | AH28: =SUM(C28:AG28) -> 331296
A29: Limpieza e higiene | B29: =AH29/$AH$10 -> 0 | C29: 0 | D29: 0 | E29: 0 | F29: 0 | G29: 0 | H29: 0 | I29: 0 | J29: 0 | K29: 0 | L29: 0 | M29: 0 | N29: 0 | O29: 0 | P29: 0 | Q29: 0 | R29: 0 | S29: 0 | T29: 0 | U29: 0 | V29: 0 | W29: 0 | X29: 0 | Y29: 0 | Z29: 0 | AA29: 0 | AB29: 0 | AC29: 0 | AD29: 0 | AE29: 0 | AF29: 0 | AG29: 0 | AH29: =SUM(C29:AG29) -> 0
A30: Postres | B30: =AH30/$AH$10 -> 0.02178769 | C30: 0 | D30: 0 | E30: 0 | F30: 0 | G30: 0 | H30: 0 | I30: 0 | J30: 0 | K30: 77200 | L30: 76715 | M30: 177610 | N30: 0 | O30: 0 | P30: 0 | Q30: 0 | R30: 89400 | S30: 148812 | T30: 0 | U30: 0 | V30: 96400 | W30: 0 | X30: 0 | Y30: 0 | Z30: 0 | AA30: 0 | AB30: 0 | AC30: 0 | AD30: 241218 | AE30: 0 | AF30: 0 | AG30: 0 | AH30: =SUM(C30:AG30) -> 907355
A32: Gastos FV | B32: =AH32/$AH$10 -> 0.20759041 | C32: =sum(C33+C53+C63) -> 0 | D32: =sum(D33+D53+D63) -> 0 | E32: =sum(E33+E53+E63) -> 58245 | F32: =sum(F33+F53+F63) -> 0 | G32: =sum(G33+G53+G63) -> 13000 | H32: =sum(H33+H53+H63) -> 2385298 | I32: =sum(I33+I53+I63) -> 0 | J32: =sum(J33+J53+J63) -> 345576 | ... AH32: =sum(AH33+AH53+AH63) -> 8645166
A33: Operaciones | B33: =AH33/$AH$10 -> 0.17458218 | C33: =sum(C34:C52) -> 0 | D33: =sum(D34:D52) -> 0 | E33: =sum(E34:E52) -> 0 | F33: =sum(F34:F52) -> 0 | G33: =sum(G34:G52) -> 0 | H33: =sum(H34:H52) -> 2381361 | I33: =sum(I34:I52) -> 0 | J33: =sum(J34:J52) -> 234575 | ... AH33: =sum(AH34:AH52) -> 7270528
A34: Electricidad | B34: =AH34/$AH$10 -> 0.004667561 | C34: 0 | D34: 0 | E34: 0 | F34: 0 | G34: 0 | H34: 0 | I34: 0 | J34: 0 | K34: 0 | L34: 0 | M34: 0 | N34: 0 | O34: 0 | P34: 0 | Q34: 0 | R34: 0 | S34: 194382 | T34: 0 | U34: 0 | V34: 0 | W34: 0 | X34: 0 | Y34: 0 | Z34: 0 | AA34: 0 | AB34: 0 | AC34: 0 | AD34: 0 | AE34: 0 | AF34: 0 | AG34: 0 | AH34: =SUM(C34:AG34) -> 194382
A35: Agua | B35: =AH35/$AH$10 -> 0.0015922563 | C35: 0 | D35: 0 | E35: 0 | F35: 0 | G35: 0 | H35: 0 | I35: 0 | J35: 0 | K35: 0 | L35: 0 | M35: 0 | N35: 0 | O35: 0 | P35: 0 | Q35: 0 | R35: 0 | S35: 66310 | T35: 0 | U35: 0 | V35: 0 | W35: 0 | X35: 0 | Y35: 0 | Z35: 0 | AA35: 0 | AB35: 0 | AC35: 0 | AD35: 0 | AE35: 0 | AF35: 0 | AG35: 0 | AH35: =SUM(C35:AG35) -> 66310
A36: Gas | B36: =AH36/$AH$10 -> 0.008989993 | C36: 0 | D36: 0 | E36: 0 | F36: 0 | G36: 0 | H36: 0 | I36: 0 | J36: 0 | K36: 0 | L36: 0 | M36: 0 | N36: 0 | O36: 0 | P36: 0 | Q36: 0 | R36: 0 | S36: 374391 | T36: 0 | U36: 0 | V36: 0 | W36: 0 | X36: 0 | Y36: 0 | Z36: 0 | AA36: 0 | AB36: 0 | AC36: 0 | AD36: 0 | AE36: 0 | AF36: 0 | AG36: 0 | AH36: =SUM(C36:AG36) -> 374391
A37: Restaurantpe | B37: =AH37/$AH$10 -> 0 | C37: 0 | D37: 0 | E37: 0 | F37: 0 | G37: 0 | H37: 0 | I37: 0 | J37: 0 | K37: 0 | L37: 0 | M37: 0 | N37: 0 | O37: 0 | P37: 0 | Q37: 0 | R37: 0 | S37: 0 | T37: 0 | U37: 0 | V37: 0 | W37: 0 | X37: 0 | Y37: 0 | Z37: 0 | AA37: 0 | AB37: 0 | AC37: 0 | AD37: 0 | AE37: 0 | AF37: 0 | AG37: 0 | AH37: =SUM(C37:AG37) -> 0
A38: Toteat | B38: =AH38/$AH$10 -> 0.0056326878 | C38: 0 | D38: 0 | E38: 0 | F38: 0 | G38: 0 | H38: 0 | I38: 0 | J38: =136614+97961 -> 234575 | K38: 0 | L38: 0 | M38: 0 | N38: 0 | O38: 0 | P38: 0 | Q38: 0 | R38: 0 | S38: 0 | T38: 0 | U38: 0 | V38: 0 | W38: 0 | X38: 0 | Y38: 0 | Z38: 0 | AA38: 0 | AB38: 0 | AC38: 0 | AD38: 0 | AE38: 0 | AF38: 0 | AG38: 0 | AH38: =SUM(C38:AG38) -> 234575
A39: Alarma | B39: =AH39/$AH$10 -> 0.0011458675 | C39: 0 | D39: 0 | E39: 0 | F39: 0 | G39: 0 | H39: 0 | I39: 0 | J39: 0 | K39: 47720 | L39: 0 | M39: 0 | N39: 0 | O39: 0 | P39: 0 | Q39: 0 | R39: 0 | S39: 0 | T39: 0 | U39: 0 | V39: 0 | W39: 0 | X39: 0 | Y39: 0 | Z39: 0 | AA39: 0 | AB39: 0 | AC39: 0 | AD39: 0 | AE39: 0 | AF39: 0 | AG39: 0 | AH39: =SUM(C39:AG39) -> 47720
A40: VTR | B40: =AH40/$AH$10 -> 0.00062724958 | C40: 0 | D40: 0 | E40: 0 | F40: 0 | G40: 0 | H40: 0 | I40: 0 | J40: 0 | K40: 0 | L40: 0 | M40: 0 | N40: 0 | O40: 11811 | P40: 0 | Q40: 0 | R40: 0 | S40: 14311 | T40: 0 | U40: 0 | V40: 0 | W40: 0 | X40: 0 | Y40: 0 | Z40: 0 | AA40: 0 | AB40: 0 | AC40: 0 | AD40: 0 | AE40: 0 | AF40: 0 | AG40: 0 | AH40: =SUM(C40:AG40) -> 26122
A41: Bodega | B41: =AH41/$AH$10 -> 0.0072036932 | C41: 0 | D41: 0 | E41: 0 | F41: 0 | G41: 0 | H41: 300000 | I41: 0 | J41: 0 | K41: 0 | L41: 0 | M41: 0 | N41: 0 | O41: 0 | P41: 0 | Q41: 0 | R41: 0 | S41: 0 | T41: 0 | U41: 0 | V41: 0 | W41: 0 | X41: 0 | Y41: 0 | Z41: 0 | AA41: 0 | AB41: 0 | AC41: 0 | AD41: 0 | AE41: 0 | AF41: 0 | AG41: 0 | AH41: =SUM(C41:AG41) -> 300000
A42: Arriendo | B42: =AH42/$AH$10 -> 0.043855148 | C42: 0 | D42: 0 | E42: 0 | F42: 0 | G42: 0 | H42: 1826361 | I42: 0 | J42: 0 | K42: 0 | L42: 0 | M42: 0 | N42: 0 | O42: 0 | P42: 0 | Q42: 0 | R42: 0 | S42: 0 | T42: 0 | U42: 0 | V42: 0 | W42: 0 | X42: 0 | Y42: 0 | Z42: 0 | AA42: 0 | AB42: 0 | AC42: 0 | AD42: 0 | AE42: 0 | AF42: 0 | AG42: 0 | AH42: =SUM(C42:AG42) -> 1826361
A43: Funmigacion | B43: =AH43/$AH$10 -> 0.0028298508 | C43: 0 | D43: 0 | E43: 0 | F43: 0 | G43: 0 | H43: 0 | I43: 0 | J43: 0 | K43: 0 | L43: 0 | M43: 0 | N43: 0 | O43: 0 | P43: 0 | Q43: 0 | R43: 0 | S43: 0 | T43: 0 | U43: 0 | V43: 117850 | W43: 0 | X43: 0 | Y43: 0 | Z43: 0 | AA43: 0 | AB43: 0 | AC43: 0 | AD43: 0 | AE43: 0 | AF43: 0 | AG43: 0 | AH43: =SUM(C43:AG43) -> 117850
A44: Aroclean | B44: =AH44/$AH$10 -> 0.0033135068 | C44: 0 | D44: 0 | E44: 0 | F44: 0 | G44: 0 | H44: 0 | I44: 0 | J44: 0 | K44: 68996 | L44: 0 | M44: 0 | N44: 0 | O44: 0 | P44: 0 | Q44: 0 | R44: 0 | S44: 0 | T44: 0 | U44: 0 | V44: 68996 | W44: 0 | X44: 0 | Y44: 0 | Z44: 0 | AA44: 0 | AB44: 0 | AC44: 0 | AD44: 0 | AH44: =SUM(C44:AG44) -> 137992
A45: Reposición de vasos | B45: =AH45/$AH$10 -> 0.0043311005 | C45: 0 | D45: 0 | E45: 0 | F45: 0 | G45: 0 | H45: 0 | I45: 0 | J45: 0 | K45: 0 | L45: 0 | M45: 0 | N45: 165910 | O45: 0 | P45: 14460 | Q45: 0 | R45: 0 | S45: 0 | T45: 0 | U45: 0 | V45: 0 | W45: 0 | X45: 0 | Y45: 0 | Z45: 0 | AA45: 0 | AB45: 0 | AC45: 0 | AD45: 0 | AE45: 0 | AF45: 0 | AG45: 0 | AH45: =SUM(C45:AG45) -> 180370
A46: Reposición Articulos cocina | B46: =AH46/$AH$10 -> 0.0074210046 | C46: 0 | D46: 0 | E46: 0 | F46: 0 | G46: 0 | H46: 0 | I46: 0 | J46: 0 | K46: 0 | L46: 30990 | M46: 0 | N46: 199070 | O46: 39000 | P46: 39990 | Q46: 0 | R46: 0 | S46: 0 | T46: 0 | U46: 0 | V46: 0 | W46: 0 | X46: 0 | Y46: 0 | Z46: 0 | AA46: 0 | AB46: 0 | AC46: 0 | AD46: 0 | AE46: 0 | AF46: 0 | AG46: 0 | AH46: =SUM(C46:AG46) -> 309050
A47: Reposición articulos salón | B47: =AH47/$AH$10 -> 0.004178046 | C47: 0 | D47: 0 | E47: 0 | F47: 0 | G47: 0 | H47: 0 | I47: 0 | J47: 0 | K47: 68996 | L47: 0 | M47: 0 | N47: 0 | O47: 0 | P47: 105000 | Q47: 0 | R47: 0 | S47: 0 | T47: 0 | U47: 0 | V47: 0 | W47: 0 | X47: 0 | Y47: 0 | Z47: 0 | AA47: 0 | AB47: 0 | AC47: 0 | AD47: 0 | AE47: 0 | AF47: 0 | AG47: 0 | AH47: =SUM(C47:AG47) -> 173996
A48: Reparaciones mano de obra | B48: =AH48/$AH$10 -> 0.0046824006 | C48: 0 | D48: 0 | E48: 0 | F48: 0 | G48: 0 | H48: =35000+140000 -> 175000 | I48: 0 | J48: 0 | K48: 0 | L48: 0 | M48: 0 | N48: 0 | O48: 0 | P48: 0 | Q48: 0 | R48: 0 | S48: 0 | T48: 0 | U48: 0 | V48: 0 | W48: 0 | X48: 0 | Y48: 20000 | Z48: 0 | AA48: 0 | AB48: 0 | AC48: 0 | AD48: 0 | AE48: 0 | AF48: 0 | AG48: 0 | AH48: =SUM(C48:AG48) -> 195000
A49: Reparaciones articulos | B49: =AH49/$AH$10 -> 0.0034882684 | C49: 0 | D49: 0 | E49: 0 | F49: 0 | G49: 0 | H49: 80000 | I49: 0 | J49: 0 | K49: 0 | L49: 11790 | M49: 11790 | N49: 0 | O49: 0 | P49: 0 | Q49: 0 | R49: 0 | S49: 0 | T49: 0 | U49: 0 | V49: 0 | W49: 0 | X49: 0 | Y49: 29900 | Z49: 11790 | AA49: 0 | AB49: 0 | AC49: 0 | AD49: 0 | AE49: 0 | AF49: 0 | AG49: 0 | AH49: =SUM(C49:AG49) -> 145270
A50: Reparaciones maquinaria | B50: =AH50/$AH$10 -> 0 | C50: 0 | D50: 0 | E50: 0 | F50: 0 | G50: 0 | H50: 0 | I50: 0 | J50: 0 | K50: 0 | L50: 0 | M50: 0 | N50: 0 | O50: 0 | P50: 0 | Q50: 0 | R50: 0 | S50: 0 | T50: 0 | U50: 0 | V50: 0 | W50: 0 | X50: 0 | Y50: 0 | Z50: 0 | AA50: 0 | AB50: 0 | AC50: 0 | AD50: 0 | AE50: 0 | AF50: 0 | AG50: 0 | AH50: =SUM(C50:AG50) -> 0
A51: Asesoria | B51: =AH51/$AH$10 -> 0 | C51: 0 | D51: 0 | E51: 0 | F51: 0 | G51: 0 | H51: 0 | I51: 0 | J51: 0 | K51: 0 | L51: 0 | M51: 0 | N51: 0 | O51: 0 | P51: 0 | Q51: 0 | R51: 0 | S51: 0 | T51: 0 | U51: 0 | V51: 0 | W51: 0 | X51: 0 | Y51: 0 | Z51: 0 | AA51: 0 | AB51: 0 | AC51: 0 | AD51: 0 | AE51: 0 | AF51: 0 | AG51: 0 | AH51: =SUM(C51:AG51) -> 0
A52: Fee | B52: =AH52/$AH$10 -> 0.070623543 | C52: 0 | D52: 0 | E52: 0 | F52: 0 | G52: 0 | H52: 0 | I52: 0 | J52: 0 | K52: 0 | L52: 0 | M52: 0 | N52: 2941139 | O52: 0 | P52: 0 | Q52: 0 | R52: 0 | S52: 0 | T52: 0 | U52: 0 | V52: 0 | W52: 0 | X52: 0 | Y52: 0 | Z52: 0 | AA52: 0 | AB52: 0 | AC52: 0 | AD52: 0 | AE52: 0 | AF52: 0 | AG52: 0 | AH52: =SUM(C52:AG52) -> 2941139
A53: Administración y finanzas | B53: =AH53/$AH$10 -> 0.0056265166 | C53: =sum(C54:C61) -> 0 | D53: =sum(D54:D61) -> 0 | E53: =sum(E54:E61) -> 0 | F53: =sum(F54:F61) -> 0 | G53: =sum(G54:G61) -> 13000 | H53: =sum(H54:H61) -> 3937 | I53: =sum(I54:I61) -> 0 | J53: =sum(J54:J61) -> 111001 | ... AE53: =sum(AE54:AE61) -> 0 | AF53: =SUM(AF54:AF61) -> 0 | AG53: =sum(AG54:AG61) -> 0 | AH53: =SUM(AH54:AH61) -> 234318
A54: Comisiones cuenta corriente | B54: =AH54/$AH$10 -> 9.4536467e-05 | C54: 0 | D54: 0 | E54: 0 | F54: 0 | G54: 0 | H54: 3937 | I54: 0 | J54: 0 | K54: 0 | L54: 0 | M54: 0 | N54: 0 | O54: 0 | P54: 0 | Q54: 0 | R54: 0 | S54: 0 | T54: 0 | U54: 0 | V54: 0 | W54: 0 | X54: 0 | Y54: 0 | Z54: 0 | AA54: 0 | AB54: 0 | AC54: 0 | AD54: 0 | AE54: 0 | AF54: 0 | AG54: 0 | AH54: =SUM(C54:AG54) -> 3937
A55: Contadora | B55: =AH55/$AH$10 -> 0.0014407386 | C55: 0 | D55: 0 | E55: 0 | F55: 0 | G55: 0 | H55: 0 | I55: 0 | J55: 0 | K55: 0 | L55: 0 | M55: 0 | N55: 0 | O55: 0 | P55: 0 | Q55: 0 | R55: 0 | S55: 0 | T55: 0 | U55: 0 | V55: 0 | W55: 60000 | X55: 0 | Y55: 0 | Z55: 0 | AA55: 0 | AB55: 0 | AC55: 0 | AD55: 0 | AE55: 0 | AF55: 0 | AG55: 0 | AH55: =SUM(C55:AG55) -> 60000
A56: Patentes comerciales | B56: =AH56/$AH$10 -> 0 | C56: 0 | D56: 0 | E56: 0 | F56: 0 | G56: 0 | H56: 0 | I56: 0 | J56: 0 | K56: 0 | L56: 0 | M56: 0 | N56: 0 | O56: 0 | P56: 0 | Q56: 0 | R56: 0 | S56: 0 | T56: 0 | U56: 0 | V56: 0 | W56: 0 | X56: 0 | Y56: 0 | Z56: 0 | AA56: 0 | AB56: 0 | AC56: 0 | AD56: 0 | AE56: 0 | AF56: 0 | AG56: 0 | AH56: =SUM(C56:AG56) -> 0
A57: Insumos de oficina | B57: =AH57/$AH$10 -> 0.00073429646 | C57: 0 | D57: 0 | E57: 0 | F57: 0 | G57: 13000 | H57: 0 | I57: 0 | J57: 0 | K57: 0 | L57: 0 | M57: 10880 | N57: 0 | O57: 0 | P57: 0 | Q57: 0 | R57: 0 | S57: 0 | T57: 0 | U57: 0 | V57: 0 | W57: 0 | X57: 0 | Y57: 0 | Z57: 0 | AA57: 2200 | AB57: 4500 | AC57: 0 | AD57: 0 | AE57: 0 | AF57: 0 | AG57: 0 | AH57: =SUM(C57:AG57) -> 30580
A58: Wasabil | B58: =AH58/$AH$10 -> 0 | C58: 0 | D58: 0 | E58: 0 | F58: 0 | G58: 0 | H58: 0 | I58: 0 | J58: 0 | K58: 0 | L58: 0 | M58: 0 | N58: 0 | O58: 0 | P58: 0 | Q58: 0 | R58: 0 | S58: 0 | T58: 0 | U58: 0 | V58: 0 | W58: 0 | X58: 0 | Y58: 0 | Z58: 0 | AA58: 0 | AB58: 0 | AC58: 0 | AD58: 0 | AE58: 0 | AF58: 0 | AG58: 0 | AH58: =SUM(C58:AG58) -> 0
A59: Devolución clientes | B59: =AH59/$AH$10 -> 0.003356945 | C59: 0 | D59: 0 | E59: 0 | F59: 0 | G59: 0 | H59: 0 | I59: 0 | J59: =50601+30100+30300 -> 111001 | K59: 0 | L59: 0 | M59: 0 | N59: 0 | O59: 0 | P59: 0 | Q59: 0 | R59: 28800 | S59: 0 | T59: 0 | U59: 0 | V59: 0 | W59: 0 | X59: 0 | Y59: 0 | Z59: 0 | AA59: 0 | AB59: 0 | AC59: 0 | AD59: 0 | AE59: 0 | AF59: 0 | AG59: 0 | AH59: =SUM(C59:AG59) -> 139801
A60: Reuniones ejecutivas | B60: =AH60/$AH$10 -> 0 | C60: 0 | D60: 0 | E60: 0 | F60: 0 | G60: 0 | H60: 0 | I60: 0 | J60: 0 | K60: 0 | L60: 0 | M60: 0 | N60: 0 | O60: 0 | P60: 0 | Q60: 0 | R60: 0 | S60: 0 | T60: 0 | U60: 0 | V60: 0 | W60: 0 | X60: 0 | Y60: 0 | Z60: 0 | AA60: 0 | AB60: 0 | AC60: 0 | AD60: 0 | AE60: 0 | AF60: 0 | AG60: 0 | AH60: =SUM(C60:AG60) -> 0
A61: Certificados | B61: =AH61/$AH$10 -> 0 | C61: 0 | D61: 0 | E61: 0 | F61: 0 | G61: 0 | H61: 0 | I61: 0 | J61: 0 | K61: 0 | L61: 0 | M61: 0 | N61: 0 | O61: 0 | P61: 0 | Q61: 0 | R61: 0 | S61: 0 | T61: 0 | U61: 0 | V61: 0 | W61: 0 | X61: 0 | Y61: 0 | Z61: 0 | AA61: 0 | AB61: 0 | AC61: 0 | AD61: 0 | AE61: 0 | AF61: 0 | AG61: 0 | AH61: =SUM(C61:AG61) -> 0
A63: Marketing | B63: =AH63/$AH$10 -> 0.027381718 | C63: =sum(C64:C73) -> 0 | D63: =sum(D64:D73) -> 0 | E63: =sum(E64:E73) -> 58245 | F63: =sum(F64:F73) -> 0 | G63: =sum(G64:G73) -> 0 | H63: =sum(H64:H73) -> 0 | I63: =sum(I64:I73) -> 0 | J63: =sum(J64:J73) -> 0 | ... AB63: =sum(AB64:AB73) -> 0 | AC63: =sum(AC64:AC74) -> 217061 | AD63: =sum(AD64:AD73) -> 600000 | AE63: =sum(AE64:AE73) -> 0 | AF63: =sum(AF64:AF73) -> 0 | AG63: =sum(AG64:AG73) -> 0 | AH63: =SUM(AH64:AH74) -> 1140320
A64: Mercat | B64: =AH64/$AH$10 -> 0.0078342325 | C64: 0 | D64: 0 | E64: 0 | F64: 0 | G64: 0 | H64: 0 | I64: 0 | J64: 0 | K64: 108647 | L64: 0 | M64: 0 | N64: 0 | O64: 0 | P64: 0 | Q64: 0 | R64: 0 | S64: 0 | T64: 0 | U64: 0 | V64: 108767 | W64: 0 | X64: 0 | Y64: 0 | Z64: 0 | AA64: 0 | AB64: 0 | AC64: 108845 | AD64: 0 | AE64: 0 | AF64: 0 | AG64: 0 | AH64: =SUM(C64:AG64) -> 326259
A65: Brevo | B65: =AH65/$AH$10 -> 0.001398597 | C65: 0 | D65: 0 | E65: 58245 | F65: 0 | G65: 0 | H65: 0 | I65: 0 | J65: 0 | K65: 0 | L65: 0 | M65: 0 | N65: 0 | O65: 0 | P65: 0 | Q65: 0 | R65: 0 | S65: 0 | T65: 0 | U65: 0 | V65: 0 | W65: 0 | X65: 0 | Y65: 0 | Z65: 0 | AA65: 0 | AB65: 0 | AC65: 0 | AD65: 0 | AE65: 0 | AF65: 0 | AG65: 0 | AH65: =SUM(C65:AG65) -> 58245
A66: Fiweex | B66: =AH66/$AH$10 -> 0.001142986 | C66: 0 | D66: 0 | E66: 0 | F66: 0 | G66: 0 | H66: 0 | I66: 0 | J66: 0 | K66: 47600 | L66: 0 | M66: 0 | N66: 0 | O66: 0 | P66: 0 | Q66: 0 | R66: 0 | S66: 0 | T66: 0 | U66: 0 | V66: 0 | W66: 0 | X66: 0 | Y66: 0 | Z66: 0 | AA66: 0 | AB66: 0 | AC66: 0 | AD66: 0 | AE66: 0 | AF66: 0 | AG66: 0 | AH66: =SUM(C66:AG66) -> 47600
A67: Fujifilm instax | B67: =AH67/$AH$10 -> 0 | C67: 0 | D67: 0 | E67: 0 | F67: 0 | G67: 0 | H67: 0 | I67: 0 | J67: 0 | K67: 0 | L67: 0 | M67: 0 | N67: 0 | O67: 0 | P67: 0 | Q67: 0 | R67: 0 | S67: 0 | T67: 0 | U67: 0 | V67: 0 | W67: 0 | X67: 0 | Y67: 0 | Z67: 0 | AA67: 0 | AB67: 0 | AC67: 0 | AD67: 0 | AE67: 0 | AF67: 0 | AG67: 0 | AH67: =SUM(C67:AG67) -> 0
A68: Resos | B68: =AH68/$AH$10 -> 0.0023946517 | C68: 0 | D68: 0 | E68: 0 | F68: 0 | G68: 0 | H68: 0 | I68: 0 | J68: 0 | K68: 0 | L68: 0 | M68: 0 | N68: 0 | O68: 0 | P68: 0 | Q68: 0 | R68: 0 | S68: 0 | T68: 0 | U68: 0 | V68: 0 | W68: 0 | X68: 0 | Y68: 0 | Z68: 0 | AA68: 0 | AB68: 0 | AC68: 99726 | AD68: 0 | AE68: 0 | AF68: 0 | AG68: 0 | AH68: =SUM(C68:AG68) -> 99726
A69: HappyCow | B69: =AH69/$AH$10 -> 0 | C69: 0 | D69: 0 | E69: 0 | F69: 0 | G69: 0 | H69: 0 | I69: 0 | J69: 0 | K69: 0 | L69: 0 | M69: 0 | N69: 0 | O69: 0 | P69: 0 | Q69: 0 | R69: 0 | S69: 0 | T69: 0 | U69: 0 | V69: 0 | W69: 0 | X69: 0 | Y69: 0 | Z69: 0 | AA69: 0 | AB69: 0 | AC69: 0 | AD69: 0 | AE69: 0 | AF69: 0 | AG69: 0 | AH69: =SUM(C69:AG69) -> 0
A70: Meta Ads | B70: =AH70/$AH$10 -> 0 | C70: 0 | D70: 0 | E70: 0 | F70: 0 | G70: 0 | H70: 0 | I70: 0 | J70: 0 | K70: 0 | L70: 0 | M70: 0 | N70: 0 | O70: 0 | P70: 0 | Q70: 0 | R70: 0 | S70: 0 | T70: 0 | U70: 0 | V70: 0 | W70: 0 | X70: 0 | Y70: 0 | Z70: 0 | AA70: 0 | AB70: 0 | AC70: 0 | AD70: 0 | AE70: 0 | AF70: 0 | AG70: 0 | AH70: =SUM(C70:AG70) -> 0
A71: Influencers | B71: =AH71/$AH$10 -> 0 | C71: 0 | D71: 0 | E71: 0 | F71: 0 | G71: 0 | H71: 0 | I71: 0 | J71: 0 | K71: 0 | L71: 0 | M71: 0 | N71: 0 | O71: 0 | P71: 0 | Q71: 0 | R71: 0 | S71: 0 | T71: 0 | U71: 0 | V71: 0 | W71: 0 | X71: 0 | Y71: 0 | Z71: 0 | AA71: 0 | AB71: 0 | AC71: 0 | AD71: 0 | AE71: 0 | AF71: 0 | AG71: 0 | AH71: =SUM(C71:AG71) -> 0
A72: Chatfuel | B72: =AH72/$AH$10 -> 0 | C72: 0 | D72: 0 | E72: 0 | F72: 0 | G72: 0 | H72: 0 | I72: 0 | J72: 0 | K72: 0 | L72: 0 | M72: 0 | N72: 0 | O72: 0 | P72: 0 | Q72: 0 | R72: 0 | S72: 0 | T72: 0 | U72: 0 | V72: 0 | W72: 0 | X72: 0 | Y72: 0 | Z72: 0 | AA72: 0 | AB72: 0 | AC72: 0 | AD72: 0 | AE72: 0 | AF72: 0 | AG72: 0 | AH72: =SUM(C72:AG72) -> 0
A73: Community manager | B73: =AH73/$AH$10 -> 0.014407386 | C73: 0 | D73: 0 | E73: 0 | F73: 0 | G73: 0 | H73: 0 | I73: 0 | J73: 0 | K73: 0 | L73: 0 | M73: 0 | N73: 0 | O73: 0 | P73: 0 | Q73: 0 | R73: 0 | S73: 0 | T73: 0 | U73: 0 | V73: 0 | W73: 0 | X73: 0 | Y73: 0 | Z73: 0 | AA73: 0 | AB73: 0 | AC73: 0 | AD73: 600000 | AE73: 0 | AF73: 0 | AG73: 0 | AH73: =SUM(C73:AG73) -> 600000
A74: Microsoft | B74: =AH74/$AH$10 -> 0.00020386452 | C74: 0 | D74: 0 | E74: 0 | F74: 0 | G74: 0 | H74: 0 | I74: 0 | J74: 0 | K74: 0 | L74: 0 | M74: 0 | N74: 0 | O74: 0 | P74: 0 | Q74: 0 | R74: 0 | S74: 0 | T74: 0 | U74: 0 | V74: 0 | W74: 0 | X74: 0 | Y74: 0 | Z74: 0 | AA74: 0 | AB74: 0 | AC74: 8490 | AD74: 0 | AH74: =SUM(C74:AG74) -> 8490
A76: Inversiones activos | B76: =AH76/$AH$10 -> 0 | C76: =sum(C77:C79) -> 0 | D76: =sum(D77:D79) -> 0 | E76: =sum(E77:E79) -> 0 | F76: =sum(F77:F79) -> 0 | G76: =sum(G77:G79) -> 0 | H76: =sum(H77:H79) -> 0 | I76: =sum(I77:I79) -> 0 | J76: =sum(J77:J79) -> 0 | ... AH76: =sum(AH77:AH79) -> 0
A77: Nuevas maquinaria | B77: =AH77/$AH$10 -> 0 | C77: 0 | D77: 0 | E77: 0 | F77: 0 | G77: 0 | H77: 0 | I77: 0 | J77: 0 | K77: 0 | L77: 0 | M77: 0 | N77: 0 | O77: 0 | P77: 0 | Q77: 0 | R77: 0 | S77: 0 | T77: 0 | U77: 0 | V77: 0 | W77: 0 | X77: 0 | Y77: 0 | Z77: 0 | AA77: 0 | AB77: 0 | AC77: 0 | AD77: 0 | AE77: 0 | AF77: 0 | AG77: 0 | AH77: =SUM(C77:AG77) -> 0
A78: Nueva decoración y muebles | B78: =AH78/$AH$10 -> 0 | C78: 0 | D78: 0 | E78: 0 | F78: 0 | G78: 0 | H78: 0 | I78: 0 | J78: 0 | K78: 0 | L78: 0 | M78: 0 | N78: 0 | O78: 0 | P78: 0 | Q78: 0 | R78: 0 | S78: 0 | T78: 0 | U78: 0 | V78: 0 | W78: 0 | X78: 0 | Y78: 0 | Z78: 0 | AA78: 0 | AB78: 0 | AC78: 0 | AD78: 0 | AE78: 0 | AF78: 0 | AG78: 0 | AH78: =SUM(C78:AG78) -> 0
A79: Remodelaciones | B79: =AH79/$AH$10 -> 0 | C79: 0 | D79: 0 | E79: 0 | F79: 0 | G79: 0 | H79: 0 | I79: 0 | J79: 0 | K79: 0 | L79: 0 | M79: 0 | N79: 0 | O79: 0 | P79: 0 | Q79: 0 | R79: 0 | S79: 0 | T79: 0 | U79: 0 | V79: 0 | W79: 0 | X79: 0 | Y79: 0 | Z79: 0 | AA79: 0 | AB79: 0 | AC79: 0 | AD79: 0 | AE79: 0 | AF79: 0 | AG79: 0 | AH79: =SUM(C79:AG79) -> 0
A81: Dinero temporal | B81: =AH81/$AH$10 -> 0.10777145 | C81: =sum(C82:C85) -> 0 | D81: =sum(D82:D85) -> 595045 | E81: =sum(E82:E85) -> 277150 | F81: =sum(F82:F85) -> 0 | G81: =sum(G82:G85) -> 218321 | H81: =sum(H82:H85) -> 0 | I81: =sum(I82:I85) -> 0 | J81: =sum(J82:J85) -> 0 | ... AH81: =sum(AH82:AH85) -> 4488175
A82: Delifast | B82: =AH82/$AH$10 -> 0.019144295 | C82: 0 | D82: 0 | E82: 0 | F82: 0 | G82: 218321 | H82: 0 | I82: 0 | J82: 0 | K82: 0 | L82: 0 | M82: 0 | N82: 0 | O82: 196117 | P82: 0 | Q82: 0 | R82: 0 | S82: 0 | T82: 0 | U82: 0 | V82: 234810 | W82: 0 | X82: 0 | Y82: 0 | Z82: 0 | AA82: 0 | AB82: 0 | AC82: 148022 | AD82: 0 | AE82: 0 | AF82: 0 | AG82: 0 | AH82: =SUM(C82:AG82) -> 797270
A83: Uber direct | B83: =AH83/$AH$10 -> 0 | C83: 0 | D83: 0 | E83: 0 | F83: 0 | G83: 0 | H83: 0 | I83: 0 | J83: 0 | K83: 0 | L83: 0 | M83: 0 | N83: 0 | O83: 0 | P83: 0 | Q83: 0 | R83: 0 | S83: 0 | T83: 0 | U83: 0 | V83: 0 | W83: 0 | X83: 0 | Y83: 0 | Z83: 0 | AA83: 0 | AB83: 0 | AC83: 0 | AD83: 0 | AE83: 0 | AF83: 0 | AG83: 0 | AH83: =SUM(C83:AG83) -> 0
A84: Monto delivery | B84: =AH84/$AH$10 -> 0.022130946 | C84: 0 | D84: 0 | E84: 277150 | F84: 0 | G84: 0 | H84: 0 | I84: 0 | J84: 0 | K84: 0 | L84: 150000 | M84: 50900 | N84: 0 | O84: 0 | P84: 0 | Q84: 0 | R84: 0 | S84: 227500 | T84: 0 | U84: 0 | V84: 0 | W84: 0 | X84: 0 | Y84: 0 | Z84: =12500+203600 -> 216100 | AA84: 0 | AB84: 0 | AC84: 0 | AD84: 0 | AE84: 0 | AF84: 0 | AG84: 0 | AH84: =SUM(C84:AG84) -> 921650
A85: Propina personal | B85: =AH85/$AH$10 -> 0.066496211 | C85: 0 | D85: 595045 | E85: 0 | F85: 0 | G85: 0 | H85: 0 | I85: 0 | J85: 0 | K85: 585003 | L85: 0 | M85: 0 | N85: 0 | O85: 0 | P85: 0 | Q85: 0 | R85: 1006607 | S85: 0 | T85: 0 | U85: 0 | V85: 0 | W85: 0 | X85: 0 | Y85: 567600 | Z85: 15000 | AA85: 0 | AB85: 0 | AC85: 0 | AD85: 0 | AE85: 0 | AF85: 0 | AG85: 0 | AH85: =SUM(C85:AG85) -> 2769255
A87: RRHH | B87: =AH87/$AH$10 -> 0.28485782 | C87: =sum(C88:C96) -> 0 | D87: =sum(D88:D96) -> 116500 | E87: =sum(E88:E96) -> 927213 | F87: =sum(F88:F96) -> 211010 | G87: =sum(G88:G96) -> 0 | H87: =sum(H88:H96) -> 0 | I87: =sum(I88:I96) -> 0 | J87: =sum(J88:J96) -> 0 | ... AG87: =sum(AG88:AG96) -> 0 | AH87: =SUM(AH88:AH96) -> 11862991
A88: Turnos feriados | B88: =AH88/$AH$10 -> 0 | C88: 0 | D88: 0 | E88: 0 | F88: 0 | G88: 0 | H88: 0 | I88: 0 | J88: 0 | K88: 0 | L88: 0 | M88: 0 | N88: 0 | O88: 0 | P88: 0 | Q88: 0 | R88: 0 | S88: 0 | T88: 0 | U88: 0 | V88: 0 | W88: 0 | X88: 0 | Y88: 0 | Z88: 0 | AA88: 0 | AB88: 0 | AC88: 0 | AD88: 0 | AE88: 0 | AF88: 0 | AG88: 0 | AH88: =SUM(C88:AG88) -> 0
A89: Sueldo personal | B89: =AH89/$AH$10 -> 0.20476892 | C89: 0 | D89: =46500+50000 -> 96500 | E89: =755213+124000+48000 -> 927213 | F89: 0 | G89: 0 | H89: 0 | I89: 0 | J89: 0 | K89: 0 | L89: 0 | M89: 48000 | N89: 0 | O89: 0 | P89: 0 | Q89: =150000+270000+200000+200000+170500+229500 -> 1220000 | R89: 0 | S89: =200000+48000 -> 248000 | T89: 0 | U89: 97053 | V89: 0 | W89: 0 | X89: 0 | Y89: 0 | Z89: 0 | AA89: 0 | AB89: 0 | AC89: 0 | AD89: =401262+580000+551262+800225+600000+800000+700000+611625+301396+545128 -> 5890898 | AE89: 0 | AF89: 0 | AG89: 0 | AH89: =SUM(C89:AG89) -> 8527664
A90: Traslados personal | B90: =AH90/$AH$10 -> 0.0035781705 | C90: 0 | D90: 0 | E90: 0 | F90: 0 | G90: 0 | H90: 0 | I90: 0 | J90: 0 | K90: 0 | L90: 0 | M90: 0 | N90: 0 | O90: 3598 | P90: 47028 | Q90: =6000+12000+10000+10000 -> 38000 | R90: 0 | S90: 12388 | T90: 0 | U90: 0 | V90: 0 | W90: 0 | X90: 0 | Y90: 0 | Z90: 48000 | AA90: 0 | AB90: 0 | AC90: 0 | AD90: 0 | AE90: 0 | AF90: 0 | AG90: 0 | AH90: =SUM(C90:AG90) -> 149014
A91: Turnos extras | B91: =AH91/$AH$10 -> 0.006723447 | C91: 0 | D91: 20000 | E91: 0 | F91: 0 | G91: 0 | H91: 0 | I91: 0 | J91: 0 | K91: 25000 | L91: 0 | M91: 80000 | N91: 0 | O91: 0 | P91: 0 | Q91: =35000+25000 -> 60000 | R91: =30000+25000 -> 55000 | S91: 0 | T91: 0 | U91: 0 | V91: 0 | W91: 0 | X91: 20000 | Y91: 20000 | Z91: 0 | AA91: 0 | AB91: 0 | AC91: 0 | AD91: 0 | AE91: 0 | AF91: 0 | AG91: 0 | AH91: =SUM(C91:AG91) -> 280000
A92: Bonos | B92: =AH92/$AH$10 -> 0.0086686843 | C92: 0 | D92: 0 | E92: 0 | F92: 211010 | G92: 0 | H92: 0 | I92: 0 | J92: 0 | K92: 0 | L92: 0 | M92: 0 | N92: 0 | O92: 0 | P92: 0 | Q92: 0 | R92: 0 | S92: 150000 | T92: 0 | U92: 0 | V92: 0 | W92: 0 | X92: 0 | Y92: 0 | Z92: 0 | AA92: 0 | AB92: 0 | AC92: 0 | AD92: 0 | AE92: 0 | AF92: 0 | AG92: 0 | AH92: =SUM(C92:AG92) -> 361010
A93: Previred | B93: =AH93/$AH$10 -> 0.046403862 | C93: 0 | D93: 0 | E93: 0 | F93: 0 | G93: 0 | H93: 0 | I93: 0 | J93: 0 | K93: 0 | L93: 0 | M93: 0 | N93: 0 | O93: 0 | P93: 1932503 | Q93: 0 | R93: 0 | S93: 0 | T93: 0 | U93: 0 | V93: 0 | W93: 0 | X93: 0 | Y93: 0 | Z93: 0 | AA93: 0 | AB93: 0 | AC93: 0 | AD93: 0 | AE93: 0 | AF93: 0 | AG93: 0 | AH93: =SUM(C93:AG93) -> 1932503
A94: Uniforme pesonal | B94: =AH94/$AH$10 -> 0.001080554 | C94: 0 | D94: 0 | E94: 0 | F94: 0 | G94: 0 | H94: 0 | I94: 0 | J94: 0 | K94: 0 | L94: 0 | M94: 0 | N94: 0 | O94: 45000 | P94: 0 | Q94: 0 | R94: 0 | S94: 0 | T94: 0 | U94: 0 | V94: 0 | W94: 0 | X94: 0 | Y94: 0 | Z94: 0 | AA94: 0 | AB94: 0 | AC94: 0 | AD94: 0 | AE94: 0 | AF94: 0 | AG94: 0 | AH94: =SUM(C94:AG94) -> 45000
A95: Finiquitos | B95: =AH95/$AH$10 -> 0.0015656027 | C95: 0 | D95: 0 | E95: 0 | F95: 0 | G95: 0 | H95: 0 | I95: 0 | J95: 0 | K95: 0 | L95: 0 | M95: 65200 | N95: 0 | O95: 0 | P95: 0 | Q95: 0 | R95: 0 | S95: 0 | T95: 0 | U95: 0 | V95: 0 | W95: 0 | X95: 0 | Y95: 0 | Z95: 0 | AA95: 0 | AB95: 0 | AC95: 0 | AD95: 0 | AE95: 0 | AF95: 0 | AG95: 0 | AH95: =SUM(C95:AG95) -> 65200
A96: Recreación | B96: =AH96/$AH$10 -> 0.012068587 | C96: 0 | D96: 0 | E96: 0 | F96: 0 | G96: 0 | H96: 0 | I96: 0 | J96: 0 | K96: 0 | L96: 0 | M96: 0 | N96: 0 | O96: 0 | P96: 152000 | Q96: 0 | R96: =170600+30000+150000 -> 350600 | S96: 0 | T96: 0 | U96: 0 | V96: 0 | W96: 0 | X96: 0 | Y96: 0 | Z96: 0 | AA96: 0 | AB96: 0 | AC96: 0 | AD96: 0 | AE96: 0 | AF96: 0 | AG96: 0 | AH96: =SUM(C96:AG96) -> 502600
A98: Impuestos fiscales | B98: =AH98/$AH$10 -> 0.10675263 | C98: =SUM(C99:C100) -> 0 | D98: =SUM(D99:D100) -> 0 | E98: =SUM(E99:E100) -> 0 | F98: =SUM(F99:F100) -> 0 | G98: =SUM(G99:G100) -> 0 | H98: =SUM(H99:H100) -> 0 | I98: =SUM(I99:I100) -> 0 | J98: =SUM(J99:J100) -> 0 | ... AH98: =SUM(AH99:AH100) -> 4445746
A99: Impuesto sobre la renta | B99: =AH99/$AH$10 -> 0 | C99: 0 | D99: 0 | E99: 0 | F99: 0 | G99: 0 | H99: 0 | I99: 0 | J99: 0 | K99: 0 | L99: 0 | M99: 0 | N99: 0 | O99: 0 | P99: 0 | Q99: 0 | R99: 0 | S99: 0 | T99: 0 | U99: 0 | V99: 0 | W99: 0 | X99: 0 | Y99: 0 | Z99: 0 | AA99: 0 | AB99: 0 | AC99: 0 | AD99: 0 | AE99: 0 | AF99: 0 | AG99: 0 | AH99: =SUM(C99:AG99) -> 0
A100: IVA | B100: =AH100/$AH$10 -> 0.10675263 | C100: 0 | D100: 0 | E100: 0 | F100: 0 | G100: 0 | H100: 0 | I100: 0 | J100: 0 | K100: 0 | L100: 0 | M100: 0 | N100: 0 | O100: 0 | P100: 0 | Q100: 0 | R100: 0 | S100: 0 | T100: 0 | U100: 0 | V100: 4445746 | W100: 0 | X100: 0 | Y100: 0 | Z100: 0 | AA100: 0 | AB100: 0 | AC100: 0 | AD100: 0 | AE100: 0 | AF100: 0 | AG100: 0 | AH100: =SUM(C100:AG100) -> 4445746
A102: Amortizaciones | AH102: =AH103+AH104 -> 1760416
A103: Préstamo | C103: 0 | D103: 0 | E103: 0 | F103: 0 | G103: 0 | H103: 0 | I103: 0 | J103: 0 | K103: 0 | L103: 0 | M103: 0 | N103: 0 | O103: 0 | P103: 0 | Q103: 0 | R103: 0 | S103: 0 | T103: 0 | U103: 0 | V103: 0 | W103: 0 | X103: 0 | Y103: 0 | Z103: 0 | AA103: 0 | AB103: 1760416 | AC103: 0 | AD103: 0 | AE103: 0 | AF103: 0 | AG103: 0 | AH103: =sum(C103:AG103) -> 1760416
C104: 0 | D104: 0 | E104: 0 | F104: 0 | G104: 0 | H104: 0 | I104: 0 | J104: 0 | K104: 0 | L104: 0 | M104: 0 | N104: 0 | O104: 0 | P104: 0 | Q104: 0 | R104: 0 | S104: 0 | T104: 0 | U104: 0 | V104: 0 | W104: 0 | X104: 0 | Y104: 0 | Z104: 0 | AA104: 0 | AB104: 0 | AC104: 0 | AD104: 0 | AE104: 0 | AF104: 0 | AG104: 0 | AH104: =sum(C104:AG104) -> 0
A106: Total egresos conciliación | C106: =C98+C87+C81+C32+C76+C12+C103+C104 -> 827960 | D106: =D98+D87+D81+D32+D76+D12+D103+D104 -> 882485 | E106: =E98+E87+E81+E32+E76+E12+E103+E104 -> 2009025 | F106: =F98+F87+F81+F32+F76+F12+F103+F104 -> 367846 | G106: =G98+G87+G81+G32+G76+G12+G103+G104 -> 1075106 | H106: =H98+H87+H81+H32+H76+H12+H103+H104 -> 2610988 | I106: =I98+I87+I81+I32+I76+I12+I103+I104 -> 176918 | J106: =J98+J87+J81+J32+J76+J12+J103+J104 -> 376826 | ... AG106: =AG98+AG87+AG81+AG32+AG76+AG12+AG103+AG104 -> 0 | AH106: =sum(C106:AF106) -> 45046586
A107: Total egresos operativos | C107: =C98+C87+C32+C76+C12 -> 827960 | D107: =D98+D87+D32+D76+D12 -> 287440 | E107: =E98+E87+E32+E76+E12 -> 1731875 | F107: =F98+F87+F32+F76+F12 -> 367846 | G107: =G98+G87+G32+G76+G12 -> 856785 | H107: =H98+H87+H32+H76+H12 -> 2610988 | I107: =I98+I87+I32+I76+I12 -> 176918 | J107: =J98+J87+J32+J76+J12 -> 376826 | ... AG107: =AG98+AG87+AG32+AG76+AG12 -> 0 | AH107: =sum(C107:AG107) -> 38797995
A109: Rentabilidad | B109: =AH109/$AH$10 -> 0.068370492 | C109: =C9-C107 -> 1987475 | D109: =D9-D107 -> 1004063 | E109: =E9-E107 -> -505126 | F109: =F9-F107 -> 702347 | G109: =G9-G107 -> 434194 | H109: =H9-H107 -> -1272393 | I109: =I9-I107 -> 1633922 | J109: =J9-J107 -> 2023578 | ... AG109: =AG9-AG107 -> 0 | AH109: =AH10-AH107 -> 2847310

Sheet Marzo
C1: 46082 | D1: 46083 | E1: 46084 | F1: 46085 | G1: 46086 | H1: 46087 | I1: 46088 | J1: 46089 | K1: 46090 | L1: 46091 | M1: 46092 | N1: 46093 | O1: 46094 | P1: 46095 | Q1: 46096 | R1: 46097 | S1: 46098 | T1: 46099 | U1: 46100 | V1: 46101 | W1: 46102 | X1: 46103 | Y1: 46104 | Z1: 46105 | AA1: 46106 | AB1: 46107 | AC1: 46108 | AD1: 46109 | AE1: 46110 | AF1: 46111 | AG1: 46112 | AH1: Totales
A4: Ingresos
A5: Transbank | C5: =101972+558399+1912448 -> 2572819 | D5: =10402+235655+1074530 -> 1320587 | E5: =218017+30292 -> 248309 | F5: =36170+666573+667006+15943 -> 1385692 | G5: =439805+320141+61779+28796 -> 850521 | H5: =572819+95070+536572+29195 -> 1233656 | I5: =111004+957263+812195+209298 -> 2089760 | J5: =1542953+566171+43843+99344+17647 -> 2269958 | K5: =87089+1159007+161522+34742 -> 1442360 | L5: =30591+74469 -> 105060 | M5: =470324+632956+66185 -> 1169465 | N5: =725159+370053+26405 -> 1121617 | O5: =22419+916538+374056+75031 -> 1388044 | P5: =554234+19730+1082502+23117+28479 -> 1708062 | Q5: =45936+421095+1088033+158633 -> 1713697 | R5: =200383+684768+28700 -> 913851 | S5: =45230+23217+2872+S6 -> 71319 | T5: =514361+442837+36104+8868+38761 -> 1040931 | U5: =244245+639804+46155+35771 -> 965975 | V5: =11709+235237+61580+784927 -> 1093453 | W5: =712418+630939+46434+144796 -> 1534587 | X5: =604572+969415+101938 -> 1675925 | Y5: =12271+837071+440924+50519 -> 1340785 | Z5: 19950 | AA5: =16540+379476+578204 -> 974220 | AB5: =464555+32982+292650+54841 -> 845028 | AC5: =228610+939251+23317+36060+25807 -> 1253045 | AD5: =731697+414855+113593 -> 1260145 | AE5: =54306+119073+651539+1448251+53011 -> 2326180 | AF5: =166104+803143 -> 969247 | AG5: =16671+54305+278841 -> 349817 | AH5: =SUM(C5:AG5) -> 37254065
A6: Transferencias | C6: 0 | D6: 0 | E6: 0 | F6: 25900 | G6: 26220 | H6: 0 | I6: 1800 | J6: 0 | K6: 0 | L6: 0 | M6: 25900 | N6: 0 | O6: 198650 | P6: 14700 | Q6: 0 | R6: 0 | S6: 0 | T6: 0 | U6: 0 | V6: 0 | W6: 0 | X6: 0 | Y6: 0 | Z6: 0 | AA6: 0 | AB6: 67200 | AC6: 0 | AD6: 12900 | AE6: 42000 | AF6: 16240 | AG6: 0 | AH6: =SUM(C6:AG6) -> 431510
A7: Efectivo | C7: 0 | D7: 0 | E7: 0 | F7: 0 | G7: 0 | H7: 0 | I7: 0 | J7: 0 | K7: 0 | L7: 0 | M7: 0 | N7: 0 | O7: 0 | P7: 0 | Q7: 0 | R7: 0 | S7: 0 | T7: 0 | U7: 0 | V7: 0 | W7: 0 | X7: 0 | Y7: 0 | Z7: 0 | AA7: 0 | AB7: 0 | AC7: 0 | AD7: 0 | AE7: 0 | AF7: 0 | AG7: 200000 | AH7: =SUM(C7:AG7) -> 200000
A8: Uber | C8: 0 | D8: 0 | E8: =285025+529384 -> 814409 | F8: 0 | G8: 0 | H8: 0 | I8: 0 | J8: 0 | K8: 0 | L8: =444793+162633 -> 607426 | M8: 0 | N8: 0 | O8: 0 | P8: 0 | Q8: 0 | R8: 0 | S8: =496444+194626 -> 691070 | T8: 0 | U8: 0 | V8: 0 | W8: 0 | X8: 0 | Y8: 0 | Z8: =562344+259622 -> 821966 | AA8: 0 | AB8: 0 | AC8: 0 | AD8: 0 | AE8: 0 | AF8: 0 | AG8: 0 | AH8: =SUM(C8:AG8) -> 2934871
A9: Total bruto | C9: =SUM(C5:C8) -> 2572819 | D9: =SUM(D5:D8) -> 1320587 | E9: =SUM(E5:E8) -> 1062718 | F9: =SUM(F5:F8) -> 1411592 | G9: =SUM(G5:G8) -> 876741 | H9: =SUM(H5:H8) -> 1233656 | I9: =SUM(I5:I8) -> 2091560 | J9: =SUM(J5:J8) -> 2269958 | ... AH9: =SUM(AH5:AH8) -> 40820446
A10: Total neto | AH10: =AH9-AH82 -> 36939460
A12: Materia prima | B12: =AH12/$AH$10 -> 0.33387759 | C12: =sum(C13:C30) -> 7000 | D12: =sum(D13:D30) -> 30300 | E12: =sum(E13:E30) -> 1156221 | F12: =sum(F13:F30) -> 1240950 | G12: =sum(G13:G30) -> 84000 | H12: =sum(H13:H30) -> 0 | I12: =sum(I13:I30) -> 175212 | J12: =sum(J13:J30) -> 15020 | ... AG12: =sum(AG13:AG30) -> 1609185 | AH12: =sum(AH13:AH31) -> 12333258
A13: MP | B13: =AH13/$AH$10 -> 0.057693047 | C13: 0 | D13: =12800+17500 -> 30300 | E13: =30000+84000+60000 -> 174000 | F13: 0 | G13: 84000 | H13: 0 | I13: =36000+69001+15280 -> 120281 | J13: 15020 | K13: 0 | L13: 15420 | M13: 0 | N13: 10590 | O13: =22970+233835+26490 -> 283295 | P13: =15600+6000 -> 21600 | Q13: 12220 | R13: =84000+7530 -> 91530 | S13: 55770 | T13: =20841+96250 -> 117091 | U13: 0 | V13: 86190 | W13: 0 | X13: 7900 | Y13: 0 | Z13: 238000 | AA13: =51338+238000 -> 289338 | AB13: =65530+20610 -> 86140 | AC13: =84500+94000+71400 -> 249900 | AD13: 63975 | AE13: 0 | AF13: =15800+26840 -> 42640 | AG13: 35950 | AH13: =SUM(C13:AG13) -> 2131150
A14: Arroz | B14: =AH14/$AH$10 -> 0.011776025 | C14: 0 | D14: 0 | E14: 87000 | F14: 0 | G14: 0 | H14: 0 | I14: 0 | J14: 0 | K14: 0 | L14: 116000 | M14: 0 | N14: 0 | O14: 0 | P14: 0 | Q14: 0 | R14: 0 | S14: 0 | T14: 116000 | U14: 0 | V14: 0 | W14: 0 | X14: 0 | Y14: 0 | Z14: 0 | AA14: 0 | AB14: 0 | AC14: 0 | AD14: 0 | AE14: 0 | AF14: 0 | AG14: 116000 | AH14: =SUM(C14:AG14) -> 435000
A15: Hod Food | B15: =AH15/$AH$10 -> 0.077739848 | C15: 0 | D15: 0 | E15: 0 | F15: 757851 | G15: 0 | H15: 0 | I15: 0 | J15: 0 | K15: 0 | L15: 448404 | M15: 0 | N15: 0 | O15: 0 | P15: 0 | Q15: 0 | R15: 0 | S15: 0 | T15: 350990 | U15: 0 | V15: 0 | W15: 0 | X15: 0 | Y15: 0 | Z15: 0 | AA15: 834557 | AB15: 0 | AC15: 0 | AD15: 0 | AE15: 0 | AF15: 0 | AG15: 479866 | AH15: =SUM(C15:AG15) -> 2871668
A16: Seitan | B16: =AH16/$AH$10 -> 0.008337209 | C16: 0 | D16: 0 | E16: 153986 | F16: 0 | G16: 0 | H16: 0 | I16: 0 | J16: 0 | K16: 0 | L16: 0 | M16: 0 | N16: 0 | O16: 0 | P16: 153986 | Q16: 0 | R16: 0 | S16: 0 | T16: 0 | U16: 0 | V16: 0 | W16: 0 | X16: 0 | Y16: 0 | Z16: 0 | AA16: 0 | AB16: 0 | AC16: 0 | AD16: 0 | AE16: 0 | AF16: 0 | AG16: 0 | AH16: =SUM(C16:AG16) -> 307972
A17: Palta | B17: =AH17/$AH$10 -> 0.037308044 | C17: 0 | D17: 0 | E17: 0 | F17: 0 | G17: 0 | H17: 0 | I17: 0 | J17: 0 | K17: 0 | L17: 486115 | M17: 0 | N17: 0 | O17: 0 | P17: 0 | Q17: 0 | R17: 0 | S17: 0 | T17: 0 | U17: 447559 | V17: 0 | W17: 0 | X17: 0 | Y17: 0 | Z17: 0 | AA17: 0 | AB17: 0 | AC17: 0 | AD17: 0 | AE17: 0 | AF17: 0 | AG17: 444465 | AH17: =SUM(C17:AG17) -> 1378139
A18: Carivo | B18: =AH18/$AH$10 -> 0.065381844 | C18: 0 | D18: 0 | E18: 459220 | F18: 0 | G18: 0 | H18: 0 | I18: 0 | J18: 0 | K18: 0 | L18: 597150 | M18: 0 | N18: 0 | O18: 0 | P18: 0 | Q18: 0 | R18: 0 | S18: 524350 | T18: 0 | U18: 0 | V18: 0 | W18: 0 | X18: 0 | Y18: 0 | Z18: 427210 | AA18: 0 | AB18: 0 | AC18: 0 | AD18: 0 | AE18: 0 | AF18: 0 | AG18: 407240 | AH18: =SUM(C18:AG18) -> 2415170
A19: Shen | B19: =AH19/$AH$10 -> 0.010569321 | C19: 0 | D19: 0 | E19: 136850 | F19: 0 | G19: 0 | H19: 0 | I19: 0 | J19: 0 | K19: 0 | L19: 0 | M19: 0 | N19: 0 | O19: 0 | P19: 0 | Q19: 0 | R19: 0 | S19: 169575 | T19: 0 | U19: 0 | V19: 0 | W19: 0 | X19: 0 | Y19: 0 | Z19: 0 | AA19: 84000 | AB19: 0 | AC19: 0 | AD19: 0 | AE19: 0 | AF19: 0 | AG19: 0 | AH19: =SUM(C19:AG19) -> 390425
A20: Mozzen | B20: =AH20/$AH$10 -> 0.0061652769 | C20: 0 | D20: 0 | E20: 0 | F20: 227742 | G20: 0 | H20: 0 | I20: 0 | J20: 0 | K20: 0 | L20: 0 | M20: 0 | N20: 0 | O20: 0 | P20: 0 | Q20: 0 | R20: 0 | S20: 0 | T20: 0 | U20: 0 | V20: 0 | W20: 0 | X20: 0 | Y20: 0 | Z20: 0 | AA20: 0 | AB20: 0 | AC20: 0 | AD20: 0 | AE20: 0 | AF20: 0 | AG20: 0 | AH20: =SUM(C20:AG20) -> 227742
A21: Café y Té | B21: =AH21/$AH$10 -> 0 | C21: 0 | D21: 0 | E21: 0 | F21: 0 | G21: 0 | H21: 0 | I21: 0 | J21: 0 | K21: 0 | L21: 0 | M21: 0 | N21: 0 | O21: 0 | P21: 0 | Q21: 0 | R21: 0 | S21: 0 | T21: 0 | U21: 0 | V21: 0 | W21: 0 | X21: 0 | Y21: 0 | Z21: 0 | AA21: 0 | AB21: 0 | AC21: 0 | AD21: 0 | AE21: 0 | AF21: 0 | AG21: 0 | AH21: =SUM(C21:AG21) -> 0
A22: Leche de soya | B22: =AH22/$AH$10 -> 0.0036531666 | C22: 0 | D22: 0 | E22: 0 | F22: 0 | G22: 0 | H22: 0 | I22: 0 | J22: 0 | K22: 0 | L22: 0 | M22: 0 | N22: 0 | O22: 0 | P22: 0 | Q22: 0 | R22: 0 | S22: 134946 | T22: 0 | U22: 0 | V22: 0 | W22: 0 | X22: 0 | Y22: 0 | Z22: 0 | AA22: 0 | AB22: 0 | AC22: 0 | AD22: 0 | AE22: 0 | AF22: 0 | AG22: 0 | AH22: =SUM(C22:AG22) -> 134946
A23: Bebestibles | B23: =AH23/$AH$10 -> 0.0049664776 | C23: 0 | D23: 0 | E23: =19501 -> 19501 | F23: 0 | G23: 0 | H23: 0 | I23: 0 | J23: 0 | K23: 0 | L23: 0 | M23: 19501 | N23: 0 | O23: 0 | P23: 0 | Q23: 0 | R23: 0 | S23: 0 | T23: 75047 | U23: 0 | V23: 0 | W23: 23205 | X23: 0 | Y23: 0 | Z23: 23000 | AA23: 0 | AB23: 0 | AC23: 23205 | AD23: 0 | AE23: 0 | AF23: 0 | AG23: 0 | AH23: =SUM(C23:AG23) -> 183459
A24: Brugga | B24: =AH24/$AH$10 -> 0.01275709 | C24: 0 | D24: 0 | E24: 125664 | F24: 0 | G24: 0 | H24: 0 | I24: 0 | J24: 0 | K24: 0 | L24: 0 | M24: 0 | N24: 0 | O24: 125664 | P24: 0 | Q24: 0 | R24: 0 | S24: 0 | T24: 0 | U24: 94248 | V24: 0 | W24: 0 | X24: 0 | Y24: 0 | Z24: 0 | AA24: 0 | AB24: 0 | AC24: 0 | AD24: 0 | AE24: 0 | AF24: 0 | AG24: 125664 | AH24: =SUM(C24:AG24) -> 471240
A25: Colación | B25: =AH25/$AH$10 -> 0.0065281951 | C25: 7000 | D25: 0 | E25: 0 | F25: 0 | G25: 0 | H25: 0 | I25: 54931 | J25: 0 | K25: 12320 | L25: 0 | M25: 0 | N25: 46509 | O25: 0 | P25: 0 | Q25: 10400 | R25: 6780 | S25: 0 | T25: 0 | U25: 0 | V25: 29008 | W25: 0 | X25: 0 | Y25: 0 | Z25: 0 | AA25: 0 | AB25: 9490 | AC25: 56810 | AD25: 0 | AE25: 7900 | AF25: 0 | AG25: 0 | AH25: =SUM(C25:AG25) -> 241148
A26: Empaques y desechables | B26: =AH26/$AH$10 -> 0.013309317 | C26: 0 | D26: 0 | E26: 0 | F26: 137957 | G26: 0 | H26: 0 | I26: 0 | J26: 0 | K26: 0 | L26: 0 | M26: 0 | N26: 160168 | O26: 0 | P26: 0 | Q26: 0 | R26: 0 | S26: 10500 | T26: 0 | U26: 0 | V26: 0 | W26: 0 | X26: 0 | Y26: 0 | Z26: 0 | AA26: 6000 | AB26: 154914 | AC26: 22100 | AD26: 0 | AE26: 0 | AF26: 0 | AG26: 0 | AH26: =SUM(C26:AG26) -> 491639
A27: Soyas sachet | B27: =AH27/$AH$10 -> 0.0024363377 | C27: 0 | D27: 0 | E27: 0 | F27: 0 | G27: 0 | H27: 0 | I27: 0 | J27: 0 | K27: 0 | L27: 0 | M27: 0 | N27: 0 | O27: 0 | P27: 0 | Q27: 0 | R27: 0 | S27: 89997 | T27: 0 | U27: 0 | V27: 0 | W27: 0 | X27: 0 | Y27: 0 | Z27: 0 | AA27: 0 | AB27: 0 | AC27: 0 | AD27: 0 | AE27: 0 | AF27: 0 | AG27: 0 | AH27: =SUM(C27:AG27) -> 89997
A28: Servilletas | B28: =AH28/$AH$10 -> 0 | C28: 0 | D28: 0 | E28: 0 | F28: 0 | G28: 0 | H28: 0 | I28: 0 | J28: 0 | K28: 0 | L28: 0 | M28: 0 | N28: 0 | O28: 0 | P28: 0 | Q28: 0 | R28: 0 | S28: 0 | T28: 0 | U28: 0 | V28: 0 | W28: 0 | X28: 0 | Y28: 0 | Z28: 0 | AA28: 0 | AB28: 0 | AC28: 0 | AD28: 0 | AE28: 0 | AF28: 0 | AG28: 0 | AH28: =SUM(C28:AG28) -> 0
A29: Limpieza e higiene | B29: =AH29/$AH$10 -> 0.0014410064 | C29: 0 | D29: 0 | E29: 0 | F29: 0 | G29: 0 | H29: 0 | I29: 0 | J29: 0 | K29: 0 | L29: 0 | M29: 0 | N29: 0 | O29: 0 | P29: 0 | Q29: 0 | R29: 0 | S29: 0 | T29: 0 | U29: 0 | V29: 0 | W29: 0 | X29: 0 | Y29: 53230 | Z29: 0 | AA29: 0 | AB29: 0 | AC29: 0 | AD29: 0 | AE29: 0 | AF29: 0 | AG29: 0 | AH29: =SUM(C29:AG29) -> 53230
A30: Postres | B30: =AH30/$AH$10 -> 0.013815389 | C30: 0 | D30: 0 | E30: 0 | F30: 117400 | G30: 0 | H30: 0 | I30: 0 | J30: 0 | K30: 0 | L30: 0 | M30: 0 | N30: 0 | O30: 0 | P30: 241218 | Q30: 0 | R30: 75000 | S30: 0 | T30: 76715 | U30: 0 | V30: 0 | W30: 0 | X30: 0 | Y30: 0 | Z30: 0 | AA30: 0 | AB30: 0 | AC30: 0 | AD30: 0 | AE30: 0 | AF30: 0 | AG30: 0 | AH30: =SUM(C30:AG30) -> 510333
AH31: =SUM(C31:AG31) -> 0
A32: Gastos FV | B32: =AH32/$AH$10 -> 0.20771281 | C32: =sum(C33+C53+C63) -> 0 | D32: =sum(D33+D53+D63) -> 0 | E32: =sum(E33+E53+E63) -> 58245 | F32: =sum(F33+F53+F63) -> 223822 | G32: =sum(G33+G53+G63) -> 9401 | H32: =sum(H33+H53+H63) -> 1864570 | I32: =sum(I33+I53+I63) -> 108969 | J32: =sum(J33+J53+J63) -> 0 | ... AH32: =sum(AH33+AH53+AH63) -> 7672799
A33: Operaciones | B33: =AH33/$AH$10 -> 0.17493182 | C33: =sum(C34:C52) -> 0 | D33: =sum(D34:D52) -> 0 | E33: =sum(E34:E52) -> 0 | F33: =sum(F34:F52) -> 223822 | G33: =sum(G34:G52) -> 0 | H33: =sum(H34:H52) -> 1860620 | I33: =sum(I34:I52) -> 0 | J33: =sum(J34:J52) -> 0 | ... AH33: =sum(AH34:AH52) -> 6461887
A34: Electricidad | B34: =AH34/$AH$10 -> 0.0056157562 | C34: 0 | D34: 0 | E34: 0 | F34: 0 | G34: 0 | H34: 0 | I34: 0 | J34: 0 | K34: 0 | L34: 0 | M34: 0 | N34: 0 | O34: 0 | P34: 0 | Q34: 0 | R34: 0 | S34: 194080 | T34: 0 | U34: 0 | V34: 0 | W34: 0 | X34: 0 | Y34: 0 | Z34: 0 | AA34: 0 | AB34: 0 | AC34: 13363 | AD34: 0 | AE34: 0 | AF34: 0 | AG34: 0 | AH34: =SUM(C34:AG34) -> 207443
A35: Agua | B35: =AH35/$AH$10 -> 0.002995171 | C35: 0 | D35: 0 | E35: 0 | F35: 0 | G35: 0 | H35: 0 | I35: 0 | J35: 0 | K35: 0 | L35: 0 | M35: 0 | N35: 0 | O35: 0 | P35: 0 | Q35: 0 | R35: 0 | S35: 110640 | T35: 0 | U35: 0 | V35: 0 | W35: 0 | X35: 0 | Y35: 0 | Z35: 0 | AA35: 0 | AB35: 0 | AC35: 0 | AD35: 0 | AE35: 0 | AF35: 0 | AG35: 0 | AH35: =SUM(C35:AG35) -> 110640
A36: Gas | B36: =AH36/$AH$10 -> 0.01067942 | C36: 0 | D36: 0 | E36: 0 | F36: 0 | G36: 0 | H36: 0 | I36: 0 | J36: 0 | K36: 0 | L36: 0 | M36: 0 | N36: 0 | O36: 0 | P36: 0 | Q36: 0 | R36: 0 | S36: 394492 | T36: 0 | U36: 0 | V36: 0 | W36: 0 | X36: 0 | Y36: 0 | Z36: 0 | AA36: 0 | AB36: 0 | AC36: 0 | AD36: 0 | AE36: 0 | AF36: 0 | AG36: 0 | AH36: =SUM(C36:AG36) -> 394492
A37: Restaurantpe | B37: =AH37/$AH$10 -> 0 | C37: 0 | D37: 0 | E37: 0 | F37: 0 | G37: 0 | H37: 0 | I37: 0 | J37: 0 | K37: 0 | L37: 0 | M37: 0 | N37: 0 | O37: 0 | P37: 0 | Q37: 0 | R37: 0 | S37: 0 | T37: 0 | U37: 0 | V37: 0 | W37: 0 | X37: 0 | Y37: 0 | Z37: 0 | AA37: 0 | AB37: 0 | AC37: 0 | AD37: 0 | AE37: 0 | AF37: 0 | AG37: 0 | AH37: =SUM(C37:AG37) -> 0
A38: Toteat | B38: =AH38/$AH$10 -> 0.0060591573 | C38: 0 | D38: 0 | E38: 0 | F38: =87812+136010 -> 223822 | G38: 0 | H38: 0 | I38: 0 | J38: 0 | K38: 0 | L38: 0 | M38: 0 | N38: 0 | O38: 0 | P38: 0 | Q38: 0 | R38: 0 | S38: 0 | T38: 0 | U38: 0 | V38: 0 | W38: 0 | X38: 0 | Y38: 0 | Z38: 0 | AA38: 0 | AB38: 0 | AC38: 0 | AD38: 0 | AE38: 0 | AF38: 0 | AG38: 0 | AH38: =SUM(C38:AG38) -> 223822
A39: Alarma | B39: =AH39/$AH$10 -> 0.0012948484 | C39: 0 | D39: 0 | E39: 0 | F39: 0 | G39: 0 | H39: 0 | I39: 0 | J39: 0 | K39: 0 | L39: 0 | M39: 0 | N39: 0 | O39: 0 | P39: 0 | Q39: 0 | R39: 0 | S39: 47831 | T39: 0 | U39: 0 | V39: 0 | W39: 0 | X39: 0 | Y39: 0 | Z39: 0 | AA39: 0 | AB39: 0 | AC39: 0 | AD39: 0 | AE39: 0 | AF39: 0 | AG39: 0 | AH39: =SUM(C39:AG39) -> 47831
A40: VTR | B40: =AH40/$AH$10 -> 0.00031973938 | C40: 0 | D40: 0 | E40: 0 | F40: 0 | G40: 0 | H40: 0 | I40: 0 | J40: 0 | K40: 0 | L40: 0 | M40: 0 | N40: 0 | O40: 0 | P40: 0 | Q40: 0 | R40: 0 | S40: 11811 | T40: 0 | U40: 0 | V40: 0 | W40: 0 | X40: 0 | Y40: 0 | Z40: 0 | AA40: 0 | AB40: 0 | AC40: 0 | AD40: 0 | AE40: 0 | AF40: 0 | AG40: 0 | AH40: =SUM(C40:AG40) -> 11811
A41: Bodega | B41: =AH41/$AH$10 -> 0.0094749625 | C41: 0 | D41: 0 | E41: 0 | F41: 0 | G41: 0 | H41: 0 | I41: 0 | J41: 0 | K41: 0 | L41: 0 | M41: 0 | N41: 0 | O41: 0 | P41: 0 | Q41: 0 | R41: 0 | S41: 0 | T41: 0 | U41: 0 | V41: 0 | W41: 0 | X41: 0 | Y41: 0 | Z41: 0 | AA41: 0 | AB41: 0 | AC41: 0 | AD41: 350000 | AE41: 0 | AF41: 0 | AG41: 0 | AH41: =SUM(C41:AG41) -> 350000
A42: Arriendo | B42: =AH42/$AH$10 -> 0.049557303 | C42: 0 | D42: 0 | E42: 0 | F42: 0 | G42: 0 | H42: 1830620 | I42: 0 | J42: 0 | K42: 0 | L42: 0 | M42: 0 | N42: 0 | O42: 0 | P42: 0 | Q42: 0 | R42: 0 | S42: 0 | T42: 0 | U42: 0 | V42: 0 | W42: 0 | X42: 0 | Y42: 0 | Z42: 0 | AA42: 0 | AB42: 0 | AC42: 0 | AD42: 0 | AE42: 0 | AF42: 0 | AG42: 0 | AH42: =SUM(C42:AG42) -> 1830620
A43: Funmigacion | B43: =AH43/$AH$10 -> 0.0027071322 | C43: 0 | D43: 0 | E43: 0 | F43: 0 | G43: 0 | H43: 0 | I43: 0 | J43: 0 | K43: 0 | L43: 0 | M43: 0 | N43: 0 | O43: 0 | P43: 0 | Q43: 0 | R43: 0 | S43: 0 | T43: 0 | U43: 0 | V43: 0 | W43: 0 | X43: 0 | Y43: 0 | Z43: 0 | AA43: 0 | AB43: 0 | AC43: 0 | AD43: 0 | AE43: 0 | AF43: 0 | AG43: 100000 | AH43: =SUM(C43:AG43) -> 100000
A44: Aroclean | B44: =AH44/$AH$10 -> 0.0018678129 | C44: 0 | D44: 0 | E44: 0 | F44: 0 | G44: 0 | H44: 0 | I44: 0 | J44: 0 | K44: 0 | L44: 0 | M44: 0 | N44: 0 | O44: 0 | P44: 0 | Q44: 0 | R44: 0 | S44: 0 | T44: 0 | U44: 0 | V44: 0 | W44: 0 | X44: 0 | Y44: 0 | Z44: 0 | AA44: 0 | AB44: 0 | AC44: 0 | AD44: 0 | AE44: 0 | AF44: 0 | AG44: 68996 | AH44: =SUM(C44:AG44) -> 68996
A45: Reposición de vasos | B45: =AH45/$AH$10 -> 0 | C45: 0 | D45: 0 | E45: 0 | F45: 0 | G45: 0 | H45: 0 | I45: 0 | J45: 0 | K45: 0 | L45: 0 | M45: 0 | N45: 0 | O45: 0 | P45: 0 | Q45: 0 | R45: 0 | S45: 0 | T45: 0 | U45: 0 | V45: 0 | W45: 0 | X45: 0 | Y45: 0 | Z45: 0 | AA45: 0 | AB45: 0 | AC45: 0 | AD45: 0 | AE45: 0 | AF45: 0 | AG45: 0 | AH45: =SUM(C45:AG45) -> 0
A46: Reposición Articulos cocina | B46: =AH46/$AH$10 -> 0 | C46: 0 | D46: 0 | E46: 0 | F46: 0 | G46: 0 | H46: 0 | I46: 0 | J46: 0 | K46: 0 | L46: 0 | M46: 0 | N46: 0 | O46: 0 | P46: 0 | Q46: 0 | R46: 0 | S46: 0 | T46: 0 | U46: 0 | V46: 0 | W46: 0 | X46: 0 | Y46: 0 | Z46: 0 | AA46: 0 | AB46: 0 | AC46: 0 | AD46: 0 | AE46: 0 | AF46: 0 | AG46: 0 | AH46: =SUM(C46:AG46) -> 0
A47: Reposición articulos salón | B47: =AH47/$AH$10 -> 0 | C47: 0 | D47: 0 | E47: 0 | F47: 0 | G47: 0 | H47: 0 | I47: 0 | J47: 0 | K47: 0 | L47: 0 | M47: 0 | N47: 0 | O47: 0 | P47: 0 | Q47: 0 | R47: 0 | S47: 0 | T47: 0 | U47: 0 | V47: 0 | W47: 0 | X47: 0 | Y47: 0 | Z47: 0 | AA47: 0 | AB47: 0 | AC47: 0 | AD47: 0 | AE47: 0 | AF47: 0 | AG47: 0 | AH47: =SUM(C47:AG47) -> 0
A48: Reparaciones mano de obra | B48: =AH48/$AH$10 -> 0.0040606982 | C48: 0 | D48: 0 | E48: 0 | F48: 0 | G48: 0 | H48: 30000 | I48: 0 | J48: 0 | K48: 0 | L48: 0 | M48: 0 | N48: 0 | O48: 0 | P48: 0 | Q48: 0 | R48: 0 | S48: 0 | T48: 0 | U48: 0 | V48: 0 | W48: 0 | X48: 0 | Y48: 120000 | Z48: 0 | AA48: 0 | AB48: 0 | AC48: 0 | AD48: 0 | AE48: 0 | AF48: 0 | AG48: 0 | AH48: =SUM(C48:AG48) -> 150000
A49: Reparaciones articulos | B49: =AH49/$AH$10 -> 0.0026259182 | C49: 0 | D49: 0 | E49: 0 | F49: 0 | G49: 0 | H49: 0 | I49: 0 | J49: 0 | K49: 0 | L49: 0 | M49: 0 | N49: 2000 | O49: 0 | P49: 0 | Q49: 0 | R49: 0 | S49: 0 | T49: 0 | U49: 0 | V49: 0 | W49: 0 | X49: 0 | Y49: 95000 | Z49: 0 | AA49: 0 | AB49: 0 | AC49: 0 | AD49: 0 | AE49: 0 | AF49: 0 | AG49: 0 | AH49: =SUM(C49:AG49) -> 97000
A50: Reparaciones maquinaria | B50: =AH50/$AH$10 -> 0 | C50: 0 | D50: 0 | E50: 0 | F50: 0 | G50: 0 | H50: 0 | I50: 0 | J50: 0 | K50: 0 | L50: 0 | M50: 0 | N50: 0 | O50: 0 | P50: 0 | Q50: 0 | R50: 0 | S50: 0 | T50: 0 | U50: 0 | V50: 0 | W50: 0 | X50: 0 | Y50: 0 | Z50: 0 | AA50: 0 | AB50: 0 | AC50: 0 | AD50: 0 | AE50: 0 | AF50: 0 | AG50: 0 | AH50: =SUM(C50:AG50) -> 0
... A52: Fee | B52: =AH52/$AH$10 -> 0.077673902 | C52: 0 | D52: 0 | E52: 0 | F52: 0 | G52: 0 | H52: 0 | I52: 0 | J52: 0 | K52: 0 | L52: 0 | M52: 0 | N52: 2869232 | O52: 0 | P52: 0 | Q52: 0 | R52: 0 | S52: 0 | T52: 0 | U52: 0 | V52: 0 | W52: 0 | X52: 0 | Y52: 0 | Z52: 0 | AA52: 0 | AB52: 0 | AC52: 0 | AD52: 0 | AE52: 0 | AF52: 0 | AG52: 0 | AH52: =SUM(C52:AG52) -> 2869232
A53: Administración y finanzas | B53: =AH53/$AH$10 -> 0.0018138056 | C53: =sum(C54:C61) -> 0 | D53: =sum(D54:D61) -> 0 | E53: =sum(E54:E61) -> 0 | F53: =sum(F54:F61) -> 0 | G53: =sum(G54:G61) -> 9401 | H53: =sum(H54:H61) -> 3950 | I53: =sum(I54:I61) -> 0 | J53: =sum(J54:J61) -> 0 | ... AE53: =sum(AE54:AE61) -> 0 | AF53: =SUM(AF54:AF61) -> 0 | AG53: =sum(AG54:AG61) -> 0 | AH53: =SUM(AH54:AH61) -> 67001
A54: Comisiones cuenta corriente | B54: =AH54/$AH$10 -> 0.00010693172 | C54: 0 | D54: 0 | E54: 0 | F54: 0 | G54: 0 | H54: 3950 | I54: 0 | J54: 0 | K54: 0 | L54: 0 | M54: 0 | N54: 0 | O54: 0 | P54: 0 | Q54: 0 | R54: 0 | S54: 0 | T54: 0 | U54: 0 | V54: 0 | W54: 0 | X54: 0 | Y54: 0 | Z54: 0 | AA54: 0 | AB54: 0 | AC54: 0 | AD54: 0 | AE54: 0 | AF54: 0 | AG54: 0 | AH54: =SUM(C54:AG54) -> 3950
A55: Contadora | B55: =AH55/$AH$10 -> 0 | C55: 0 | D55: 0 | E55: 0 | F55: 0 | G55: 0 | H55: 0 | I55: 0 | J55: 0 | K55: 0 | L55: 0 | M55: 0 | N55: 0 | O55: 0 | P55: 0 | Q55: 0 | R55: 0 | S55: 0 | T55: 0 | U55: 0 | V55: 0 | W55: 0 | X55: 0 | Y55: 0 | Z55: 0 | AA55: 0 | AB55: 0 | AC55: 0 | AD55: 0 | AE55: 0 | AF55: 0 | AG55: 0 | AH55: =SUM(C55:AG55) -> 0
A56: Patentes comerciales | B56: =AH56/$AH$10 -> 0 | C56: 0 | D56: 0 | E56: 0 | F56: 0 | G56: 0 | H56: 0 | I56: 0 | J56: 0 | K56: 0 | L56: 0 | M56: 0 | N56: 0 | O56: 0 | P56: 0 | Q56: 0 | R56: 0 | S56: 0 | T56: 0 | U56: 0 | V56: 0 | W56: 0 | X56: 0 | Y56: 0 | Z56: 0 | AA56: 0 | AB56: 0 | AC56: 0 | AD56: 0 | AE56: 0 | AF56: 0 | AG56: 0 | AH56: =SUM(C56:AG56) -> 0
A57: Insumos de oficina | B57: =AH57/$AH$10 -> 0.00078915609 | C57: 0 | D57: 0 | E57: 0 | F57: 0 | G57: 9401 | H57: 0 | I57: 0 | J57: 0 | K57: 0 | L57: 0 | M57: 19750 | N57: 0 | O57: 0 | P57: 0 | Q57: 0 | R57: 0 | S57: 0 | T57: 0 | U57: 0 | V57: 0 | W57: 0 | X57: 0 | Y57: 0 | Z57: 0 | AA57: 0 | AB57: 0 | AC57: 0 | AD57: 0 | AE57: 0 | AF57: 0 | AG57: 0 | AH57: =SUM(C57:AG57) -> 29151
A58: Wasabil | B58: =AH58/$AH$10 -> 0 | C58: 0 | D58: 0 | E58: 0 | F58: 0 | G58: 0 | H58: 0 | I58: 0 | J58: 0 | K58: 0 | L58: 0 | M58: 0 | N58: 0 | O58: 0 | P58: 0 | Q58: 0 | R58: 0 | S58: 0 | T58: 0 | U58: 0 | V58: 0 | W58: 0 | X58: 0 | Y58: 0 | Z58: 0 | AA58: 0 | AB58: 0 | AC58: 0 | AD58: 0 | AE58: 0 | AF58: 0 | AG58: 0 | AH58: =SUM(C58:AG58) -> 0
A59: Devolución clientes | B59: =AH59/$AH$10 -> 0.00075528987 | C59: 0 | D59: 0 | E59: 0 | F59: 0 | G59: 0 | H59: 0 | I59: 0 | J59: 0 | K59: 0 | L59: 0 | M59: 0 | N59: 0 | O59: 0 | P59: 0 | Q59: 0 | R59: 0 | S59: 0 | T59: 0 | U59: 0 | V59: 0 | W59: 27900 | X59: 0 | Y59: 0 | Z59: 0 | AA59: 0 | AB59: 0 | AC59: 0 | AD59: 0 | AE59: 0 | AF59: 0 | AG59: 0 | AH59: =SUM(C59:AG59) -> 27900
A60: Reuniones ejecutivas | B60: =AH60/$AH$10 -> 0 | C60: 0 | D60: 0 | E60: 0 | F60: 0 | G60: 0 | H60: 0 | I60: 0 | J60: 0 | K60: 0 | L60: 0 | M60: 0 | N60: 0 | O60: 0 | P60: 0 | Q60: 0 | R60: 0 | S60: 0 | T60: 0 | U60: 0 | V60: 0 | W60: 0 | X60: 0 | Y60: 0 | Z60: 0 | AA60: 0 | AB60: 0 | AC60: 0 | AD60: 0 | AE60: 0 | AF60: 0 | AG60: 0 | AH60: =SUM(C60:AG60) -> 0
A61: Certificados | B61: =AH61/$AH$10 -> 0.00016242793 | C61: 0 | D61: 0 | E61: 0 | F61: 0 | G61: 0 | H61: 0 | I61: 0 | J61: 0 | K61: 0 | L61: 0 | M61: 0 | N61: 0 | O61: 0 | P61: 0 | Q61: 0 | R61: 0 | S61: 0 | T61: 0 | U61: 6000 | V61: 0 | W61: 0 | X61: 0 | Y61: 0 | Z61: 0 | AA61: 0 | AB61: 0 | AC61: 0 | AD61: 0 | AE61: 0 | AF61: 0 | AG61: 0 | AH61: =SUM(C61:AG61) -> 6000
A63: Marketing | B63: =AH63/$AH$10 -> 0.030967183 | C63: =sum(C64:C73) -> 0 | D63: =sum(D64:D73) -> 0 | E63: =sum(E64:E73) -> 58245 | F63: =sum(F64:F73) -> 0 | G63: =sum(G64:G73) -> 0 | H63: =sum(H64:H73) -> 0 | I63: =sum(I64:I73) -> 108969 | J63: =sum(J64:J73) -> 0 | ... AB63: =sum(AB64:AB73) -> 0 | AC63: =sum(AC64:AC74) -> 111003 | AD63: =sum(AD64:AD73) -> 0 | AE63: =sum(AE64:AE73) -> 0 | AF63: =sum(AF64:AF73) -> 0 | AG63: =sum(AG64:AG73) -> 600000 | AH63: =SUM(AH64:AH74) -> 1143911
A64: Mercat | B64: =AH64/$AH$10 -> 0.0088540276 | C64: 0 | D64: 0 | E64: 0 | F64: 0 | G64: 0 | H64: 0 | I64: 108969 | J64: 0 | K64: 0 | L64: 0 | M64: 0 | N64: 0 | O64: 0 | P64: 0 | Q64: 0 | R64: 0 | S64: 0 | T64: 0 | U64: 0 | V64: 0 | W64: 0 | X64: 0 | Y64: 0 | Z64: =109047+109047 -> 218094 | AA64: 0 | AB64: 0 | AC64: 0 | AD64: 0 | AE64: 0 | AF64: 0 | AG64: 0 | AH64: =SUM(C64:AG64) -> 327063
A65: Brevo | B65: =AH65/$AH$10 -> 0.0015767691 | C65: 0 | D65: 0 | E65: 58245 | F65: 0 | G65: 0 | H65: 0 | I65: 0 | J65: 0 | K65: 0 | L65: 0 | M65: 0 | N65: 0 | O65: 0 | P65: 0 | Q65: 0 | R65: 0 | S65: 0 | T65: 0 | U65: 0 | V65: 0 | W65: 0 | X65: 0 | Y65: 0 | Z65: 0 | AA65: 0 | AB65: 0 | AC65: 0 | AD65: 0 | AE65: 0 | AF65: 0 | AG65: 0 | AH65: =SUM(C65:AG65) -> 58245
A66: Fiweex | B66: =AH66/$AH$10 -> 0.0012885949 | C66: 0 | D66: 0 | E66: 0 | F66: 0 | G66: 0 | H66: 0 | I66: 0 | J66: 0 | K66: 0 | L66: 0 | M66: 0 | N66: 0 | O66: 0 | P66: 0 | Q66: 0 | R66: 0 | S66: 0 | T66: 0 | U66: 0 | V66: 0 | W66: 0 | X66: 0 | Y66: 0 | Z66: 0 | AA66: 47600 | AB66: 0 | AC66: 0 | AD66: 0 | AE66: 0 | AF66: 0 | AG66: 0 | AH66: =SUM(C66:AG66) -> 47600
A67: Fujifilm instax | B67: =AH67/$AH$10 -> 0 | C67: 0 | D67: 0 | E67: 0 | F67: 0 | G67: 0 | H67: 0 | I67: 0 | J67: 0 | K67: 0 | L67: 0 | M67: 0 | N67: 0 | O67: 0 | P67: 0 | Q67: 0 | R67: 0 | S67: 0 | T67: 0 | U67: 0 | V67: 0 | W67: 0 | X67: 0 | Y67: 0 | Z67: 0 | AA67: 0 | AB67: 0 | AC67: 0 | AD67: 0 | AE67: 0 | AF67: 0 | AG67: 0 | AH67: =SUM(C67:AG67) -> 0
A68: Resos | B68: =AH68/$AH$10 -> 0.0027751624 | C68: 0 | D68: 0 | E68: 0 | F68: 0 | G68: 0 | H68: 0 | I68: 0 | J68: 0 | K68: 0 | L68: 0 | M68: 0 | N68: 0 | O68: 0 | P68: 0 | Q68: 0 | R68: 0 | S68: 0 | T68: 0 | U68: 0 | V68: 0 | W68: 0 | X68: 0 | Y68: 0 | Z68: 0 | AA68: 0 | AB68: 0 | AC68: 102513 | AD68: 0 | AE68: 0 | AF68: 0 | AG68: 0 | AH68: =SUM(C68:AG68) -> 102513
A69: HappyCow | B69: =AH69/$AH$10 -> 0 | C69: 0 | D69: 0 | E69: 0 | F69: 0 | G69: 0 | H69: 0 | I69: 0 | J69: 0 | K69: 0 | L69: 0 | M69: 0 | N69: 0 | O69: 0 | P69: 0 | Q69: 0 | R69: 0 | S69: 0 | T69: 0 | U69: 0 | V69: 0 | W69: 0 | X69: 0 | Y69: 0 | Z69: 0 | AA69: 0 | AB69: 0 | AC69: 0 | AD69: 0 | AE69: 0 | AF69: 0 | AG69: 0 | AH69: =SUM(C69:AG69) -> 0
A70: Meta Ads | B70: =AH70/$AH$10 -> 0 | C70: 0 | D70: 0 | E70: 0 | F70: 0 | G70: 0 | H70: 0 | I70: 0 | J70: 0 | K70: 0 | L70: 0 | M70: 0 | N70: 0 | O70: 0 | P70: 0 | Q70: 0 | R70: 0 | S70: 0 | T70: 0 | U70: 0 | V70: 0 | W70: 0 | X70: 0 | Y70: 0 | Z70: 0 | AA70: 0 | AB70: 0 | AC70: 0 | AD70: 0 | AE70: 0 | AF70: 0 | AG70: 0 | AH70: =SUM(C70:AG70) -> 0
A71: Influencers | B71: =AH71/$AH$10 -> 0 | C71: 0 | D71: 0 | E71: 0 | F71: 0 | G71: 0 | H71: 0 | I71: 0 | J71: 0 | K71: 0 | L71: 0 | M71: 0 | N71: 0 | O71: 0 | P71: 0 | Q71: 0 | R71: 0 | S71: 0 | T71: 0 | U71: 0 | V71: 0 | W71: 0 | X71: 0 | Y71: 0 | Z71: 0 | AA71: 0 | AB71: 0 | AC71: 0 | AD71: 0 | AE71: 0 | AF71: 0 | AG71: 0 | AH71: =SUM(C71:AG71) -> 0
A72: Chatfuel | B72: =AH72/$AH$10 -> 0 | C72: 0 | D72: 0 | E72: 0 | F72: 0 | G72: 0 | H72: 0 | I72: 0 | J72: 0 | K72: 0 | L72: 0 | M72: 0 | N72: 0 | O72: 0 | P72: 0 | Q72: 0 | R72: 0 | S72: 0 | T72: 0 | U72: 0 | V72: 0 | W72: 0 | X72: 0 | Y72: 0 | Z72: 0 | AA72: 0 | AB72: 0 | AC72: 0 | AD72: 0 | AE72: 0 | AF72: 0 | AG72: 0 | AH72: =SUM(C72:AG72) -> 0
A73: Community manager | B73: =AH73/$AH$10 -> 0.016242793 | C73: 0 | D73: 0 | E73: 0 | F73: 0 | G73: 0 | H73: 0 | I73: 0 | J73: 0 | K73: 0 | L73: 0 | M73: 0 | N73: 0 | O73: 0 | P73: 0 | Q73: 0 | R73: 0 | S73: 0 | T73: 0 | U73: 0 | V73: 0 | W73: 0 | X73: 0 | Y73: 0 | Z73: 0 | AA73: 0 | AB73: 0 | AC73: 0 | AD73: 0 | AE73: 0 | AF73: 0 | AG73: 600000 | AH73: =SUM(C73:AG73) -> 600000
A74: Microsoft | B74: =AH74/$AH$10 -> 0.00022983552 | C74: 0 | D74: 0 | E74: 0 | F74: 0 | G74: 0 | H74: 0 | I74: 0 | J74: 0 | K74: 0 | L74: 0 | M74: 0 | N74: 0 | O74: 0 | P74: 0 | Q74: 0 | R74: 0 | S74: 0 | T74: 0 | U74: 0 | V74: 0 | W74: 0 | X74: 0 | Y74: 0 | Z74: 0 | AA74: 0 | AB74: 0 | AC74: 8490 | AD74: 0 | AE74: 0 | AF74: 0 | AG74: 0 | AH74: =SUM(C74:AG74) -> 8490
A76: Inversiones activos | B76: =AH76/$AH$10 -> 0.089335361 | C76: =sum(C77:C79) -> 0 | D76: =sum(D77:D79) -> 0 | E76: =sum(E77:E79) -> 0 | F76: =sum(F77:F79) -> 0 | G76: =sum(G77:G79) -> 0 | H76: =sum(H77:H79) -> 0 | I76: =sum(I77:I79) -> 0 | J76: =sum(J77:J79) -> 0 | ... M76: =sum(M77:M79) -> 0 | N76: =sum(N77:N80) -> 1000000 | O76: =sum(O77:O79) -> 0 | P76: =sum(P77:P80) -> 2300000 | Q76: =sum(Q77:Q79) -> 0 | R76: =sum(R77:R79) -> 0 | S76: =sum(S77:S79) -> 0 | T76: =sum(T77:T79) -> 0 | U76: =sum(U77:U79) -> 0 | V76: =sum(V77:V79) -> 0 | W76: =sum(W77:W79) -> 0 | X76: =sum(X77:X79) -> 0 | ... AG76: =sum(AG77:AG79) -> 0 | AH76: =sum(AH77:AH80) -> 3300000
A77: Nuevas maquinaria | B77: =AH77/$AH$10 -> 0 | C77: 0 | D77: 0 | E77: 0 | F77: 0 | G77: 0 | H77: 0 | I77: 0 | J77: 0 | K77: 0 | L77: 0 | M77: 0 | N77: 0 | O77: 0 | P77: 0 | Q77: 0 | R77: 0 | S77: 0 | T77: 0 | U77: 0 | V77: 0 | W77: 0 | X77: 0 | Y77: 0 | Z77: 0 | AA77: 0 | AB77: 0 | AC77: 0 | AD77: 0 | AE77: 0 | AF77: 0 | AG77: 0 | AH77: =SUM(C77:AG77) -> 0
A78: Nueva decoración y muebles | B78: =AH78/$AH$10 -> 0 | C78: 0 | D78: 0 | E78: 0 | F78: 0 | G78: 0 | H78: 0 | I78: 0 | J78: 0 | K78: 0 | L78: 0 | M78: 0 | N78: 0 | O78: 0 | P78: 0 | Q78: 0 | R78: 0 | S78: 0 | T78: 0 | U78: 0 | V78: 0 | W78: 0 | X78: 0 | Y78: 0 | Z78: 0 | AA78: 0 | AB78: 0 | AC78: 0 | AD78: 0 | AE78: 0 | AF78: 0 | AG78: 0 | AH78: =SUM(C78:AG78) -> 0
A79: Remodelaciones | B79: =AH79/$AH$10 -> 0 | C79: 0 | D79: 0 | E79: 0 | F79: 0 | G79: 0 | H79: 0 | I79: 0 | J79: 0 | K79: 0 | L79: 0 | M79: 0 | N79: 0 | O79: 0 | P79: 0 | Q79: 0 | R79: 0 | S79: 0 | T79: 0 | U79: 0 | V79: 0 | W79: 0 | X79: 0 | Y79: 0 | Z79: 0 | AA79: 0 | AB79: 0 | AC79: 0 | AD79: 0 | AE79: 0 | AF79: 0 | AG79: 0 | AH79: =SUM(C79:AG79) -> 0
A80: Kojo | B80: =AH80/$AH$10 -> 0.089335361 | C80: 0 | D80: 0 | E80: 0 | F80: 0 | G80: 0 | H80: 0 | I80: 0 | J80: 0 | K80: 0 | L80: 0 | M80: 0 | N80: 1000000 | O80: 0 | P80: 2300000 | Q80: 0 | R80: 0 | S80: 0 | T80: 0 | U80: 0 | V80: 0 | W80: 0 | X80: 0 | Y80: 0 | Z80: 0 | AA80: 0 | AB80: 0 | AC80: 0 | AD80: 0 | AE80: 0 | AF80: 0 | AG80: 0 | AH80: =SUM(C80:AG80) -> 3300000
A82: Dinero temporal | B82: =AH82/$AH$10 -> 0.10506342 | C82: =sum(C83:C86) -> 0 | D82: =sum(D83:D86) -> 499779 | E82: =sum(E83:E86) -> 286800 | F82: =sum(F83:F86) -> 0 | G82: =sum(G83:G86) -> 0 | H82: =sum(H83:H86) -> 141567 | I82: =sum(I83:I86) -> 0 | J82: =sum(J83:J86) -> 0 | ... AH82: =sum(AH83:AH86) -> 3880986
A83: Delifast | B83: =AH83/$AH$10 -> 0.020849032 | C83: 0 | D83: 0 | E83: 0 | F83: 0 | G83: 0 | H83: 141567 | I83: 0 | J83: 0 | K83: 0 | L83: 0 | M83: 0 | N83: 0 | O83: 192127 | P83: 0 | Q83: 0 | R83: 0 | S83: 213311 | T83: 0 | U83: 0 | V83: 0 | W83: 0 | X83: 0 | Y83: 0 | Z83: 223147 | AA83: 0 | AB83: 0 | AC83: 0 | AD83: 0 | AE83: 0 | AF83: 0 | AG83: 0 | AH83: =SUM(C83:AG83) -> 770152
A84: Uber direct | B84: =AH84/$AH$10 -> 0 | C84: 0 | D84: 0 | E84: 0 | F84: 0 | G84: 0 | H84: 0 | I84: 0 | J84: 0 | K84: 0 | L84: 0 | M84: 0 | N84: 0 | O84: 0 | P84: 0 | Q84: 0 | R84: 0 | S84: 0 | T84: 0 | U84: 0 | V84: 0 | W84: 0 | X84: 0 | Y84: 0 | Z84: 0 | AA84: 0 | AB84: 0 | AC84: 0 | AD84: 0 | AE84: 0 | AF84: 0 | AG84: 0 | AH84: =SUM(C84:AG84) -> 0
A85: Monto delivery | B85: =AH85/$AH$10 -> 0.02122933 | C85: 0 | D85: 0 | E85: 286800 | F85: 0 | G85: 0 | H85: 0 | I85: 0 | J85: 0 | K85: 0 | L85: 0 | M85: 230800 | N85: 0 | O85: 0 | P85: 0 | Q85: 0 | R85: 0 | S85: =38900+39900+49800+30000+3000 -> 161600 | T85: 0 | U85: 105000 | V85: 0 | W85: 0 | X85: 0 | Y85: 0 | Z85: 0 | AA85: 0 | AB85: 0 | AC85: 0 | AD85: 0 | AE85: 0 | AF85: 0 | AG85: 0 | AH85: =SUM(C85:AG85) -> 784200
A86: Propina personal | B86: =AH86/$AH$10 -> 0.062985057 | C86: 0 | D86: 499779 | E86: 0 | F86: 0 | G86: 0 | H86: 0 | I86: 0 | J86: 0 | K86: 506430 | L86: 0 | M86: 0 | N86: 0 | O86: 0 | P86: 0 | Q86: 0 | R86: 482637 | S86: 0 | T86: 0 | U86: 0 | V86: 0 | W86: 0 | X86: 0 | Y86: 0 | Z86: 387781 | AA86: 0 | AB86: 0 | AC86: 0 | AD86: 0 | AE86: 0 | AF86: 450007 | AG86: 0 | AH86: =SUM(C86:AG86) -> 2326634
A88: RRHH | B88: =AH88/$AH$10 -> 0.30361789 | C88: =sum(C89:C97) -> 214500 | D88: =sum(D89:D97) -> 0 | E88: =sum(E89:E97) -> 163000 | F88: =sum(F89:F97) -> 277750 | G88: =sum(G89:G97) -> 824125 | H88: =sum(H89:H97) -> 0 | I88: =sum(I89:I97) -> 0 | J88: =sum(J89:J97) -> 0 | ... AG88: =sum(AG89:AG97) -> 6690949 | AH88: =SUM(AH89:AH97) -> 11215481
A89: Turnos feriados | B89: =AH89/$AH$10 -> 0 | C89: 0 | D89: 0 | E89: 0 | F89: 0 | G89: 0 | H89: 0 | I89: 0 | J89: 0 | K89: 0 | L89: 0 | M89: 0 | N89: 0 | O89: 0 | P89: 0 | Q89: 0 | R89: 0 | S89: 0 | T89: 0 | U89: 0 | V89: 0 | W89: 0 | X89: 0 | Y89: 0 | Z89: 0 | AA89: 0 | AB89: 0 | AC89: 0 | AD89: 0 | AE89: 0 | AF89: 0 | AG89: 0 | AH89: =SUM(C89:AG89) -> 0
A90: Sueldo personal | B90: =AH90/$AH$10 -> 0.23940724 | C90: 162500 | D90: 0 | E90: 56000 | F90: 0 | G90: 824125 | H90: 0 | I90: 0 | J90: 0 | K90: 0 | L90: 0 | M90: 48000 | N90: 0 | O90: 0 | P90: 0 | Q90: =200000+200000+180000+150000+100000+200000 -> 1030000 | R90: 0 | S90: 32000 | T90: 0 | U90: 0 | V90: 0 | W90: 0 | X90: 0 | Y90: 0 | Z90: 0 | AA90: 0 | AB90: 0 | AC90: 0 | AD90: 0 | AE90: 0 | AF90: 0 | AG90: =800000+551265+401262+500000+800225+570000+600000+700000+611625+369072+380000+357500+50000 -> 6690949 | AH90: =SUM(C90:AG90) -> 8843574
A91: Traslados personal | B91: =AH91/$AH$10 -> 5.6308349e-05 | C91: 0 | D91: 0 | E91: 0 | F91: 0 | G91: 0 | H91: 0 | I91: 0 | J91: 0 | K91: 0 | L91: 0 | M91: 0 | N91: 0 | O91: 0 | P91: 0 | Q91: 0 | R91: 0 | S91: 0 | T91: 0 | U91: 2080 | V91: 0 | W91: 0 | X91: 0 | Y91: 0 | Z91: 0 | AA91: 0 | AB91: 0 | AC91: 0 | AD91: 0 | AE91: 0 | AF91: 0 | AG91: 0 | AH91: =SUM(C91:AG91) -> 2080
A92: Turnos extras | B92: =AH92/$AH$10 -> 0.0048457666 | C92: 52000 | D92: 0 | E92: =20000+20000+22000+25000 -> 87000 | F92: 0 | G92: 0 | H92: 0 | I92: 0 | J92: 0 | K92: 20000 | L92: 0 | M92: 0 | N92: 0 | O92: 0 | P92: 0 | Q92: 20000 | R92: 0 | S92: 0 | T92: 0 | U92: 0 | V92: 0 | W92: 0 | X92: 0 | Y92: 0 | Z92: 0 | AA92: 0 | AB92: 0 | AC92: 0 | AD92: 0 | AE92: 0 | AF92: 0 | AG92: 0 | AH92: =SUM(C92:AG92) -> 179000
A93: Bonos | B93: =AH93/$AH$10 -> 0.0075190596 | C93: 0 | D93: 0 | E93: 0 | F93: =55550+55550+55550+55550+55550 -> 277750 | G93: 0 | H93: 0 | I93: 0 | J93: 0 | K93: 0 | L93: 0 | M93: 0 | N93: 0 | O93: 0 | P93: 0 | Q93: 0 | R93: 0 | S93: 0 | T93: 0 | U93: 0 | V93: 0 | W93: 0 | X93: 0 | Y93: 0 | Z93: 0 | AA93: 0 | AB93: 0 | AC93: 0 | AD93: 0 | AE93: 0 | AF93: 0 | AG93: 0 | AH93: =SUM(C93:AG93) -> 277750
A94: Previred | B94: =AH94/$AH$10 -> 0.05070667 | C94: 0 | D94: 0 | E94: 0 | F94: 0 | G94: 0 | H94: 0 | I94: 0 | J94: 0 | K94: 0 | L94: 0 | M94: 1873077 | N94: 0 | O94: 0 | P94: 0 | Q94: 0 | R94: 0 | S94: 0 | T94: 0 | U94: 0 | V94: 0 | W94: 0 | X94: 0 | Y94: 0 | Z94: 0 | AA94: 0 | AB94: 0 | AC94: 0 | AD94: 0 | AE94: 0 | AF94: 0 | AG94: 0 | AH94: =SUM(C94:AG94) -> 1873077
A95: Uniforme pesonal | B95: =AH95/$AH$10 -> 0 | C95: 0 | D95: 0 | E95: 0 | F95: 0 | G95: 0 | H95: 0 | I95: 0 | J95: 0 | K95: 0 | L95: 0 | M95: 0 | N95: 0 | O95: 0 | P95: 0 | Q95: 0 | R95: 0 | S95: 0 | T95: 0 | U95: 0 | V95: 0 | W95: 0 | X95: 0 | Y95: 0 | Z95: 0 | AA95: 0 | AB95: 0 | AC95: 0 | AD95: 0 | AE95: 0 | AF95: 0 | AG95: 0 | AH95: =SUM(C95:AG95) -> 0
A96: Finiquitos | B96: =AH96/$AH$10 -> 0 | C96: 0 | D96: 0 | E96: 0 | F96: 0 | G96: 0 | H96: 0 | I96: 0 | J96: 0 | K96: 0 | L96: 0 | M96: 0 | N96: 0 | O96: 0 | P96: 0 | Q96: 0 | R96: 0 | S96: 0 | T96: 0 | U96: 0 | V96: 0 | W96: 0 | X96: 0 | Y96: 0 | Z96: 0 | AA96: 0 | AB96: 0 | AC96: 0 | AD96: 0 | AE96: 0 | AF96: 0 | AG96: 0 | AH96: =SUM(C96:AG96) -> 0
A97: Recreación | B97: =AH97/$AH$10 -> 0.0010828529 | C97: 0 | D97: 0 | E97: 20000 | F97: 0 | G97: 0 | H97: 0 | I97: 0 | J97: 0 | K97: 0 | L97: 0 | M97: 0 | N97: 0 | O97: 0 | P97: 0 | Q97: 0 | R97: 0 | S97: 0 | T97: 0 | U97: 0 | V97: 0 | W97: 0 | X97: 0 | Y97: 0 | Z97: 0 | AA97: 0 | AB97: 0 | AC97: 20000 | AD97: 0 | AE97: 0 | AF97: 0 | AG97: 0 | AH97: =SUM(C97:AG97) -> 40000
A99: Impuestos fiscales | B99: =AH99/$AH$10 -> 0.12938974 | C99: =SUM(C100:C101) -> 0 | D99: =SUM(D100:D101) -> 0 | E99: =SUM(E100:E101) -> 0 | F99: =SUM(F100:F101) -> 0 | G99: =SUM(G100:G101) -> 0 | H99: =SUM(H100:H101) -> 0 | I99: =SUM(I100:I101) -> 0 | J99: =SUM(J100:J101) -> 0 | ... AH99: =SUM(AH100:AH101) -> 4779587
A100: Impuesto sobre la renta | B100: =AH100/$AH$10 -> 0 | C100: 0 | D100: 0 | E100: 0 | F100: 0 | G100: 0 | H100: 0 | I100: 0 | J100: 0 | K100: 0 | L100: 0 | M100: 0 | N100: 0 | O100: 0 | P100: 0 | Q100: 0 | R100: 0 | S100: 0 | T100: 0 | U100: 0 | V100: 0 | W100: 0 | X100: 0 | Y100: 0 | Z100: 0 | AA100: 0 | AB100: 0 | AC100: 0 | AD100: 0 | AE100: 0 | AF100: 0 | AG100: 0 | AH100: =SUM(C100:AG100) -> 0
A101: IVA | B101: =AH101/$AH$10 -> 0.12938974 | C101: 0 | D101: 0 | E101: 0 | F101: 0 | G101: 0 | H101: 0 | I101: 0 | J101: 0 | K101: 0 | L101: 0 | M101: 0 | N101: 0 | O101: 0 | P101: 0 | Q101: 0 | R101: 0 | S101: 0 | T101: 0 | U101: 4779587 | V101: 0 | W101: 0 | X101: 0 | Y101: 0 | Z101: 0 | AA101: 0 | AB101: 0 | AC101: 0 | AD101: 0 | AE101: 0 | AF101: 0 | AG101: 0 | AH101: =SUM(C101:AG101) -> 4779587
A103: Amortizaciones | AB103: =AB104+AB105 -> 1760416 | AH103: =AH104+AH105 -> 1760416
A104: Préstamo | C104: 0 | D104: 0 | E104: 0 | F104: 0 | G104: 0 | H104: 0 | I104: 0 | J104: 0 | K104: 0 | L104: 0 | M104: 0 | N104: 0 | O104: 0 | P104: 0 | Q104: 0 | R104: 0 | S104: 0 | T104: 0 | U104: 0 | V104: 0 | W104: 0 | X104: 0 | Y104: 0 | Z104: 0 | AA104: 0 | AB104: 1760416 | AC104: 0 | AD104: 0 | AE104: 0 | AF104: 0 | AG104: 0 | AH104: =sum(C104:AG104) -> 1760416
C105: 0 | D105: 0 | E105: 0 | F105: 0 | G105: 0 | H105: 0 | I105: 0 | J105: 0 | K105: 0 | L105: 0 | M105: 0 | N105: 0 | O105: 0 | P105: 0 | Q105: 0 | R105: 0 | S105: 0 | T105: 0 | U105: 0 | V105: 0 | W105: 0 | X105: 0 | Y105: 0 | Z105: 0 | AA105: 0 | AB105: 0 | AC105: 0 | AD105: 0 | AE105: 0 | AF105: 0 | AG105: 0 | AH105: =sum(C105:AG105) -> 0
A107: Total egresos conciliación | C107: =C99+C88+C82+C32+C76+C12+C104+C105 -> 221500 | D107: =D99+D88+D82+D32+D76+D12+D104+D105 -> 530079 | E107: =E99+E88+E82+E32+E76+E12+E104+E105 -> 1664266 | F107: =F99+F88+F82+F32+F76+F12+F104+F105 -> 1742522 | G107: =G99+G88+G82+G32+G76+G12+G104+G105 -> 917526 | H107: =H99+H88+H82+H32+H76+H12+H104+H105 -> 2006137 | I107: =I99+I88+I82+I32+I76+I12+I104+I105 -> 284181 | J107: =J99+J88+J82+J32+J76+J12+J104+J105 -> 15020 | ... AA107: =AA99+AA88+AA82+AA32+AA76+AA12+AA104+AA105 -> 1261495 | AB107: =AB99+AB88+AB82+AB32+AB76+AB12+AB104 -> 2010960 | AC107: =AC99+AC88+AC82+AC32+AC76+AC12+AC104+AC105 -> 496381 | AD107: =AD99+AD88+AD82+AD32+AD76+AD12+AD104+AD105 -> 413975 | AE107: =AE99+AE88+AE82+AE32+AE76+AE12+AE104+AE105 -> 7900 | AF107: =AF99+AF88+AF82+AF32+AF76+AF12+AF104+AF105 -> 492647 | AG107: =AG99+AG88+AG82+AG32+AG76+AG12+AG104+AG105 -> 9069130 | AH107: =sum(C107:AG107) -> 44942527
A108: Total egresos operativos | C108: =C99+C88+C32+C76+C12 -> 221500 | D108: =D99+D88+D32+D76+D12 -> 30300 | E108: =E99+E88+E32+E76+E12 -> 1377466 | F108: =F99+F88+F32+F76+F12 -> 1742522 | G108: =G99+G88+G32+G76+G12 -> 917526 | H108: =H99+H88+H32+H76+H12 -> 1864570 | I108: =I99+I88+I32+I76+I12 -> 284181 | J108: =J99+J88+J32+J76+J12 -> 15020 | ... AG108: =AG99+AG88+AG32+AG76+AG12 -> 9069130 | AH108: =sum(C108:AG108) -> 39301125
A110: Rentabilidad | B110: =AH110/$AH$10 -> -0.063933393 | C110: =C9-C108 -> 2351319 | D110: =D9-D108 -> 1290287 | E110: =E9-E108 -> -314748 | F110: =F9-F108 -> -330930 | G110: =G9-G108 -> -40785 | H110: =H9-H108 -> -630914 | I110: =I9-I108 -> 1807379 | J110: =J9-J108 -> 2254938 | ... AG110: =AG9-AG108 -> -8519313 | AH110: =AH10-AH108 -> -2361665

Sheet Abril
C1: 46113 | D1: 46114 | E1: 46115 | F1: 46116 | G1: 46117 | H1: 46118 | I1: 46119 | J1: 46120 | K1: 46121 | L1: 46122 | M1: 46123 | N1: 46124 | O1: 46125 | P1: 46126 | Q1: 46127 | R1: 46128 | S1: 46129 | T1: 46130 | U1: 46131 | V1: 46132 | W1: 46133 | X1: 46134 | Y1: 46135 | Z1: 46136 | AA1: 46137 | AB1: 46138 | AC1: 46139 | AD1: 46140 | AE1: 46141 | AF1: 46142 | AH1: Totales
A4: Ingresos
A5: Transbank | C5: =667957+79894+912033+8131+106219 -> 1774234 | D5: =870428+489261+37666+177465 -> 1574820 | E5: =677368+717856+225891+66960+8071 -> 1696146 | F5: =442216+1285065+46633 -> 1773914 | G5: =70050+356223+1336911+97849 -> 1861033 | H5: =1250181+271029 -> 1521210 | I5: =278271+38941+3951 -> 321163 | J5: =448991+400286+30010+16540 -> 895827 | K5: =695233+316979+154031 -> 1166243 | L5: =1212830+35505+702249+39857+39833+11091 -> 2041365 | M5: =28598+553457+575438+209192+44839 -> 1411524 | N5: =469020+74333+1223646+53906 -> 1820905 | O5: =201577+537734+6268 -> 745579 | P5: =145167+44517+14857 -> 204541 | Q5: =24289+496073+537042+13850 -> 1071254 | R5: =615469+288051+56897+5273 -> 965690 | S5: =436873+248785+45054+20606+50319 -> 801637 | T5: =838581+333876+70946+39857 -> 1283260 | U5: =1079633+553715+74732+85693 -> 1793773 | V5: =1136070+360409 -> 1496479 | W5: =112370+24288+19550 -> 156208 | X5: =366602+589928+13850 -> 970380 | Y5: =364875+36569+748326+68979 -> 1218749 | Z5: =883235+1011032+184880+17795+88085 -> 2185027 | AA5: =569436+14425+553991+69351+23318 -> 1230521 | AB5: =135713+1863773+31587+354162 -> 2385235 | AC5: =137009+999668+34576 -> 1171253 | AD5: =219722+66434 -> 286156 | AE5: =515463+115297+25807+43412 -> 699979 | AF5: =469886+543452+7807+109110 -> 1130255 | AG5: 0 | AH5: =SUM(C5:AG5) -> 37654360
A6: Transferencias | C6: 0 | D6: 0 | E6: 9020 | F6: 0 | G6: 0 | H6: 0 | I6: 0 | J6: 0 | K6: 0 | L6: 0 | M6: 0 | N6: 0 | O6: 0 | P6: 55000 | Q6: 25900 | R6: 0 | S6: 0 | T6: 0 | U6: 21455 | V6: 0 | W6: 0 | X6: 0 | Y6: 30240 | Z6: 1300 | AA6: 0 | AB6: 0 | AC6: 0 | AD6: 0 | AE6: 18950 | AF6: 0 | AG6: 0 | AH6: =SUM(C6:AG6) -> 161865
A7: Efectivo | C7: 0 | D7: 0 | E7: 0 | F7: 0 | G7: 0 | H7: 0 | I7: 0 | J7: 0 | K7: 0 | L7: 0 | M7: 0 | N7: 0 | O7: 0 | P7: 0 | Q7: 0 | R7: 0 | S7: 0 | T7: 0 | U7: 0 | V7: 0 | W7: 0 | X7: 0 | Y7: 0 | Z7: 0 | AA7: 0 | AB7: 0 | AC7: 0 | AD7: 200000 | AE7: 0 | AF7: 0 | AG7: 0 | AH7: =SUM(C7:AG7) -> 200000
A8: Uber | C8: 0 | D8: 0 | E8: 0 | F8: 0 | G8: 0 | H8: 0 | I8: 0 | J8: =503331+147765 -> 651096 | K8: 0 | L8: 0 | M8: 0 | N8: 0 | O8: 0 | P8: =295935+369316 -> 665251 | Q8: 0 | R8: 0 | S8: 0 | T8: 0 | U8: 0 | V8: 0 | W8: =426984+227006 -> 653990 | X8: 0 | Y8: 0 | Z8: 0 | AA8: 0 | AB8: 0 | AC8: 0 | AD8: =113291+558587 -> 671878 | AE8: 0 | AF8: 0 | AG8: 0 | AH8: =SUM(C8:AG8) -> 2642215
A9: Total bruto | C9: =SUM(C5:C8) -> 1774234 | D9: =SUM(D5:D8) -> 1574820 | E9: =SUM(E5:E8) -> 1705166 | F9: =SUM(F5:F8) -> 1773914 | G9: =SUM(G5:G8) -> 1861033 | H9: =SUM(H5:H8) -> 1521210 | I9: =SUM(I5:I8) -> 321163 | J9: =SUM(J5:J8) -> 1546923 | ... AH9: =SUM(AH5:AH8) -> 40658440
A10: Total neto | AH10: =AH9-AH83 -> 36439992
A12: Materia prima | B12: =AH12/$AH$10 -> 0.31195838 | C12: =sum(C13:C31) -> 655705 | D12: =sum(D13:D31) -> 92743 | E12: =sum(E13:E31) -> 71690 | F12: =sum(F13:F31) -> 56351 | G12: =sum(G15:G31) -> 12500 | H12: =sum(H13:H31) -> 500890 | I12: =sum(I13:I31) -> 1184070 | J12: =sum(J13:J31) -> 571936 | K12: =sum(K13:K31) -> 680475 | L12: =sum(L13:L31) -> 179150 | M12: =sum(M13:M31) -> 14380 | N12: =sum(N13:N31) -> 0 | O12: =sum(O13:O31) -> 330721 | ... AH12: =sum(AH13:AH31) -> 11367761
A13: MP | B13: =AH13/$AH$10 -> 0.02472989 | C13: =84000+50000 -> 134000 | D13: 50000 | E13: 59490 | F13: 0 | G13: 0 | H13: 62490 | I13: 0 | J13: 84000 | K13: 5200 | L13: 0 | M13: 14380 | N13: 0 | O13: 72470 | P13: 0 | Q13: 0 | R13: 0 | S13: 65000 | T13: 0 | U13: 0 | V13: 0 | W13: =95287+13990 -> 109277 | X13: 0 | Y13: 56490 | Z13: =41960+71000 -> 112960 | AA13: =10000+7800 -> 17800 | AB13: 0 | AC13: 0 | AD13: 0 | AE13: 84000+55000 | AF13: =37600+20000 -> 57600 | AG13: 0 | AH13: =SUM(C13:AG13) -> 901157
A14: Arroz | B14: =AH14/$AH$10 -> 0.013084525 | C14: 0 | D14: 0 | E14: 0 | F14: 0 | G14: 0 | H14: 0 | I14: 119200 | J14: 0 | K14: 0 | L14: 0 | M14: 0 | N14: 0 | O14: 0 | P14: 0 | Q14: 119200 | R14: 0 | S14: 0 | T14: 0 | U14: 0 | V14: 0 | W14: 0 | X14: 119200 | Y14: 0 | Z14: 0 | AA14: 0 | AB14: 0 | AC14: 0 | AD14: 0 | AE14: 119200 | AF14: 0 | AG14: 0 | AH14: =SUM(C14:AG14) -> 476800
A15: Hod Food | B15: =AH15/$AH$10 -> 0.067389312 | C15: 0 | D15: 0 | E15: 0 | F15: 0 | G15: 0 | H15: 0 | I15: 672333 | J15: 0 | K15: 0 | L15: 0 | M15: 0 | N15: 0 | O15: 0 | P15: 599256 | Q15: 0 | R15: 0 | S15: 0 | T15: 0 | U15: 0 | V15: 0 | W15: 399007 | X15: 0 | Y15: 0 | Z15: 0 | AA15: 0 | AB15: 0 | AC15: 0 | AD15: 577753 | AE15: 0 | AF15: 207317 | AG15: 0 | AH15: =SUM(C15:AG15) -> 2455666
A16: Seitan | B16: =AH16/$AH$10 -> 0.0084514837 | C16: 0 | D16: 0 | E16: 0 | F16: 0 | G16: 0 | H16: 0 | I16: 153986 | J16: 0 | K16: 0 | L16: 0 | M16: 0 | N16: 0 | O16: 0 | P16: 0 | Q16: 0 | R16: 0 | S16: 0 | T16: 0 | U16: 0 | V16: 0 | W16: 0 | X16: 0 | Y16: 0 | Z16: 0 | AA16: 0 | AB16: 0 | AC16: 0 | AD16: 0 | AE16: 0 | AF16: 153986 | AG16: 0 | AH16: =SUM(C16:AG16) -> 307972
A17: Palta | B17: =AH17/$AH$10 -> 0.036284558 | C17: 0 | D17: 0 | E17: 0 | F17: 0 | G17: 0 | H17: 428400 | I17: 0 | J17: 0 | K17: 0 | L17: 0 | M17: 0 | N17: 0 | O17: 0 | P17: 0 | Q17: 0 | R17: 401625 | S17: 0 | T17: 0 | U17: 156604 | V17: 0 | W17: 0 | X17: 0 | Y17: 0 | Z17: 335580 | AA17: 0 | AB17: 0 | AC17: 0 | AD17: 0 | AE17: 0 | AF17: 0 | AG17: 0 | AH17: =SUM(C17:AG17) -> 1322209
A18: Champiñon | B18: =AH18/$AH$10 -> 0.0073476965 | C18: 0 | D18: 0 | E18: 0 | F18: 0 | G18: 0 | H18: 0 | I18: 0 | J18: 0 | K18: 0 | L18: 0 | M18: 0 | N18: 0 | O18: 0 | P18: 0 | Q18: 0 | R18: 0 | S18: 0 | T18: 0 | U18: 0 | V18: 0 | W18: 0 | X18: 267750 | Y18: 0 | Z18: 0 | AA18: 0 | AB18: 0 | AC18: 0 | AD18: 0 | AE18: 0 | AF18: 0 | AG18: 0 | AH18: =SUM(C18:AG18) -> 267750
A19: Verduras | B19: =AH19/$AH$10 -> 0.066945404 | C19: 139825 | D19: 0 | E19: 0 | F19: 0 | G19: 0 | H19: 0 | I19: 0 | J19: 160650 | K19: 628405 | L19: 0 | M19: 0 | N19: 0 | O19: 0 | P19: 0 | Q19: 608450 | R19: 0 | S19: 0 | T19: 0 | U19: 0 | V19: 0 | W19: 413400 | X19: 0 | Y19: 0 | Z19: 0 | AA19: 0 | AB19: 0 | AC19: 0 | AD19: 0 | AE19: 488760 | AF19: 0 | AG19: 0 | AH19: =SUM(C19:AG19) -> 2439490
A20: shen | B20: =AH20/$AH$10 -> 0.017248357 | C20: 169575 | D20: 0 | E20: 0 | F20: 0 | G20: 0 | H20: 0 | I20: 0 | J20: 0 | K20: 0 | L20: 98770 | M20: 0 | N20: 0 | O20: 0 | P20: 0 | Q20: 0 | R20: 0 | S20: 101150 | T20: 0 | U20: 0 | V20: 84000 | W20: 0 | X20: 0 | Y20: 84000 | Z20: 0 | AA20: 0 | AB20: 0 | AC20: 0 | AD20: 0 | AE20: 91035 | AF20: 0 | AG20: 0 | AH20: =SUM(C20:AG20) -> 628530
A21: Mozzen | B21: =AH21/$AH$10 -> 0.0077745077 | C21: 0 | D21: 0 | E21: 0 | F21: 0 | G21: 0 | H21: 0 | I21: 0 | J21: 283303 | K21: 0 | L21: 0 | M21: 0 | N21: 0 | O21: 0 | P21: 0 | Q21: 0 | R21: 0 | S21: 0 | T21: 0 | U21: 0 | V21: 0 | W21: 0 | X21: 0 | Y21: 0 | Z21: 0 | AA21: 0 | AB21: 0 | AC21: 0 | AD21: 0 | AE21: 0 | AF21: 0 | AG21: 0 | AH21: =SUM(C21:AG21) -> 283303
A22: Café y Té | B22: =AH22/$AH$10 -> 0 | C22: 0 | D22: 0 | E22: 0 | F22: 0 | G22: 0 | H22: 0 | I22: 0 | J22: 0 | K22: 0 | L22: 0 | M22: 0 | N22: 0 | O22: 0 | P22: 0 | Q22: 0 | R22: 0 | S22: 0 | T22: 0 | U22: 0 | V22: 0 | W22: 0 | X22: 0 | Y22: 0 | Z22: 0 | AA22: 0 | AB22: 0 | AC22: 0 | AD22: 0 | AE22: 0 | AF22: 0 | AG22: 0 | AH22: =SUM(C22:AG22) -> 0
A23: Leche de soya | B23: =AH23/$AH$10 -> 0.0075762915 | C23: 0 | D23: 0 | E23: 0 | F23: 0 | G23: 0 | H23: 0 | I23: =129424+5522 -> 134946 | J23: 0 | K23: 0 | L23: 0 | M23: 0 | N23: 0 | O23: 0 | P23: 0 | Q23: 0 | R23: 0 | S23: 0 | T23: 0 | U23: 0 | V23: 0 | W23: 0 | X23: 0 | Y23: 0 | Z23: 0 | AA23: 0 | AB23: 0 | AC23: 0 | AD23: 141134 | AE23: 0 | AF23: 0 | AG23: 0 | AH23: =SUM(C23:AG23) -> 276080
A24: Bebestibles | B24: =AH24/$AH$10 -> 0.0021832057 | C24: 0 | D24: 0 | E24: 0 | F24: 56351 | G24: 0 | H24: 0 | I24: 23205 | J24: 0 | K24: 0 | L24: 0 | M24: 0 | N24: 0 | O24: 0 | P24: 0 | Q24: 0 | R24: 0 | S24: 0 | T24: 0 | U24: 0 | V24: 0 | W24: 0 | X24: 0 | Y24: 0 | Z24: 0 | AA24: 0 | AB24: 0 | AC24: 0 | AD24: 0 | AE24: 0 | AF24: 0 | AG24: 0 | AH24: =SUM(C24:AG24) -> 79556
A25: Brugga | B25: =AH25/$AH$10 -> 0.0077591675 | C25: 0 | D25: 0 | E25: 0 | F25: 0 | G25: 0 | H25: 0 | I25: 0 | J25: 0 | K25: 0 | L25: 0 | M25: 0 | N25: 0 | O25: 0 | P25: 188496 | Q25: 0 | R25: 0 | S25: 0 | T25: 0 | U25: 0 | V25: 0 | W25: 0 | X25: 0 | Y25: 0 | Z25: 0 | AA25: 0 | AB25: 0 | AC25: 0 | AD25: 94248 | AE25: 0 | AF25: 0 | AG25: 0 | AH25: =SUM(C25:AG25) -> 282744
A26: Colación | B26: =AH26/$AH$10 -> 0.0087845519 | C26: 0 | D26: 42743 | E26: 0 | F26: 0 | G26: 12500 | H26: 10000 | I26: 0 | J26: 0 | K26: 46870 | L26: 0 | M26: 0 | N26: 0 | O26: 17033 | P26: 0 | Q26: 0 | R26: 49508 | S26: 0 | T26: 30418 | U26: 0 | V26: 0 | W26: 0 | X26: 0 | Y26: 40391 | Z26: 0 | AA26: 12634 | AB26: 0 | AC26: 0 | AD26: 58012 | AE26: 0 | AF26: 0 | AG26: 0 | AH26: =SUM(C26:AG26) -> 320109
A27: Empaques y desechables | B27: =AH27/$AH$10 -> 0.01797805 | C27: 122308 | D27: 0 | E27: 0 | F27: 0 | G27: 0 | H27: 0 | I27: 0 | J27: 0 | K27: 0 | L27: =71960+8420 -> 80380 | M27: 0 | N27: 0 | O27: 0 | P27: 156794 | Q27: 0 | R27: 0 | S27: 0 | T27: 0 | U27: 0 | V27: 0 | W27: 0 | X27: 0 | Y27: 137136 | Z27: =6350+47622 -> 53972 | AA27: 0 | AB27: 0 | AC27: 0 | AD27: 0 | AE27: 104530 | AF27: 0 | AG27: 0 | AH27: =SUM(C27:AG27) -> 655120
A28: Soyas sachet | B28: =AH28/$AH$10 -> 0.0049394632 | C28: 89997 | D28: 0 | E28: 0 | F28: 0 | G28: 0 | H28: 0 | I28: 0 | J28: 0 | K28: 0 | L28: 0 | M28: 0 | N28: 0 | O28: 0 | P28: 0 | Q28: 0 | R28: 0 | S28: 0 | T28: 0 | U28: 89997 | V28: 0 | W28: 0 | X28: 0 | Y28: 0 | Z28: 0 | AA28: 0 | AB28: 0 | AC28: 0 | AD28: 0 | AE28: 0 | AF28: 0 | AG28: 0 | AH28: =SUM(C28:AG28) -> 179994
A29: Servilletas | B29: =AH29/$AH$10 -> 0 | C29: 0 | D29: 0 | E29: 0 | F29: 0 | G29: 0 | H29: 0 | I29: 0 | J29: 0 | K29: 0 | L29: 0 | M29: 0 | N29: 0 | O29: 0 | P29: 0 | Q29: 0 | R29: 0 | S29: 0 | T29: 0 | U29: 0 | V29: 0 | W29: 0 | X29: 0 | Y29: 0 | Z29: 0 | AA29: 0 | AB29: 0 | AC29: 0 | AD29: 0 | AE29: 0 | AF29: 0 | AG29: 0 | AH29: =SUM(C29:AG29) -> 0
A30: Limpieza e higiene | B30: =AH30/$AH$10 -> 0.0026252201 | C30: 0 | D30: 0 | E30: =3500+900+2800+5000 -> 12200 | F30: 0 | G30: 0 | H30: 0 | I30: 0 | J30: 43983 | K30: 0 | L30: 0 | M30: 0 | N30: 0 | O30: 0 | P30: 0 | Q30: 0 | R30: 0 | S30: 0 | T30: 0 | U30: 20000 | V30: 0 | W30: 0 | X30: 0 | Y30: 7980 | Z30: 3000 | AA30: 0 | AB30: 0 | AC30: 5000 | AD30: =1800+1700 -> 3500 | AE30: 0 | AF30: 0 | AG30: 0 | AH30: =SUM(C30:AG30) -> 95663
A31: Postres | B31: =AH31/$AH$10 -> 0.010856698 | C31: 0 | D31: 0 | E31: 0 | F31: 0 | G31: 0 | H31: 0 | I31: 80400 | J31: 0 | K31: 0 | L31: 0 | M31: 0 | N31: 0 | O31: 241218 | P31: 0 | Q31: 0 | R31: 0 | S31: 0 | T31: 0 | U31: 74000 | V31: 0 | W31: 0 | X31: 0 | Y31: 0 | Z31: 0 | AA31: 0 | AB31: 0 | AC31: 0 | AD31: 0 | AE31: 0 | AF31: 0 | AG31: 0 | AH31: =SUM(C31:AG31) -> 395618
A33: Gastos FV | B33: =AH33/$AH$10 -> 0.22701385 | C33: =sum(C34+C54+C64) -> 0 | D33: =sum(D34+D54+D64) -> 0 | E33: =sum(E34+E54+E64) -> 68735 | F33: =sum(F34+F54+F64) -> 60000 | G33: =sum(G34+G54+G64) -> 0 | H33: =sum(H34+H54+H64) -> 318870 | I33: =sum(I34+I54+I64) -> 1832719 | J33: =sum(J34+J54+J64) -> 3951 | ... AH33: =sum(AH34+AH54+AH64) -> 8272383
A34: Operaciones | B34: =AH34/$AH$10 -> 0.19234636 | C34: =sum(C35:C53) -> 0 | D34: =sum(D35:D53) -> 0 | E34: =sum(E35:E53) -> 0 | F34: =sum(F35:F53) -> 0 | G34: =sum(G35:G53) -> 0 | H34: =sum(H35:H53) -> 209823 | I34: =sum(I35:I53) -> 1832719 | J34: =sum(J35:J53) -> 0 | ... AH34: =sum(AH35:AH53) -> 7009100
A35: Electricidad | B35: =AH35/$AH$10 -> 0.037938949 | C35: 0 | D35: 0 | E35: 0 | F35: 0 | G35: 0 | H35: 0 | I35: 0 | J35: 0 | K35: 0 | L35: 0 | M35: 0 | N35: 0 | O35: 0 | P35: 0 | Q35: 0 | R35: 0 | S35: =363919+131378 -> 495297 | T35: 0 | U35: 0 | V35: 0 | W35: 0 | X35: 0 | Y35: 0 | Z35: 0 | AA35: 887198 | AB35: 0 | AC35: 0 | AD35: 0 | AE35: 0 | AF35: 0 | AG35: 0 | AH35: =SUM(C35:AG35) -> 1382495
A36: Agua | B36: =AH36/$AH$10 -> 0.0015079586 | C36: 0 | D36: 0 | E36: 0 | F36: 0 | G36: 0 | H36: 0 | I36: 0 | J36: 0 | K36: 0 | L36: 0 | M36: 0 | N36: 0 | O36: 0 | P36: 0 | Q36: 0 | R36: 0 | S36: 54950 | T36: 0 | U36: 0 | V36: 0 | W36: 0 | X36: 0 | Y36: 0 | Z36: 0 | AA36: 0 | AB36: 0 | AC36: 0 | AD36: 0 | AE36: 0 | AF36: 0 | AG36: 0 | AH36: =SUM(C36:AG36) -> 54950
A37: Gas | B37: =AH37/$AH$10 -> 0.0097425927 | C37: 0 | D37: 0 | E37: 0 | F37: 0 | G37: 0 | H37: 0 | I37: 0 | J37: 0 | K37: 0 | L37: 0 | M37: 0 | N37: 0 | O37: 0 | P37: 0 | Q37: 0 | R37: 0 | S37: 355020 | T37: 0 | U37: 0 | V37: 0 | W37: 0 | X37: 0 | Y37: 0 | Z37: 0 | AA37: 0 | AB37: 0 | AC37: 0 | AD37: 0 | AE37: 0 | AF37: 0 | AG37: 0 | AH37: =SUM(C37:AG37) -> 355020
A38: Restaurantpe | B38: =AH38/$AH$10 -> 0 | C38: 0 | D38: 0 | E38: 0 | F38: 0 | G38: 0 | H38: 0 | I38: 0 | J38: 0 | K38: 0 | L38: 0 | M38: 0 | N38: 0 | O38: 0 | P38: 0 | Q38: 0 | R38: 0 | S38: 0 | T38: 0 | U38: 0 | V38: 0 | W38: 0 | X38: 0 | Y38: 0 | Z38: 0 | AA38: 0 | AB38: 0 | AC38: 0 | AD38: 0 | AE38: 0 | AF38: 0 | AG38: 0 | AH38: =SUM(C38:AG38) -> 0
A39: Toteat | B39: =AH39/$AH$10 -> 0.0057580419 | C39: 0 | D39: 0 | E39: 0 | F39: 0 | G39: 0 | H39: =90777+119046 -> 209823 | I39: 0 | J39: 0 | K39: 0 | L39: 0 | M39: 0 | N39: 0 | O39: 0 | P39: 0 | Q39: 0 | R39: 0 | S39: 0 | T39: 0 | U39: 0 | V39: 0 | W39: 0 | X39: 0 | Y39: 0 | Z39: 0 | AA39: 0 | AB39: 0 | AC39: 0 | AD39: 0 | AE39: 0 | AF39: 0 | AG39: 0 | AH39: =SUM(C39:AG39) -> 209823
A40: Alarma | B40: =AH40/$AH$10 -> 0.0013141057 | C40: 0 | D40: 0 | E40: 0 | F40: 0 | G40: 0 | H40: 0 | I40: 0 | J40: 0 | K40: 0 | L40: 0 | M40: 0 | N40: 0 | O40: 0 | P40: 0 | Q40: 0 | R40: 0 | S40: 47886 | T40: 0 | U40: 0 | V40: 0 | W40: 0 | X40: 0 | Y40: 0 | Z40: 0 | AA40: 0 | AB40: 0 | AC40: 0 | AD40: 0 | AE40: 0 | AF40: 0 | AG40: 0 | AH40: =SUM(C40:AG40) -> 47886
A41: VTR | B41: =AH41/$AH$10 -> 0.00032412192 | C41: 0 | D41: 0 | E41: 0 | F41: 0 | G41: 0 | H41: 0 | I41: 0 | J41: 0 | K41: 0 | L41: 0 | M41: 0 | N41: 0 | O41: 0 | P41: 0 | Q41: 0 | R41: 0 | S41: 11811 | T41: 0 | U41: 0 | V41: 0 | W41: 0 | X41: 0 | Y41: 0 | Z41: 0 | AA41: 0 | AB41: 0 | AC41: 0 | AD41: 0 | AE41: 0 | AF41: 0 | AG41: 0 | AH41: =SUM(C41:AG41) -> 11811
A42: Bodega | B42: =AH42/$AH$10 -> 0.009604832 | C42: 0 | D42: 0 | E42: 0 | F42: 0 | G42: 0 | H42: 0 | I42: 0 | J42: 0 | K42: 0 | L42: 0 | M42: 0 | N42: 0 | O42: 0 | P42: 0 | Q42: 0 | R42: 0 | S42: 0 | T42: 0 | U42: 0 | V42: 0 | W42: 0 | X42: 0 | Y42: 0 | Z42: 0 | AA42: 0 | AB42: 0 | AC42: 0 | AD42: 0 | AE42: 0 | AF42: 350000 | AG42: 0 | AH42: =SUM(C42:AG42) -> 350000
A43: Arriendo | B43: =AH43/$AH$10 -> 0.050294166 | C43: 0 | D43: 0 | E43: 0 | F43: 0 | G43: 0 | H43: 0 | I43: 1832719 | J43: 0 | K43: 0 | L43: 0 | M43: 0 | N43: 0 | O43: 0 | P43: 0 | Q43: 0 | R43: 0 | S43: 0 | T43: 0 | U43: 0 | V43: 0 | W43: 0 | X43: 0 | Y43: 0 | Z43: 0 | AA43: 0 | AB43: 0 | AC43: 0 | AD43: 0 | AE43: 0 | AF43: 0 | AG43: 0 | AH43: =SUM(C43:AG43) -> 1832719
A44: Funmigacion | B44: =AH44/$AH$10 -> 0 | C44: 0 | D44: 0 | E44: 0 | F44: 0 | G44: 0 | H44: 0 | I44: 0 | J44: 0 | K44: 0 | L44: 0 | M44: 0 | N44: 0 | O44: 0 | P44: 0 | Q44: 0 | R44: 0 | S44: 0 | T44: 0 | U44: 0 | V44: 0 | W44: 0 | X44: 0 | Y44: 0 | Z44: 0 | AA44: 0 | AB44: 0 | AC44: 0 | AD44: 0 | AE44: 0 | AF44: 0 | AG44: 0 | AH44: =SUM(C44:AG44) -> 0
A45: Aroclean | B45: =AH45/$AH$10 -> 0.0021216799 | C45: 0 | D45: 0 | E45: 0 | F45: 0 | G45: 0 | H45: 0 | I45: 0 | J45: 0 | K45: 0 | L45: 0 | M45: 0 | N45: 0 | O45: 0 | P45: 0 | Q45: 0 | R45: 0 | S45: 0 | T45: 0 | U45: 0 | V45: 0 | W45: 0 | X45: 0 | Y45: 0 | Z45: 77314 | AA45: 0 | AB45: 0 | AC45: 0 | AD45: 0 | AE45: 0 | AF45: 0 | AG45: 0 | AH45: =SUM(C45:AG45) -> 77314
A46: Reposición de vasos | B46: =AH46/$AH$10 -> 0 | C46: 0 | D46: 0 | E46: 0 | F46: 0 | G46: 0 | H46: 0 | I46: 0 | J46: 0 | K46: 0 | L46: 0 | M46: 0 | N46: 0 | O46: 0 | P46: 0 | Q46: 0 | R46: 0 | S46: 0 | T46: 0 | U46: 0 | V46: 0 | W46: 0 | X46: 0 | Y46: 0 | Z46: 0 | AA46: 0 | AB46: 0 | AC46: 0 | AD46: 0 | AE46: 0 | AF46: 0 | AG46: 0 | AH46: =SUM(C46:AG46) -> 0
A47: Reposición Articulos cocina | B47: =AH47/$AH$10 -> 0.0010974207 | C47: 0 | D47: 0 | E47: 0 | F47: 0 | G47: 0 | H47: 0 | I47: 0 | J47: 0 | K47: 0 | L47: 0 | M47: 0 | N47: 0 | O47: 0 | P47: 0 | Q47: 0 | R47: 0 | S47: 0 | T47: 0 | U47: 0 | V47: 0 | W47: 0 | X47: 0 | Y47: 0 | Z47: 0 | AA47: 0 | AB47: 0 | AC47: 0 | AD47: 0 | AE47: 0 | AF47: 39990 | AG47: 0 | AH47: =SUM(C47:AG47) -> 39990
A48: Reposición articulos salón | B48: =AH48/$AH$10 -> 0.00017837545 | C48: 0 | D48: 0 | E48: 0 | F48: 0 | G48: 0 | H48: 0 | I48: 0 | J48: 0 | K48: 0 | L48: 0 | M48: 0 | N48: 0 | O48: 0 | P48: 0 | Q48: 0 | R48: 0 | S48: 0 | T48: 0 | U48: 0 | V48: 0 | W48: 0 | X48: 0 | Y48: 0 | Z48: 0 | AA48: 6500 | AB48: 0 | AC48: 0 | AD48: 0 | AE48: 0 | AF48: 0 | AG48: 0 | AH48: =SUM(C48:AG48) -> 6500
A49: Reparaciones mano de obra | B49: =AH49/$AH$10 -> 0 | C49: 0 | D49: 0 | E49: 0 | F49: 0 | G49: 0 | H49: 0 | I49: 0 | J49: 0 | K49: 0 | L49: 0 | M49: 0 | N49: 0 | O49: 0 | P49: 0 | Q49: 0 | R49: 0 | S49: 0 | T49: 0 | U49: 0 | V49: 0 | W49: 0 | X49: 0 | Y49: 0 | Z49: 0 | AA49: 0 | AB49: 0 | AC49: 0 | AD49: 0 | AE49: 0 | AF49: 0 | AG49: 0 | AH49: =SUM(C49:AG49) -> 0
A50: Reparaciones articulos | B50: =AH50/$AH$10 -> 0.00017974757 | C50: 0 | D50: 0 | E50: 0 | F50: 0 | G50: 0 | H50: 0 | I50: 0 | J50: 0 | K50: 0 | L50: 0 | M50: 0 | N50: 0 | O50: 0 | P50: 0 | Q50: 0 | R50: 0 | S50: 0 | T50: 0 | U50: 0 | V50: 0 | W50: 0 | X50: 0 | Y50: 6550 | Z50: 0 | AA50: 0 | AB50: 0 | AC50: 0 | AD50: 0 | AE50: 0 | AF50: 0 | AG50: 0 | AH50: =SUM(C50:AG50) -> 6550
A51: Reparaciones maquinaria | B51: =AH51/$AH$10 -> 0 | C51: 0 | D51: 0 | E51: 0 | F51: 0 | G51: 0 | H51: 0 | I51: 0 | J51: 0 | K51: 0 | L51: 0 | M51: 0 | N51: 0 | O51: 0 | P51: 0 | Q51: 0 | R51: 0 | S51: 0 | T51: 0 | U51: 0 | V51: 0 | W51: 0 | X51: 0 | Y51: 0 | Z51: 0 | AA51: 0 | AB51: 0 | AC51: 0 | AD51: 0 | AE51: 0 | AF51: 0 | AG51: 0 | AH51: =SUM(C51:AG51) -> 0
... A53: Fee | B53: =AH53/$AH$10 -> 0.072284374 | C53: 0 | D53: 0 | E53: 0 | F53: 0 | G53: 0 | H53: 0 | I53: 0 | J53: 0 | K53: 0 | L53: 0 | M53: 0 | N53: 0 | O53: 0 | P53: 2634042 | Q53: 0 | R53: 0 | S53: 0 | T53: 0 | U53: 0 | V53: 0 | W53: 0 | X53: 0 | Y53: 0 | Z53: 0 | AA53: 0 | AB53: 0 | AC53: 0 | AD53: 0 | AE53: 0 | AF53: 0 | AG53: 0 | AH53: =SUM(C53:AG53) -> 2634042
A54: Administración y finanzas | B54: =AH54/$AH$10 -> 0.0062143537 | C54: =sum(C55:C62) -> 0 | D54: =sum(D55:D62) -> 0 | E54: =sum(E55:E62) -> 0 | F54: =sum(F55:F62) -> 60000 | G54: =sum(G55:G62) -> 0 | H54: =sum(H55:H62) -> 0 | I54: =sum(I55:I62) -> 0 | J54: =sum(J55:J62) -> 3951 | ... AE54: =sum(AE55:AE62) -> 0 | AF54: =SUM(AF55:AF62) -> 5000 | AG54: =sum(AG55:AG62) -> 0 | AH54: =SUM(AH55:AH62) -> 226451
A55: Comisiones cuenta corriente | B55: =AH55/$AH$10 -> 0.00010842483 | C55: 0 | D55: 0 | E55: 0 | F55: 0 | G55: 0 | H55: 0 | I55: 0 | J55: 3951 | K55: 0 | L55: 0 | M55: 0 | N55: 0 | O55: 0 | P55: 0 | Q55: 0 | R55: 0 | S55: 0 | T55: 0 | U55: 0 | V55: 0 | W55: 0 | X55: 0 | Y55: 0 | Z55: 0 | AA55: 0 | AB55: 0 | AC55: 0 | AD55: 0 | AE55: 0 | AF55: 0 | AG55: 0 | AH55: =SUM(C55:AG55) -> 3951
A56: Contadora | B56: =AH56/$AH$10 -> 0.0032930852 | C56: 0 | D56: 0 | E56: 0 | F56: 60000 | G56: 0 | H56: 0 | I56: 0 | J56: 0 | K56: 0 | L56: 0 | M56: 0 | N56: 0 | O56: 0 | P56: 0 | Q56: 0 | R56: 0 | S56: 0 | T56: 0 | U56: 0 | V56: 60000 | W56: 0 | X56: 0 | Y56: 0 | Z56: 0 | AA56: 0 | AB56: 0 | AC56: 0 | AD56: 0 | AE56: 0 | AF56: 0 | AG56: 0 | AH56: =SUM(C56:AG56) -> 120000
A57: Patentes comerciales | B57: =AH57/$AH$10 -> 0 | C57: 0 | D57: 0 | E57: 0 | F57: 0 | G57: 0 | H57: 0 | I57: 0 | J57: 0 | K57: 0 | L57: 0 | M57: 0 | N57: 0 | O57: 0 | P57: 0 | Q57: 0 | R57: 0 | S57: 0 | T57: 0 | U57: 0 | V57: 0 | W57: 0 | X57: 0 | Y57: 0 | Z57: 0 | AA57: 0 | AB57: 0 | AC57: 0 | AD57: 0 | AE57: 0 | AF57: 0 | AG57: 0 | AH57: =SUM(C57:AG57) -> 0
A58: Insumos de oficina | B58: =AH58/$AH$10 -> 0.00013721189 | C58: 0 | D58: 0 | E58: 0 | F58: 0 | G58: 0 | H58: 0 | I58: 0 | J58: 0 | K58: 0 | L58: 0 | M58: 0 | N58: 0 | O58: 0 | P58: 0 | Q58: 0 | R58: 0 | S58: 0 | T58: 0 | U58: 0 | V58: 0 | W58: 0 | X58: 0 | Y58: 0 | Z58: 0 | AA58: 0 | AB58: 0 | AC58: 0 | AD58: 0 | AE58: 0 | AF58: 5000 | AG58: 0 | AH58: =SUM(C58:AG58) -> 5000
A59: Wasabil | B59: =AH59/$AH$10 -> 0 | C59: 0 | D59: 0 | E59: 0 | F59: 0 | G59: 0 | H59: 0 | I59: 0 | J59: 0 | K59: 0 | L59: 0 | M59: 0 | N59: 0 | O59: 0 | P59: 0 | Q59: 0 | R59: 0 | S59: 0 | T59: 0 | U59: 0 | V59: 0 | W59: 0 | X59: 0 | Y59: 0 | Z59: 0 | AA59: 0 | AB59: 0 | AC59: 0 | AD59: 0 | AE59: 0 | AF59: 0 | AG59: 0 | AH59: =SUM(C59:AG59) -> 0
A60: Devolución clientes | B60: =AH60/$AH$10 -> 1.3721189e-05 | C60: 0 | D60: 0 | E60: 0 | F60: 0 | G60: 0 | H60: 0 | I60: 0 | J60: 0 | K60: 0 | L60: 0 | M60: 0 | N60: 0 | O60: 0 | P60: 0 | Q60: 0 | R60: 0 | S60: 0 | T60: 0 | U60: 0 | V60: 0 | W60: 500 | X60: 0 | Y60: 0 | Z60: 0 | AA60: 0 | AB60: 0 | AC60: 0 | AD60: 0 | AE60: 0 | AF60: 0 | AG60: 0 | AH60: =SUM(C60:AG60) -> 500
A61: Reuniones ejecutivas | B61: =AH61/$AH$10 -> 0 | C61: 0 | D61: 0 | E61: 0 | F61: 0 | G61: 0 | H61: 0 | I61: 0 | J61: 0 | K61: 0 | L61: 0 | M61: 0 | N61: 0 | O61: 0 | P61: 0 | Q61: 0 | R61: 0 | S61: 0 | T61: 0 | U61: 0 | V61: 0 | W61: 0 | X61: 0 | Y61: 0 | Z61: 0 | AA61: 0 | AB61: 0 | AC61: 0 | AD61: 0 | AE61: 0 | AF61: 0 | AG61: 0 | AH61: =SUM(C61:AG61) -> 0
A62: Certificados | B62: =AH62/$AH$10 -> 0.0026619106 | C62: 0 | D62: 0 | E62: 0 | F62: 0 | G62: 0 | H62: 0 | I62: 0 | J62: 0 | K62: 0 | L62: 0 | M62: 0 | N62: 0 | O62: 0 | P62: 0 | Q62: 0 | R62: 0 | S62: 0 | T62: 0 | U62: 0 | V62: 0 | W62: 97000 | X62: 0 | Y62: 0 | Z62: 0 | AA62: 0 | AB62: 0 | AC62: 0 | AD62: 0 | AE62: 0 | AF62: 0 | AG62: 0 | AH62: =SUM(C62:AG62) -> 97000
A64: Marketing | B64: =AH64/$AH$10 -> 0.028453135 | C64: =sum(C65:C74) -> 0 | D64: =sum(D65:D74) -> 0 | E64: =sum(E65:E75) -> 68735 | F64: =sum(F65:F74) -> 0 | G64: =sum(G65:G74) -> 0 | H64: =sum(H65:H74) -> 109047 | I64: =sum(I65:I74) -> 0 | J64: =sum(J65:J74) -> 0 | K64: =sum(K65:K74) -> 0 | L64: =sum(L65:L74) -> 0 | M64: =sum(M65:M74) -> 0 | ... AG64: =sum(AG65:AG74) -> 0 | AH64: =SUM(AH65:AH75) -> 1036832
A65: Mercat | B65: =AH65/$AH$10 -> 0.0059999464 | C65: 0 | D65: 0 | E65: 0 | F65: 0 | G65: 0 | H65: 109047 | I65: 0 | J65: 0 | K65: 0 | L65: 0 | M65: 0 | N65: 0 | O65: 0 | P65: 0 | Q65: 0 | R65: 0 | S65: 0 | T65: 0 | U65: 0 | V65: 0 | W65: 0 | X65: 0 | Y65: 0 | Z65: 109591 | AA65: 0 | AB65: 0 | AC65: 0 | AD65: 0 | AE65: 0 | AF65: 0 | AG65: 0 | AH65: =SUM(C65:AG65) -> 218638
A66: Brevo | B66: =AH66/$AH$10 -> 0.0015983813 | C66: 0 | D66: 0 | E66: 58245 | F66: 0 | G66: 0 | H66: 0 | I66: 0 | J66: 0 | K66: 0 | L66: 0 | M66: 0 | N66: 0 | O66: 0 | P66: 0 | Q66: 0 | R66: 0 | S66: 0 | T66: 0 | U66: 0 | V66: 0 | W66: 0 | X66: 0 | Y66: 0 | Z66: 0 | AA66: 0 | AB66: 0 | AC66: 0 | AD66: 0 | AE66: 0 | AF66: 0 | AG66: 0 | AH66: =SUM(C66:AG66) -> 58245
A67: Fiweex | B67: =AH67/$AH$10 -> 0.0013062571 | C67: 0 | D67: 0 | E67: 0 | F67: 0 | G67: 0 | H67: 0 | I67: 0 | J67: 0 | K67: 0 | L67: 0 | M67: 0 | N67: 0 | O67: 0 | P67: 0 | Q67: 0 | R67: 0 | S67: 0 | T67: 0 | U67: 0 | V67: 0 | W67: 0 | X67: 0 | Y67: 0 | Z67: 47600 | AA67: 0 | AB67: 0 | AC67: 0 | AD67: 0 | AE67: 0 | AF67: 0 | AG67: 0 | AH67: =SUM(C67:AG67) -> 47600
A68: Fujifilm instax | B68: =AH68/$AH$10 -> 0 | C68: 0 | D68: 0 | E68: 0 | F68: 0 | G68: 0 | H68: 0 | I68: 0 | J68: 0 | K68: 0 | L68: 0 | M68: 0 | N68: 0 | O68: 0 | P68: 0 | Q68: 0 | R68: 0 | S68: 0 | T68: 0 | U68: 0 | V68: 0 | W68: 0 | X68: 0 | Y68: 0 | Z68: 0 | AA68: 0 | AB68: 0 | AC68: 0 | AD68: 0 | AE68: 0 | AF68: 0 | AG68: 0 | AH68: =SUM(C68:AG68) -> 0
A69: Resos | B69: =AH69/$AH$10 -> 0.0027952531 | C69: 0 | D69: 0 | E69: 0 | F69: 0 | G69: 0 | H69: 0 | I69: 0 | J69: 0 | K69: 0 | L69: 0 | M69: 0 | N69: 0 | O69: 0 | P69: 0 | Q69: 0 | R69: 0 | S69: 0 | T69: 0 | U69: 0 | V69: 0 | W69: 0 | X69: 0 | Y69: 0 | Z69: 0 | AA69: 0 | AB69: 0 | AC69: 0 | AD69: 101859 | AE69: 0 | AF69: 0 | AG69: 0 | AH69: =SUM(C69:AG69) -> 101859
A70: HappyCow | B70: =AH70/$AH$10 -> 0 | C70: 0 | D70: 0 | E70: 0 | F70: 0 | G70: 0 | H70: 0 | I70: 0 | J70: 0 | K70: 0 | L70: 0 | M70: 0 | N70: 0 | O70: 0 | P70: 0 | Q70: 0 | R70: 0 | S70: 0 | T70: 0 | U70: 0 | V70: 0 | W70: 0 | X70: 0 | Y70: 0 | Z70: 0 | AA70: 0 | AB70: 0 | AC70: 0 | AD70: 0 | AE70: 0 | AF70: 0 | AG70: 0 | AH70: =SUM(C70:AG70) -> 0
A71: Meta Ads | B71: =AH71/$AH$10 -> 0 | C71: 0 | D71: 0 | E71: 0 | F71: 0 | G71: 0 | H71: 0 | I71: 0 | J71: 0 | K71: 0 | L71: 0 | M71: 0 | N71: 0 | O71: 0 | P71: 0 | Q71: 0 | R71: 0 | S71: 0 | T71: 0 | U71: 0 | V71: 0 | W71: 0 | X71: 0 | Y71: 0 | Z71: 0 | AA71: 0 | AB71: 0 | AC71: 0 | AD71: 0 | AE71: 0 | AF71: 0 | AG71: 0 | AH71: =SUM(C71:AG71) -> 0
A72: Influencers | B72: =AH72/$AH$10 -> 0 | C72: 0 | D72: 0 | E72: 0 | F72: 0 | G72: 0 | H72: 0 | I72: 0 | J72: 0 | K72: 0 | L72: 0 | M72: 0 | N72: 0 | O72: 0 | P72: 0 | Q72: 0 | R72: 0 | S72: 0 | T72: 0 | U72: 0 | V72: 0 | W72: 0 | X72: 0 | Y72: 0 | Z72: 0 | AA72: 0 | AB72: 0 | AC72: 0 | AD72: 0 | AE72: 0 | AF72: 0 | AG72: 0 | AH72: =SUM(C72:AG72) -> 0
A73: Chatfuel | B73: =AH73/$AH$10 -> 0 | C73: 0 | D73: 0 | E73: 0 | F73: 0 | G73: 0 | H73: 0 | I73: 0 | J73: 0 | K73: 0 | L73: 0 | M73: 0 | N73: 0 | O73: 0 | P73: 0 | Q73: 0 | R73: 0 | S73: 0 | T73: 0 | U73: 0 | V73: 0 | W73: 0 | X73: 0 | Y73: 0 | Z73: 0 | AA73: 0 | AB73: 0 | AC73: 0 | AD73: 0 | AE73: 0 | AF73: 0 | AG73: 0 | AH73: =SUM(C73:AG73) -> 0
A74: Community manager | B74: =AH74/$AH$10 -> 0.016465426 | C74: 0 | D74: 0 | E74: 0 | F74: 0 | G74: 0 | H74: 0 | I74: 0 | J74: 0 | K74: 0 | L74: 0 | M74: 0 | N74: 0 | O74: 0 | P74: 0 | Q74: 0 | R74: 0 | S74: 0 | T74: 0 | U74: 0 | V74: 0 | W74: 0 | X74: 0 | Y74: 0 | Z74: 0 | AA74: 0 | AB74: 0 | AC74: 0 | AD74: 0 | AE74: 0 | AF74: 600000 | AG74: 0 | AH74: =SUM(C74:AG74) -> 600000
A75: Microsoft | B75: =AH75/$AH$10 -> 0.00028787054 | C75: 0 | D75: 0 | E75: 10490 | F75: 0 | G75: 0 | H75: 0 | I75: 0 | J75: 0 | K75: 0 | L75: 0 | M75: 0 | N75: 0 | O75: 0 | P75: 0 | Q75: 0 | R75: 0 | S75: 0 | T75: 0 | U75: 0 | V75: 0 | W75: 0 | X75: 0 | Y75: 0 | Z75: 0 | AA75: 0 | AB75: 0 | AC75: 0 | AD75: 0 | AE75: 0 | AF75: 0 | AG75: 0 | AH75: =SUM(C75:AG75) -> 10490
A77: Inversiones activos | B77: =AH77/$AH$10 -> 0.045487469 | C77: =sum(C78:C81) -> 0 | D77: =sum(D78:D80) -> 0 | E77: =sum(E78:E80) -> 0 | F77: =sum(F78:F80) -> 0 | G77: =sum(G78:G80) -> 0 | H77: =sum(H78:H80) -> 0 | I77: =sum(I78:I80) -> 0 | J77: =sum(J78:J80) -> 0 | K77: =sum(K78:K80) -> 0 | ... Z77: =sum(Z78:Z80) -> 0 | AA77: =sum(AA78:AA81) -> 179260 | AB77: =sum(AB78:AB80) -> 0 | AC77: =sum(AC78:AC80) -> 0 | AD77: =sum(AD78:AD81) -> 520287 | AE77: =sum(AE78:AE80) -> 0 | AF77: =sum(AF78:AF81) -> 958016 | AG77: =sum(AG78:AG80) -> 0 | AH77: =sum(AH78:AH81) -> 1657563
A78: Nuevas maquinaria | B78: =AH78/$AH$10 -> 0 | C78: 0 | D78: 0 | E78: 0 | F78: 0 | G78: 0 | H78: 0 | I78: 0 | J78: 0 | K78: 0 | L78: 0 | M78: 0 | N78: 0 | O78: 0 | P78: 0 | Q78: 0 | R78: 0 | S78: 0 | T78: 0 | U78: 0 | V78: 0 | W78: 0 | X78: 0 | Y78: 0 | Z78: 0 | AA78: 0 | AB78: 0 | AC78: 0 | AD78: 0 | AE78: 0 | AF78: 0 | AG78: 0 | AH78: =SUM(C78:AG78) -> 0
A79: Nueva decoración y muebles | B79: =AH79/$AH$10 -> 0 | C79: 0 | D79: 0 | E79: 0 | F79: 0 | G79: 0 | H79: 0 | I79: 0 | J79: 0 | K79: 0 | L79: 0 | M79: 0 | N79: 0 | O79: 0 | P79: 0 | Q79: 0 | R79: 0 | S79: 0 | T79: 0 | U79: 0 | V79: 0 | W79: 0 | X79: 0 | Y79: 0 | Z79: 0 | AA79: 0 | AB79: 0 | AC79: 0 | AD79: 0 | AE79: 0 | AF79: 0 | AG79: 0 | AH79: =SUM(C79:AG79) -> 0
A80: Remodelaciones | B80: =AH80/$AH$10 -> 0 | C80: 0 | D80: 0 | E80: 0 | F80: 0 | G80: 0 | H80: 0 | I80: 0 | J80: 0 | K80: 0 | L80: 0 | M80: 0 | N80: 0 | O80: 0 | P80: 0 | Q80: 0 | R80: 0 | S80: 0 | T80: 0 | U80: 0 | V80: 0 | W80: 0 | X80: 0 | Y80: 0 | Z80: 0 | AA80: 0 | AB80: 0 | AC80: 0 | AD80: 0 | AE80: 0 | AF80: 0 | AG80: 0 | AH80: =SUM(C80:AG80) -> 0
A81: Kojo | B81: =AH81/$AH$10 -> 0.045487469 | C81: 0 | D81: 0 | E81: 0 | F81: 0 | G81: 0 | H81: 0 | I81: 0 | J81: 0 | K81: 0 | L81: 0 | M81: 0 | N81: 0 | O81: 0 | P81: 0 | Q81: 0 | R81: 0 | S81: 0 | T81: 0 | U81: 0 | V81: 0 | W81: 0 | X81: 0 | Y81: 0 | Z81: 0 | AA81: 179260 | AB81: 0 | AC81: 0 | AD81: =309400+210887 -> 520287 | AE81: 0 | AF81: =607000+351016 -> 958016 | AG81: 0 | AH81: =SUM(C81:AG81) -> 1657563
A83: Dinero temporal | B83: =AH83/$AH$10 -> 0.11576424 | C83: =sum(C84:C87) -> 0 | D83: =sum(D84:D87) -> 601287 | E83: =sum(E84:E87) -> 0 | F83: =sum(F84:F87) -> 0 | G83: =sum(G84:G87) -> 0 | H83: =sum(H84:H87) -> 611381 | I83: =sum(I84:I87) -> 0 | J83: =sum(J84:J87) -> 0 | ... AH83: =sum(AH84:AH87) -> 4218448
A84: Delifast | B84: =AH84/$AH$10 -> 0.061532423 | C84: 0 | D84: 601287 | E84: 0 | F84: 0 | G84: 0 | H84: 0 | I84: 0 | J84: 0 | K84: 0 | L84: 562057 | M84: 0 | N84: 0 | O84: 0 | P84: 0 | Q84: 0 | R84: 621669 | S84: 0 | T84: 0 | U84: 0 | V84: 0 | W84: 0 | X84: 0 | Y84: 0 | Z84: 457228 | AA84: 0 | AB84: 0 | AC84: 0 | AD84: 0 | AE84: 0 | AF84: 0 | AG84: 0 | AH84: =SUM(C84:AG84) -> 2242241
A85: Uber direct | B85: =AH85/$AH$10 -> 3.902306e-05 | C85: 0 | D85: 0 | E85: 0 | F85: 0 | G85: 0 | H85: 0 | I85: 0 | J85: 0 | K85: 0 | L85: 0 | M85: 0 | N85: 0 | O85: 0 | P85: 0 | Q85: 0 | R85: 0 | S85: 0 | T85: 0 | U85: 0 | V85: 0 | W85: 0 | X85: 0 | Y85: 0 | Z85: 1422 | AA85: 0 | AB85: 0 | AC85: 0 | AD85: 0 | AE85: 0 | AF85: 0 | AG85: 0 | AH85: =SUM(C85:AG85) -> 1422
A86: Monto delivery | B86: =AH86/$AH$10 -> 0 | C86: 0 | D86: 0 | E86: 0 | F86: 0 | G86: 0 | H86: 0 | I86: 0 | J86: 0 | K86: 0 | L86: 0 | M86: 0 | N86: 0 | O86: 0 | P86: 0 | Q86: 0 | R86: 0 | S86: 0 | T86: 0 | U86: 0 | V86: 0 | W86: 0 | X86: 0 | Y86: 0 | Z86: 0 | AA86: 0 | AB86: 0 | AC86: 0 | AD86: 0 | AE86: 0 | AF86: 0 | AG86: 0 | AH86: =SUM(C86:AG86) -> 0
A87: Propina personal | B87: =AH87/$AH$10 -> 0.054192795 | C87: 0 | D87: 0 | E87: 0 | F87: 0 | G87: 0 | H87: 611381 | I87: 0 | J87: 0 | K87: 0 | L87: 0 | M87: 0 | N87: 0 | O87: 0 | P87: 402407 | Q87: 0 | R87: 0 | S87: 0 | T87: 0 | U87: 0 | V87: 407952 | W87: 0 | X87: 0 | Y87: 0 | Z87: 0 | AA87: 0 | AB87: 0 | AC87: 553045 | AD87: 0 | AE87: 0 | AF87: 0 | AG87: 0 | AH87: =SUM(C87:AG87) -> 1974785
A89: RRHH | B89: =AH89/$AH$10 -> 0.32278256 | C89: =sum(C90:C98) -> 18000 | D89: =sum(D90:D98) -> 12785 | E89: =sum(E90:E98) -> 0 | F89: =sum(F90:F98) -> 0 | G89: =sum(G90:G98) -> 907559 | H89: =sum(H90:H98) -> 216000 | I89: =sum(I90:I98) -> 0 | J89: =sum(J90:J98) -> 24980 | ... AG89: =sum(AG90:AG98) -> 0 | AH89: =SUM(AH90:AH98) -> 11762194
A90: Turnos feriados | B90: =AH90/$AH$10 -> 0 | C90: 0 | D90: 0 | E90: 0 | F90: 0 | G90: 0 | H90: 0 | I90: 0 | J90: 0 | K90: 0 | L90: 0 | M90: 0 | N90: 0 | O90: 0 | P90: 0 | Q90: 0 | R90: 0 | S90: 0 | T90: 0 | U90: 0 | V90: 0 | W90: 0 | X90: 0 | Y90: 0 | Z90: 0 | AA90: 0 | AB90: 0 | AC90: 0 | AD90: 0 | AE90: 0 | AF90: 0 | AG90: 0 | AH90: =SUM(C90:AG90) -> 0
A91: Sueldo personal | B91: =AH91/$AH$10 -> 0.26283409 | C91: 0 | D91: 0 | E91: 0 | F91: 0 | G91: 907559 | H91: 0 | I91: 0 | J91: 0 | K91: 0 | L91: 0 | M91: 0 | N91: 0 | O91: 0 | P91: 0 | Q91: =250000+200000+270000+460000+150000 -> 1330000 | R91: 0 | S91: 0 | T91: 0 | U91: 0 | V91: 0 | W91: 0 | X91: 0 | Y91: 0 | Z91: 0 | AA91: 0 | AB91: 0 | AC91: 0 | AD91: 0 | AE91: 0 | AF91: =4507589+100000+580000+750000+551262+450000+401262 -> 7340113 | AG91: 0 | AH91: =SUM(C91:AG91) -> 9577672
A92: Traslados personal | B92: =AH92/$AH$10 -> 0.00035085079 | C92: 0 | D92: 12785 | E92: 0 | F92: 0 | G92: 0 | H92: 0 | I92: 0 | J92: 0 | K92: 0 | L92: 0 | M92: 0 | N92: 0 | O92: 0 | P92: 0 | Q92: 0 | R92: 0 | S92: 0 | T92: 0 | U92: 0 | V92: 0 | W92: 0 | X92: 0 | Y92: 0 | Z92: 0 | AA92: 0 | AB92: 0 | AC92: 0 | AD92: 0 | AE92: 0 | AF92: 0 | AG92: 0 | AH92: =SUM(C92:AG92) -> 12785
A93: Turnos extras | B93: =AH93/$AH$10 -> 0 | C93: 0 | D93: 0 | E93: 0 | F93: 0 | G93: 0 | H93: 0 | I93: 0 | J93: 0 | K93: 0 | L93: 0 | M93: 0 | N93: 0 | O93: 0 | P93: 0 | Q93: 0 | R93: 0 | S93: 0 | T93: 0 | U93: 0 | V93: 0 | W93: 0 | X93: 0 | Y93: 0 | Z93: 0 | AA93: 0 | AB93: 0 | AC93: 0 | AD93: 0 | AE93: 0 | AF93: 0 | AG93: 0 | AH93: =SUM(C93:AG93) -> 0
A94: Bonos | B94: =AH94/$AH$10 -> 0.0059275534 | C94: 0 | D94: 0 | E94: 0 | F94: 0 | G94: 0 | H94: 216000 | I94: 0 | J94: 0 | K94: 0 | L94: 0 | M94: 0 | N94: 0 | O94: 0 | P94: 0 | Q94: 0 | R94: 0 | S94: 0 | T94: 0 | U94: 0 | V94: 0 | W94: 0 | X94: 0 | Y94: 0 | Z94: 0 | AA94: 0 | AB94: 0 | AC94: 0 | AD94: 0 | AE94: 0 | AF94: 0 | AG94: 0 | AH94: =SUM(C94:AG94) -> 216000
A95: Previred | B95: =AH95/$AH$10 -> 0.051401685 | C95: 0 | D95: 0 | E95: 0 | F95: 0 | G95: 0 | H95: 0 | I95: 0 | J95: 0 | K95: 0 | L95: 1873077 | M95: 0 | N95: 0 | O95: 0 | P95: 0 | Q95: 0 | R95: 0 | S95: 0 | T95: 0 | U95: 0 | V95: 0 | W95: 0 | X95: 0 | Y95: 0 | Z95: 0 | AA95: 0 | AB95: 0 | AC95: 0 | AD95: 0 | AE95: 0 | AF95: 0 | AG95: 0 | AH95: =SUM(C95:AG95) -> 1873077
A96: Uniforme pesonal | B96: =AH96/$AH$10 -> 0 | C96: 0 | D96: 0 | E96: 0 | F96: 0 | G96: 0 | H96: 0 | I96: 0 | J96: 0 | K96: 0 | L96: 0 | M96: 0 | N96: 0 | O96: 0 | P96: 0 | Q96: 0 | R96: 0 | S96: 0 | T96: 0 | U96: 0 | V96: 0 | W96: 0 | X96: 0 | Y96: 0 | Z96: 0 | AA96: 0 | AB96: 0 | AC96: 0 | AD96: 0 | AE96: 0 | AF96: 0 | AG96: 0 | AH96: =SUM(C96:AG96) -> 0
A97: Finiquitos | B97: =AH97/$AH$10 -> 0 | C97: 0 | D97: 0 | E97: 0 | F97: 0 | G97: 0 | H97: 0 | I97: 0 | J97: 0 | K97: 0 | L97: 0 | M97: 0 | N97: 0 | O97: 0 | P97: 0 | Q97: 0 | R97: 0 | S97: 0 | T97: 0 | U97: 0 | V97: 0 | W97: 0 | X97: 0 | Y97: 0 | Z97: 0 | AA97: 0 | AB97: 0 | AC97: 0 | AD97: 0 | AE97: 0 | AF97: 0 | AG97: 0 | AH97: =SUM(C97:AG97) -> 0
A98: Recreación | B98: =AH98/$AH$10 -> 0.0022683869 | C98: 18000 | D98: 0 | E98: 0 | F98: 0 | G98: 0 | H98: 0 | I98: 0 | J98: 24980 | K98: 39680 | L98: 0 | M98: 0 | N98: 0 | O98: 0 | P98: 0 | Q98: 0 | R98: 0 | S98: 0 | T98: 0 | U98: 0 | V98: 0 | W98: 0 | X98: 0 | Y98: 0 | Z98: 0 | AA98: 0 | AB98: 0 | AC98: 0 | AD98: 0 | AE98: 0 | AF98: 0 | AG98: 0 | AH98: =SUM(C98:AG98) -> 82660
A100: Impuestos fiscales | B100: =AH100/$AH$10 -> 0.10850126 | C100: =SUM(C101:C102) -> 0 | D100: =SUM(D101:D102) -> 0 | E100: =SUM(E101:E102) -> 0 | F100: =SUM(F101:F102) -> 0 | G100: =SUM(G101:G102) -> 0 | H100: =SUM(H101:H102) -> 0 | I100: =SUM(I101:I102) -> 0 | J100: =SUM(J101:J102) -> 0 | ... AH100: =SUM(AH101:AH102) -> 3953785
A101: Impuesto sobre la renta | B101: =AH101/$AH$10 -> 0 | C101: 0 | D101: 0 | E101: 0 | F101: 0 | G101: 0 | H101: 0 | I101: 0 | J101: 0 | K101: 0 | L101: 0 | M101: 0 | N101: 0 | O101: 0 | P101: 0 | Q101: 0 | R101: 0 | S101: 0 | T101: 0 | U101: 0 | V101: 0 | W101: 0 | X101: 0 | Y101: 0 | Z101: 0 | AA101: 0 | AB101: 0 | AC101: 0 | AD101: 0 | AE101: 0 | AF101: 0 | AG101: 0 | AH101: =SUM(C101:AG101) -> 0
A102: IVA | B102: =AH102/$AH$10 -> 0.10850126 | C102: 0 | D102: 0 | E102: 0 | F102: 0 | G102: 0 | H102: 0 | I102: 0 | J102: 0 | K102: 0 | L102: 0 | M102: 0 | N102: 0 | O102: 0 | P102: 0 | Q102: 0 | R102: 0 | S102: 0 | T102: 3953785 | U102: 0 | V102: 0 | W102: 0 | X102: 0 | Y102: 0 | Z102: 0 | AA102: 0 | AB102: 0 | AC102: 0 | AD102: 0 | AE102: 0 | AF102: 0 | AG102: 0 | AH102: =SUM(C102:AG102) -> 3953785
A104: Amortizaciones | AH104: =AH105+AH106 -> 1760416
A105: Préstamo | C105: 0 | D105: 0 | E105: 0 | F105: 0 | G105: 0 | H105: 0 | I105: 0 | J105: 0 | K105: 0 | L105: 0 | M105: 0 | N105: 0 | O105: 0 | P105: 0 | Q105: 0 | R105: 0 | S105: 0 | T105: 0 | U105: 0 | V105: 0 | W105: 0 | X105: 0 | Y105: 0 | Z105: 0 | AA105: 0 | AB105: 0 | AC105: 0 | AD105: 0 | AE105: 1760416 | AF105: 0 | AG105: 0 | AH105: =sum(C105:AG105) -> 1760416
C106: 0 | D106: 0 | E106: 0 | F106: 0 | G106: 0 | H106: 0 | I106: 0 | J106: 0 | K106: 0 | L106: 0 | M106: 0 | N106: 0 | O106: 0 | P106: 0 | Q106: 0 | R106: 0 | S106: 0 | T106: 0 | U106: 0 | V106: 0 | W106: 0 | X106: 0 | Y106: 0 | Z106: 0 | AA106: 0 | AB106: 0 | AC106: 0 | AD106: 0 | AE106: 0 | AF106: 0 | AG106: 0 | AH106: =sum(C106:AG106) -> 0
A108: Total egresos conciliación | C108: =C100+C89+C83+C33+C77+C12+C105+C106 -> 673705 | D108: =D100+D89+D83+D33+D77+D12+D105+D106 -> 706815 | E108: =E100+E89+E83+E33+E77+E12+E105+E106 -> 140425 | F108: =F100+F89+F83+F33+F77+F12+F105+F106 -> 116351 | G108: =G100+G89+G83+G33+G77+G12+G105+G106 -> 920059 | H108: =H100+H89+H83+H33+H77+H12+H105+H106 -> 1647141 | I108: =I100+I89+I83+I33+I77+I12+I105+I106 -> 3016789 | J108: =J100+J89+J83+J33+J77+J12+J105+J106 -> 600867 | ... AG108: =AG100+AG89+AG83+AG33+AG77+AG12+AG105+AG106 -> 0 | AH108: =sum(C108:AF108) -> 42992550
A109: Total egresos operativos | C109: =C100+C89+C33+C77+C12 -> 673705 | D109: =D100+D89+D33+D77+D12 -> 105528 | E109: =E100+E89+E33+E77+E12 -> 140425 | F109: =F100+F89+F33+F77+F12 -> 116351 | G109: =G100+G89+G33+G77+G12 -> 920059 | H109: =H100+H89+H33+H77+H12 -> 1035760 | I109: =I100+I89+I33+I77+I12 -> 3016789 | J109: =J100+J89+J33+J77+J12 -> 600867 | ... AG109: =AG100+AG89+AG33+AG77+AG12 -> 0 | AH109: =sum(C109:AG109) -> 37013686
A111: Rentabilidad | B111: =AH111/$AH$10 -> -0.015743527 | C111: =C9-C109 -> 1100529 | D111: =D9-D109 -> 1469292 | E111: =E9-E109 -> 1564741 | F111: =F9-F109 -> 1657563 | G111: =G9-G109 -> 940974 | H111: =H9-H109 -> 485450 | I111: =I9-I109 -> -2695626 | J111: =J9-J109 -> 946056 | ... AG111: =AG9-AG109 -> 0 | AH111: =AH10-AH109 -> -573694

Sheet Mayo
C1: 46143 | D1: 46144 | E1: 46145 | F1: 46146 | G1: 46147 | H1: 46148 | I1: 46149 | J1: 46150 | K1: 46151 | L1: 46152 | M1: 46153 | N1: 46154 | O1: 46155 | P1: 46156 | Q1: 46157 | R1: 46158 | S1: 46159 | T1: 46160 | U1: 46161 | V1: 46162 | W1: 46163 | X1: 46164 | Y1: 46165 | Z1: 46166 | AA1: 46167 | AB1: 46168 | AC1: 46169 | AD1: 46170 | AE1: 46171 | AF1: 46172 | AG1: 46173 | AH1: Totales
A4: Ingresos
A5: Transbank | C5: =176268+876421+398613+153572 -> 1604874 | D5: =54704+885148+53708+729585 -> 1723145 | E5: =1507569+130035+745469+32383+25807+26106 -> 2467369 | F5: =921294+208353+54922 -> 1184569 | G5: =206213 -> 206213 | H5: =334534+392994+93863 -> 821391 | I5: =38963+625658+36868+461008 -> 1162497 | J5: =31127+223853+527472+112795 -> 895247 | K5: =790736+386870+30491+73652 -> 1281749 | L5: =1625453+424379+71146+239144 -> 2360122 | M5: =343370+1584683 -> 1928053 | N5: =188528+73935+15067 -> 277530 | O5: =48098+492592+451824+28598 -> 1021112 | P5: =325461+424418+22318+90874 -> 863071 | Q5: =593353+1083769+20911+32179 -> 1730212 | R5: =771301+914259+36270+55401 -> 1777231 | S5: =1758376+421191+166503 -> 2346070 | T5: =168994+704875+108911 -> 982780 | U5: =224671 -> 224671 | V5: =495640+562402+42846 -> 1100888 | W5: =28299+354577+231200+79913 -> 693989 | X5: =25110+540530+787779 -> 1353419 | Y5: =1143873+561050+38651 -> 1743574 | Z5: =404999+447405+50020+80811+73038 -> 1056273 | AA5: =216107+628727 -> 844834 | AB5: =45437+12356+32584+201973+73608 -> 365958 | AC5: =493141+387109+27801+40158+24071 -> 972280 | AD5: =452991+37874+570759 -> 1061624 | AE5: =136890+512491+397376+26818+159537 -> 1233112 | AF5: =177862+837753+777605 -> 1793220 | AG5: =1562710+721614+107913 -> 2392237 | AH5: =SUM(C5:AG5) -> 39469314
A6: Transferencias | C6: 6900 | D6: 0 | E6: 0 | F6: 0 | G6: 0 | H6: 0 | I6: 0 | J6: =52250+38100 -> 90350 | K6: 2800 | L6: 172200 | M6: 0 | N6: 116474 | O6: 20000 | P6: 0 | Q6: 0 | R6: 0 | S6: 0 | T6: 0 | U6: 39550 | V6: 0 | W6: 0 | X6: 21200 | Y6: 0 | Z6: 0 | AA6: 0 | AB6: 0 | AC6: 0 | AD6: =4000+22900 -> 26900 | AE6: 0 | AF6: 0 | AG6: 0 | AH6: =SUM(C6:AG6) -> 496374
A7: Efectivo | C7: 0 | D7: 0 | E7: 0 | F7: 0 | G7: 0 | H7: 0 | I7: 0 | J7: 0 | K7: 0 | L7: 0 | M7: 0 | N7: 0 | O7: 0 | P7: 0 | Q7: 0 | R7: 0 | S7: 0 | T7: 0 | U7: 240000 | V7: 0 | W7: 0 | X7: 0 | Y7: 0 | Z7: 0 | AA7: 0 | AB7: 0 | AC7: 0 | AD7: 0 | AE7: 0 | AF7: 0 | AG7: 0 | AH7: =SUM(C7:AG7) -> 240000
A8: Uber | C8: 0 | D8: 0 | E8: 0 | F8: 0 | G8: =634455+327613 -> 962068 | H8: 0 | I8: 0 | J8: 0 | K8: 0 | L8: 0 | M8: 0 | N8: =594513+136690 -> 731203 | O8: 0 | P8: 0 | Q8: 0 | R8: 0 | S8: 0 | T8: 0 | U8: =448704+266440 -> 715144 | V8: 0 | W8: 0 | X8: 0 | Y8: 0 | Z8: 0 | AA8: 0 | AB8: =278893+262915 -> 541808 | AC8: 0 | AD8: 0 | AE8: 0 | AF8: 0 | AG8: 0 | AH8: =SUM(C8:AG8) -> 2950223
A9: Total bruto | C9: =SUM(C5:C8) -> 1611774 | D9: =SUM(D5:D8) -> 1723145 | E9: =SUM(E5:E8) -> 2467369 | F9: =SUM(F5:F8) -> 1184569 | G9: =SUM(G5:G8) -> 1168281 | H9: =SUM(H5:H8) -> 821391 | I9: =SUM(I5:I8) -> 1162497 | J9: =SUM(J5:J8) -> 985597 | ... AH9: =SUM(AH5:AH8) -> 43155911
A10: Total neto | AH10: =AH9-AH84 -> 38637974
A12: Materia prima | B12: =AH12/$AH$10 -> 0.30200256 | C12: =sum(C13:C32) -> 97600 | D12: =sum(D13:D32) -> 0 | E12: =sum(E13:E32) -> 442903 | F12: =sum(F13:F32) -> 88956 | G12: =sum(G13:G32) -> 1866415 | H12: =sum(H13:H32) -> 413080 | I12: =sum(I13:I32) -> 532515 | J12: =sum(J13:J32) -> 99400 | ... AH12: =sum(AH13:AH32) -> 11668767
A13: MP | B13: =AH13/$AH$10 -> 0.017623181 | C13: 13400 | D13: 0 | E13: 0 | F13: 0 | G13: =23880 -> 23880 | H13: =94000 -> 94000 | I13: 22665 | J13: 89600 | K13: =59600 -> 59600 | L13: 32700 | M13: =98019 -> 98019 | N13: 0 | O13: 0 | P13: 0 | Q13: 48300 | R13: 0 | S13: 5910 | T13: 0 | U13: 23600 | V13: 0 | W13: 0 | X13: 77550 | Y13: 0 | Z13: 0 | AA13: 0 | AB13: 0 | AC13: =49400+13800 -> 63200 | AD13: 28500 | AE13: 0 | AF13: 0 | AG13: 0 | AH13: =SUM(C13:AG13) -> 680924
A14: Arroz | B14: =AH14/$AH$10 -> 0.0092551437 | C14: 0 | D14: 0 | E14: 0 | F14: 0 | G14: 119200 | H14: 0 | I14: 0 | J14: 0 | K14: 0 | L14: 0 | M14: 0 | N14: 119200 | O14: 0 | P14: 0 | Q14: 0 | R14: 0 | S14: 0 | T14: 0 | U14: 0 | V14: 119200 | W14: 0 | X14: 0 | Y14: 0 | Z14: 0 | AA14: 0 | AB14: 0 | AC14: 0 | AD14: 0 | AE14: 0 | AF14: 0 | AG14: 0 | AH14: =SUM(C14:AG14) -> 357600
A15: Hod Food | B15: =AH15/$AH$10 -> 0.057537851 | C15: 0 | D15: 0 | E15: 0 | F15: 0 | G15: 322028 | H15: 0 | I15: 0 | J15: 0 | K15: 0 | L15: 0 | M15: 357549 | N15: 0 | O15: 0 | P15: 576424 | Q15: 0 | R15: 0 | S15: 0 | T15: 0 | U15: 396419 | V15: 0 | W15: 0 | X15: 0 | Y15: 0 | Z15: 0 | AA15: 0 | AB15: 570726 | AC15: 0 | AD15: 0 | AE15: 0 | AF15: 0 | AG15: 0 | AH15: =SUM(C15:AG15) -> 2223146
A16: Seitan | B16: =AH16/$AH$10 -> 0.0039856127 | C16: 0 | D16: 0 | E16: 0 | F16: 0 | G16: 0 | H16: 0 | I16: 0 | J16: 0 | K16: 0 | L16: 0 | M16: 0 | N16: 0 | O16: 0 | P16: 0 | Q16: 0 | R16: 0 | S16: 0 | T16: 0 | U16: 0 | V16: 0 | W16: 0 | X16: 0 | Y16: 0 | Z16: 0 | AA16: 0 | AB16: 0 | AC16: 153996 | AD16: 0 | AE16: 0 | AF16: 0 | AG16: 0 | AH16: =SUM(C16:AG16) -> 153996
A17: Palta | B17: =AH17/$AH$10 -> 0.046786899 | C17: 0 | D17: 0 | E17: 397103 | F17: 0 | G17: 0 | H17: 0 | I17: 503370 | J17: 0 | K17: 0 | L17: 0 | M17: 0 | N17: 250000 | O17: 0 | P17: 0 | Q17: 0 | R17: 0 | S17: 0 | T17: 257278 | U17: 0 | V17: 200000 | W17: 0 | X17: 0 | Y17: 0 | Z17: 0 | AA17: 0 | AB17: 0 | AC17: 0 | AD17: 200000 | AE17: 0 | AF17: 0 | AG17: 0 | AH17: =SUM(C17:AG17) -> 1807751
A18: Champiñon | B18: =AH18/$AH$10 -> 0.019942169 | C18: 0 | D18: 0 | E18: 0 | F18: 0 | G18: 321300 | H18: 0 | I18: 0 | J18: 0 | K18: 0 | L18: 0 | M18: 0 | N18: 0 | O18: 0 | P18: 0 | Q18: 0 | R18: 0 | S18: 0 | T18: 0 | U18: 187425 | V18: 0 | W18: 0 | X18: 0 | Y18: 0 | Z18: 0 | AA18: 0 | AB18: 0 | AC18: 0 | AD18: 261800 | AE18: 0 | AF18: 0 | AG18: 0 | AH18: =SUM(C18:AG18) -> 770525
A19: Verduras | B19: =AH19/$AH$10 -> 0.049535879 | C19: 0 | D19: 0 | E19: 0 | F19: 0 | G19: 523200 | H19: 0 | I19: 0 | J19: 0 | K19: 0 | L19: 0 | M19: 0 | N19: 0 | O19: 432920 | P19: 0 | Q19: 0 | R19: 0 | S19: 0 | T19: 0 | U19: 551300 | V19: 0 | W19: 0 | X19: 0 | Y19: 0 | Z19: 0 | AA19: 0 | AB19: 406546 | AC19: 0 | AD19: 0 | AE19: 0 | AF19: 0 | AG19: 0 | AH19: =SUM(C19:AG19) -> 1913966
A20: Tofu | B20: =AH20/$AH$10 -> 0.013044162 | C20: 0 | D20: 0 | E20: 0 | F20: 0 | G20: 0 | H20: 84000 | I20: 0 | J20: 0 | K20: 0 | L20: 0 | M20: 84000 | N20: 0 | O20: 0 | P20: 84000 | Q20: 0 | R20: 0 | S20: 0 | T20: 0 | U20: 0 | V20: 84000 | W20: 0 | X20: 0 | Y20: 0 | Z20: 0 | AA20: 0 | AB20: 84000 | AC20: 0 | AD20: 84000 | AE20: 0 | AF20: 0 | AG20: 0 | AH20: =SUM(C20:AG20) -> 504000
A21: shen | B21: =AH21/$AH$10 -> 0.0028180825 | C21: 0 | D21: 0 | E21: 0 | F21: 0 | G21: 0 | H21: 0 | I21: 0 | J21: 0 | K21: 0 | L21: 0 | M21: 108885 | N21: 0 | O21: 0 | P21: 0 | Q21: 0 | R21: 0 | S21: 0 | T21: 0 | U21: 0 | V21: 0 | W21: 0 | X21: 0 | Y21: 0 | Z21: 0 | AA21: 0 | AB21: 0 | AC21: 0 | AD21: 0 | AE21: 0 | AF21: 0 | AG21: 0 | AH21: =SUM(C21:AG21) -> 108885
A22: Mozzen | B22: =AH22/$AH$10 -> 0.0074840881 | C22: 0 | D22: 0 | E22: 0 | F22: 0 | G22: 0 | H22: 0 | I22: 0 | J22: 0 | K22: 0 | L22: 0 | M22: 0 | N22: 289170 | O22: 0 | P22: 0 | Q22: 0 | R22: 0 | S22: 0 | T22: 0 | U22: 0 | V22: 0 | W22: 0 | X22: 0 | Y22: 0 | Z22: 0 | AA22: 0 | AB22: 0 | AC22: 0 | AD22: 0 | AE22: 0 | AF22: 0 | AG22: 0 | AH22: =SUM(C22:AG22) -> 289170
A23: Café y Té | B23: =AH23/$AH$10 -> 0 | C23: 0 | D23: 0 | E23: 0 | F23: 0 | G23: 0 | H23: 0 | I23: 0 | J23: 0 | K23: 0 | L23: 0 | M23: 0 | N23: 0 | O23: 0 | P23: 0 | Q23: 0 | R23: 0 | S23: 0 | T23: 0 | U23: 0 | V23: 0 | W23: 0 | X23: 0 | Y23: 0 | Z23: 0 | AA23: 0 | AB23: 0 | AC23: 0 | AD23: 0 | AE23: 0 | AF23: 0 | AG23: 0 | AH23: =SUM(C23:AG23) -> 0
A24: Leche de soya | B24: =AH24/$AH$10 -> 0.003349658 | C24: 0 | D24: 0 | E24: 0 | F24: 0 | G24: 0 | H24: 0 | I24: 0 | J24: 0 | K24: 0 | L24: 0 | M24: 0 | N24: 0 | O24: 0 | P24: 0 | Q24: 0 | R24: 0 | S24: 0 | T24: 129424 | U24: 0 | V24: 0 | W24: 0 | X24: 0 | Y24: 0 | Z24: 0 | AA24: 0 | AB24: 0 | AC24: 0 | AD24: 0 | AE24: 0 | AF24: 0 | AG24: 0 | AH24: =SUM(C24:AG24) -> 129424
A25: Bebestibles | B25: =AH25/$AH$10 -> 0.0058143835 | C25: 0 | D25: 0 | E25: 10000 | F25: 0 | G25: 0 | H25: 0 | I25: 0 | J25: 0 | K25: =46410+84264 -> 130674 | L25: 0 | M25: 32130 | N25: 0 | O25: 0 | P25: 0 | Q25: 0 | R25: 0 | S25: 0 | T25: 0 | U25: 0 | V25: 0 | W25: 0 | X25: 0 | Y25: 0 | Z25: 0 | AA25: 0 | AB25: 0 | AC25: 0 | AD25: 51852 | AE25: 0 | AF25: 0 | AG25: 0 | AH25: =SUM(C25:AG25) -> 224656
A26: Brugga | B26: =AH26/$AH$10 -> 0.013822464 | C26: 0 | D26: 0 | E26: 0 | F26: 0 | G26: 0 | H26: 157080 | I26: 0 | J26: 0 | K26: 0 | L26: 0 | M26: 157080 | N26: 0 | O26: 0 | P26: 94248 | Q26: 0 | R26: 0 | S26: 0 | T26: 0 | U26: 0 | V26: 0 | W26: 0 | X26: 0 | Y26: 0 | Z26: 0 | AA26: 0 | AB26: 0 | AC26: 125664 | AD26: 0 | AE26: 0 | AF26: 0 | AG26: 0 | AH26: =SUM(C26:AG26) -> 534072
A27: Colación | B27: =AH27/$AH$10 -> 0.005686323 | C27: 0 | D27: 0 | E27: 35800 | F27: 0 | G27: 0 | H27: 0 | I27: 0 | J27: 0 | K27: 83006 | L27: 21080 | M27: 0 | N27: 15660 | O27: 0 | P27: 0 | Q27: 0 | R27: 0 | S27: 15620 | T27: 0 | U27: 0 | V27: 0 | W27: 0 | X27: 0 | Y27: 0 | Z27: 0 | AA27: 0 | AB27: 48542 | AC27: 0 | AD27: 0 | AE27: 0 | AF27: 0 | AG27: 0 | AH27: =SUM(C27:AG27) -> 219708
A28: Empaques y desechables | B28: =AH28/$AH$10 -> 0.013875598 | C28: 0 | D28: 0 | E28: 0 | F28: 0 | G28: 313589 | H28: 0 | I28: 0 | J28: 9800 | K28: 0 | L28: 0 | M28: 0 | N28: 0 | O28: 0 | P28: 0 | Q28: 0 | R28: 0 | S28: 0 | T28: 0 | U28: 114918 | V28: 97818 | W28: 0 | X28: 0 | Y28: 0 | Z28: 0 | AA28: 0 | AB28: 0 | AC28: 0 | AD28: 0 | AE28: 0 | AF28: 0 | AG28: 0 | AH28: =SUM(C28:AG28) -> 536125
A29: Soyas sachet | B29: =AH29/$AH$10 -> 0.0029115657 | C29: 0 | D29: 0 | E29: 0 | F29: 0 | G29: 0 | H29: 0 | I29: 0 | J29: 0 | K29: 0 | L29: 0 | M29: 112497 | N29: 0 | O29: 0 | P29: 0 | Q29: 0 | R29: 0 | S29: 0 | T29: 0 | U29: 0 | V29: 0 | W29: 0 | X29: 0 | Y29: 0 | Z29: 0 | AA29: 0 | AB29: 0 | AC29: 0 | AD29: 0 | AE29: 0 | AF29: 0 | AG29: 0 | AH29: =SUM(C29:AG29) -> 112497
A30: Servilletas | B30: =AH30/$AH$10 -> 0.0042871813 | C30: 0 | D30: 0 | E30: 0 | F30: 0 | G30: 0 | H30: 0 | I30: 0 | J30: 0 | K30: 0 | L30: 0 | M30: 0 | N30: 165648 | O30: 0 | P30: 0 | Q30: 0 | R30: 0 | S30: 0 | T30: 0 | U30: 0 | V30: 0 | W30: 0 | X30: 0 | Y30: 0 | Z30: 0 | AA30: 0 | AB30: 0 | AC30: 0 | AD30: 0 | AE30: 0 | AF30: 0 | AG30: 0 | AH30: =SUM(C30:AG30) -> 165648
A31: Limpieza e higiene | B31: =AH31/$AH$10 -> 0.00028935265 | C31: 0 | D31: 0 | E31: 0 | F31: 0 | G31: 2000 | H31: 0 | I31: 6480 | J31: 0 | K31: 0 | L31: 0 | M31: 0 | N31: 0 | O31: 0 | P31: 0 | Q31: 0 | R31: 0 | S31: 0 | T31: 0 | U31: 0 | V31: 2700 | W31: 0 | X31: 0 | Y31: 0 | Z31: 0 | AA31: 0 | AB31: 0 | AC31: 0 | AD31: 0 | AE31: 0 | AF31: 0 | AG31: 0 | AH31: =SUM(C31:AG31) -> 11180
A32: Postres | B32: =AH32/$AH$10 -> 0.023952964 | C32: 84200 | D32: 0 | E32: 0 | F32: 88956 | G32: 241218 | H32: 78000 | I32: 0 | J32: 0 | K32: 0 | L32: 0 | M32: 0 | N32: 0 | O32: 0 | P32: 0 | Q32: 81700 | R32: 0 | S32: 0 | T32: 0 | U32: 0 | V32: 0 | W32: 0 | X32: =176420+84000 -> 260420 | Y32: 0 | Z32: 0 | AA32: 0 | AB32: 0 | AC32: 0 | AD32: 0 | AE32: 0 | AF32: 91000 | AG32: 0 | AH32: =SUM(C32:AG32) -> 925494
A34: Gastos FV | B34: =AH34/$AH$10 -> 0.21575973 | C34: =sum(C35+C55+C65) -> 0 | D34: =sum(D35+D55+D65) -> 0 | E34: =sum(E35+E55+E65) -> 58245 | F34: =sum(F35+F55+F65) -> 0 | G34: =sum(G35+G55+G65) -> 84350 | H34: =sum(H35+H55+H65) -> 322160 | I34: =sum(I35+I55+I65) -> 1941129 | J34: =sum(J35+J55+J65) -> 59441 | ... AH34: =sum(AH35+AH55+AH65) -> 8336519
A35: Operaciones | B35: =AH35/$AH$10 -> 0.1812852 | C35: =sum(C36:C54) -> 0 | D35: =sum(D36:D54) -> 0 | E35: =sum(E36:E54) -> 0 | F35: =sum(F36:F54) -> 0 | G35: =sum(G36:G54) -> 84350 | H35: =sum(H36:H54) -> 212205 | I35: =sum(I36:I54) -> 1937141 | J35: =sum(J36:J54) -> 0 | ... AH35: =sum(AH36:AH54) -> 7004493
A36: Electricidad | B36: =AH36/$AH$10 -> 0.035708523 | C36: 0 | D36: 0 | E36: 0 | F36: 0 | G36: 0 | H36: 0 | I36: 0 | J36: 0 | K36: 0 | L36: 0 | M36: 0 | N36: 0 | O36: 0 | P36: 0 | Q36: =128606+363901 -> 492507 | R36: 0 | S36: 0 | T36: 0 | U36: 0 | V36: 0 | W36: 0 | X36: 0 | Y36: 0 | Z36: 0 | AA36: 0 | AB36: 0 | AC36: 0 | AD36: 0 | AE36: 887198 | AF36: 0 | AG36: 0 | AH36: =SUM(C36:AG36) -> 1379705
A37: Agua | B37: =AH37/$AH$10 -> 0.0019217364 | C37: 0 | D37: 0 | E37: 0 | F37: 0 | G37: 0 | H37: 0 | I37: 0 | J37: 0 | K37: 0 | L37: 0 | M37: 0 | N37: 0 | O37: 0 | P37: 0 | Q37: 74252 | R37: 0 | S37: 0 | T37: 0 | U37: 0 | V37: 0 | W37: 0 | X37: 0 | Y37: 0 | Z37: 0 | AA37: 0 | AB37: 0 | AC37: 0 | AD37: 0 | AE37: 0 | AF37: 0 | AG37: 0 | AH37: =SUM(C37:AG37) -> 74252
A38: Gas | B38: =AH38/$AH$10 -> 0.010043306 | C38: 0 | D38: 0 | E38: 0 | F38: 0 | G38: 0 | H38: 0 | I38: 0 | J38: 0 | K38: 0 | L38: 0 | M38: 0 | N38: 0 | O38: 0 | P38: 0 | Q38: 388053 | R38: 0 | S38: 0 | T38: 0 | U38: 0 | V38: 0 | W38: 0 | X38: 0 | Y38: 0 | Z38: 0 | AA38: 0 | AB38: 0 | AC38: 0 | AD38: 0 | AE38: 0 | AF38: 0 | AG38: 0 | AH38: =SUM(C38:AG38) -> 388053
A39: Restaurantpe | B39: =AH39/$AH$10 -> 0 | C39: 0 | D39: 0 | E39: 0 | F39: 0 | G39: 0 | H39: 0 | I39: 0 | J39: 0 | K39: 0 | L39: 0 | M39: 0 | N39: 0 | O39: 0 | P39: 0 | Q39: 0 | R39: 0 | S39: 0 | T39: 0 | U39: 0 | V39: 0 | W39: 0 | X39: 0 | Y39: 0 | Z39: 0 | AA39: 0 | AB39: 0 | AC39: 0 | AD39: 0 | AE39: 0 | AF39: 0 | AG39: 0 | AH39: =SUM(C39:AG39) -> 0
A40: Toteat | B40: =AH40/$AH$10 -> 0.0054921358 | C40: 0 | D40: 0 | E40: 0 | F40: 0 | G40: 0 | H40: =96658+115547 -> 212205 | I40: 0 | J40: 0 | K40: 0 | L40: 0 | M40: 0 | N40: 0 | O40: 0 | P40: 0 | Q40: 0 | R40: 0 | S40: 0 | T40: 0 | U40: 0 | V40: 0 | W40: 0 | X40: 0 | Y40: 0 | Z40: 0 | AA40: 0 | AB40: 0 | AC40: 0 | AD40: 0 | AE40: 0 | AF40: 0 | AG40: 0 | AH40: =SUM(C40:AG40) -> 212205
A41: Alarma | B41: =AH41/$AH$10 -> 0.0012484091 | C41: 0 | D41: 0 | E41: 0 | F41: 0 | G41: 0 | H41: 0 | I41: 0 | J41: 0 | K41: 0 | L41: 0 | M41: 0 | N41: 0 | O41: 0 | P41: 0 | Q41: 48236 | R41: 0 | S41: 0 | T41: 0 | U41: 0 | V41: 0 | W41: 0 | X41: 0 | Y41: 0 | Z41: 0 | AA41: 0 | AB41: 0 | AC41: 0 | AD41: 0 | AE41: 0 | AF41: 0 | AG41: 0 | AH41: =SUM(C41:AG41) -> 48236
A42: VTR | B42: =AH42/$AH$10 -> 0 | C42: 0 | D42: 0 | E42: 0 | F42: 0 | G42: 0 | H42: 0 | I42: 0 | J42: 0 | K42: 0 | L42: 0 | M42: 0 | N42: 0 | O42: 0 | P42: 0 | Q42: 0 | R42: 0 | S42: 0 | T42: 0 | U42: 0 | V42: 0 | W42: 0 | X42: 0 | Y42: 0 | Z42: 0 | AA42: 0 | AB42: 0 | AC42: 0 | AD42: 0 | AE42: 0 | AF42: 0 | AG42: 0 | AH42: =SUM(C42:AG42) -> 0
A43: Bodega | B43: =AH43/$AH$10 -> 0 | C43: 0 | D43: 0 | E43: 0 | F43: 0 | G43: 0 | H43: 0 | I43: 0 | J43: 0 | K43: 0 | L43: 0 | M43: 0 | N43: 0 | O43: 0 | P43: 0 | Q43: 0 | R43: 0 | S43: 0 | T43: 0 | U43: 0 | V43: 0 | W43: 0 | X43: 0 | Y43: 0 | Z43: 0 | AA43: 0 | AB43: 0 | AC43: 0 | AD43: 0 | AE43: 0 | AF43: 0 | AG43: 0 | AH43: =SUM(C43:AG43) -> 0
A44: Arriendo | B44: =AH44/$AH$10 -> 0.047780481 | C44: 0 | D44: 0 | E44: 0 | F44: 0 | G44: 0 | H44: 0 | I44: 1846141 | J44: 0 | K44: 0 | L44: 0 | M44: 0 | N44: 0 | O44: 0 | P44: 0 | Q44: 0 | R44: 0 | S44: 0 | T44: 0 | U44: 0 | V44: 0 | W44: 0 | X44: 0 | Y44: 0 | Z44: 0 | AA44: 0 | AB44: 0 | AC44: 0 | AD44: 0 | AE44: 0 | AF44: 0 | AG44: 0 | AH44: =SUM(C44:AG44) -> 1846141
A45: Funmigacion | B45: =AH45/$AH$10 -> 0 | C45: 0 | D45: 0 | E45: 0 | F45: 0 | G45: 0 | H45: 0 | I45: 0 | J45: 0 | K45: 0 | L45: 0 | M45: 0 | N45: 0 | O45: 0 | P45: 0 | Q45: 0 | R45: 0 | S45: 0 | T45: 0 | U45: 0 | V45: 0 | W45: 0 | X45: 0 | Y45: 0 | Z45: 0 | AA45: 0 | AB45: 0 | AC45: 0 | AD45: 0 | AE45: 0 | AF45: 0 | AG45: 0 | AH45: =SUM(C45:AG45) -> 0
A46: Aroclean | B46: =AH46/$AH$10 -> 0.0020009848 | C46: 0 | D46: 0 | E46: 0 | F46: 0 | G46: 0 | H46: 0 | I46: 0 | J46: 0 | K46: 0 | L46: 0 | M46: 0 | N46: 0 | O46: 0 | P46: 0 | Q46: 0 | R46: 0 | S46: 0 | T46: 0 | U46: 0 | V46: 77314 | W46: 0 | X46: 0 | Y46: 0 | Z46: 0 | AA46: 0 | AB46: 0 | AC46: 0 | AD46: 0 | AE46: 0 | AF46: 0 | AG46: 0 | AH46: =SUM(C46:AG46) -> 77314
A47: Reposición de vasos | B47: =AH47/$AH$10 -> 0 | C47: 0 | D47: 0 | E47: 0 | F47: 0 | G47: 0 | H47: 0 | I47: 0 | J47: 0 | K47: 0 | L47: 0 | M47: 0 | N47: 0 | O47: 0 | P47: 0 | Q47: 0 | R47: 0 | S47: 0 | T47: 0 | U47: 0 | V47: 0 | W47: 0 | X47: 0 | Y47: 0 | Z47: 0 | AA47: 0 | AB47: 0 | AC47: 0 | AD47: 0 | AE47: 0 | AF47: 0 | AG47: 0 | AH47: =SUM(C47:AG47) -> 0
A48: Reposición Articulos cocina | B48: =AH48/$AH$10 -> 0.0043571125 | C48: 0 | D48: 0 | E48: 0 | F48: 0 | G48: 77350 | H48: 0 | I48: 91000 | J48: 0 | K48: 0 | L48: 0 | M48: 0 | N48: 0 | O48: 0 | P48: 0 | Q48: 0 | R48: 0 | S48: 0 | T48: 0 | U48: 0 | V48: 0 | W48: 0 | X48: 0 | Y48: 0 | Z48: 0 | AA48: 0 | AB48: 0 | AC48: 0 | AD48: 0 | AE48: 0 | AF48: 0 | AG48: 0 | AH48: =SUM(C48:AG48) -> 168350
A49: Reposición articulos salón | B49: =AH49/$AH$10 -> 0.00018116892 | C49: 0 | D49: 0 | E49: 0 | F49: 0 | G49: 7000 | H49: 0 | I49: 0 | J49: 0 | K49: 0 | L49: 0 | M49: 0 | N49: 0 | O49: 0 | P49: 0 | Q49: 0 | R49: 0 | S49: 0 | T49: 0 | U49: 0 | V49: 0 | W49: 0 | X49: 0 | Y49: 0 | Z49: 0 | AA49: 0 | AB49: 0 | AC49: 0 | AD49: 0 | AE49: 0 | AF49: 0 | AG49: 0 | AH49: =SUM(C49:AG49) -> 7000
A50: Reparaciones mano de obra | B50: =AH50/$AH$10 -> 0 | C50: 0 | D50: 0 | E50: 0 | F50: 0 | G50: 0 | H50: 0 | I50: 0 | J50: 0 | K50: 0 | L50: 0 | M50: 0 | N50: 0 | O50: 0 | P50: 0 | Q50: 0 | R50: 0 | S50: 0 | T50: 0 | U50: 0 | V50: 0 | W50: 0 | X50: 0 | Y50: 0 | Z50: 0 | AA50: 0 | AB50: 0 | AC50: 0 | AD50: 0 | AE50: 0 | AF50: 0 | AG50: 0 | AH50: =SUM(C50:AG50) -> 0
A51: Reparaciones articulos | B51: =AH51/$AH$10 -> 0 | C51: 0 | D51: 0 | E51: 0 | F51: 0 | G51: 0 | H51: 0 | I51: 0 | J51: 0 | K51: 0 | L51: 0 | M51: 0 | N51: 0 | O51: 0 | P51: 0 | Q51: 0 | R51: 0 | S51: 0 | T51: 0 | U51: 0 | V51: 0 | W51: 0 | X51: 0 | Y51: 0 | Z51: 0 | AA51: 0 | AB51: 0 | AC51: 0 | AD51: 0 | AE51: 0 | AF51: 0 | AG51: 0 | AH51: =SUM(C51:AG51) -> 0
A52: Reparaciones maquinaria | B52: =AH52/$AH$10 -> 0.0036233784 | C52: 0 | D52: 0 | E52: 0 | F52: 0 | G52: 0 | H52: 0 | I52: 0 | J52: 0 | K52: 0 | L52: 0 | M52: 0 | N52: 0 | O52: 0 | P52: 0 | Q52: 0 | R52: 0 | S52: 0 | T52: 0 | U52: 0 | V52: 0 | W52: 0 | X52: 0 | Y52: 0 | Z52: 0 | AA52: 0 | AB52: 140000 | AC52: 0 | AD52: 0 | AE52: 0 | AF52: 0 | AG52: 0 | AH52: =SUM(C52:AG52) -> 140000
... A54: Fee | B54: =AH54/$AH$10 -> 0.068927967 | C54: 0 | D54: 0 | E54: 0 | F54: 0 | G54: 0 | H54: 0 | I54: 0 | J54: 0 | K54: 0 | L54: 0 | M54: 0 | N54: 0 | O54: 2663237 | P54: 0 | Q54: 0 | R54: 0 | S54: 0 | T54: 0 | U54: 0 | V54: 0 | W54: 0 | X54: 0 | Y54: 0 | Z54: 0 | AA54: 0 | AB54: 0 | AC54: 0 | AD54: 0 | AE54: 0 | AF54: 0 | AG54: 0 | AH54: =SUM(C54:AG54) -> 2663237
A55: Administración y finanzas | B55: =AH55/$AH$10 -> 0.002873572 | C55: =sum(C56:C63) -> 0 | D55: =sum(D56:D63) -> 0 | E55: =sum(E56:E63) -> 0 | F55: =sum(F56:F63) -> 0 | G55: =sum(G56:G63) -> 0 | H55: =sum(H56:H63) -> 0 | I55: =sum(I56:I63) -> 3988 | J55: =sum(J56:J63) -> 59441 | ... AE55: =sum(AE56:AE63) -> 6000 | AF55: =SUM(AF56:AF63) -> 0 | AG55: =sum(AG56:AG63) -> 0 | AH55: =SUM(AH56:AH63) -> 111029
A56: Comisiones cuenta corriente | B56: =AH56/$AH$10 -> 0.00010321452 | C56: 0 | D56: 0 | E56: 0 | F56: 0 | G56: 0 | H56: 0 | I56: 3988 | J56: 0 | K56: 0 | L56: 0 | M56: 0 | N56: 0 | O56: 0 | P56: 0 | Q56: 0 | R56: 0 | S56: 0 | T56: 0 | U56: 0 | V56: 0 | W56: 0 | X56: 0 | Y56: 0 | Z56: 0 | AA56: 0 | AB56: 0 | AC56: 0 | AD56: 0 | AE56: 0 | AF56: 0 | AG56: 0 | AH56: =SUM(C56:AG56) -> 3988
A57: Contadora | B57: =AH57/$AH$10 -> 0 | C57: 0 | D57: 0 | E57: 0 | F57: 0 | G57: 0 | H57: 0 | I57: 0 | J57: 0 | K57: 0 | L57: 0 | M57: 0 | N57: 0 | O57: 0 | P57: 0 | Q57: 0 | R57: 0 | S57: 0 | T57: 0 | U57: 0 | V57: 0 | W57: 0 | X57: 0 | Y57: 0 | Z57: 0 | AA57: 0 | AB57: 0 | AC57: 0 | AD57: 0 | AE57: 0 | AF57: 0 | AG57: 0 | AH57: =SUM(C57:AG57) -> 0
A58: Patentes comerciales | B58: =AH58/$AH$10 -> 0 | C58: 0 | D58: 0 | E58: 0 | F58: 0 | G58: 0 | H58: 0 | I58: 0 | J58: 0 | K58: 0 | L58: 0 | M58: 0 | N58: 0 | O58: 0 | P58: 0 | Q58: 0 | R58: 0 | S58: 0 | T58: 0 | U58: 0 | V58: 0 | W58: 0 | X58: 0 | Y58: 0 | Z58: 0 | AA58: 0 | AB58: 0 | AC58: 0 | AD58: 0 | AE58: 0 | AF58: 0 | AG58: 0 | AH58: =SUM(C58:AG58) -> 0
A59: Insumos de oficina | B59: =AH59/$AH$10 -> 0.0016936965 | C59: 0 | D59: 0 | E59: 0 | F59: 0 | G59: 0 | H59: 0 | I59: 0 | J59: 59441 | K59: 0 | L59: 0 | M59: 0 | N59: 0 | O59: 0 | P59: 0 | Q59: 0 | R59: 0 | S59: 0 | T59: 0 | U59: 0 | V59: 0 | W59: 0 | X59: 0 | Y59: 0 | Z59: 0 | AA59: 0 | AB59: 0 | AC59: 0 | AD59: 0 | AE59: 6000 | AF59: 0 | AG59: 0 | AH59: =SUM(C59:AG59) -> 65441
A60: Wasabil | B60: =AH60/$AH$10 -> 0 | C60: 0 | D60: 0 | E60: 0 | F60: 0 | G60: 0 | H60: 0 | I60: 0 | J60: 0 | K60: 0 | L60: 0 | M60: 0 | N60: 0 | O60: 0 | P60: 0 | Q60: 0 | R60: 0 | S60: 0 | T60: 0 | U60: 0 | V60: 0 | W60: 0 | X60: 0 | Y60: 0 | Z60: 0 | AA60: 0 | AB60: 0 | AC60: 0 | AD60: 0 | AE60: 0 | AF60: 0 | AG60: 0 | AH60: =SUM(C60:AG60) -> 0
A61: Devolución clientes | B61: =AH61/$AH$10 -> 0.001076661 | C61: 0 | D61: 0 | E61: 0 | F61: 0 | G61: 0 | H61: 0 | I61: 0 | J61: 0 | K61: 0 | L61: 0 | M61: 0 | N61: 0 | O61: 0 | P61: 0 | Q61: 0 | R61: 41600 | S61: 0 | T61: 0 | U61: 0 | V61: 0 | W61: 0 | X61: 0 | Y61: 0 | Z61: 0 | AA61: 0 | AB61: 0 | AC61: 0 | AD61: 0 | AE61: 0 | AF61: 0 | AG61: 0 | AH61: =SUM(C61:AG61) -> 41600
A62: Reuniones ejecutivas | B62: =AH62/$AH$10 -> 0 | C62: 0 | D62: 0 | E62: 0 | F62: 0 | G62: 0 | H62: 0 | I62: 0 | J62: 0 | K62: 0 | L62: 0 | M62: 0 | N62: 0 | O62: 0 | P62: 0 | Q62: 0 | R62: 0 | S62: 0 | T62: 0 | U62: 0 | V62: 0 | W62: 0 | X62: 0 | Y62: 0 | Z62: 0 | AA62: 0 | AB62: 0 | AC62: 0 | AD62: 0 | AE62: 0 | AF62: 0 | AG62: 0 | AH62: =SUM(C62:AG62) -> 0
A63: Certificados | B63: =AH63/$AH$10 -> 0 | C63: 0 | D63: 0 | E63: 0 | F63: 0 | G63: 0 | H63: 0 | I63: 0 | J63: 0 | K63: 0 | L63: 0 | M63: 0 | N63: 0 | O63: 0 | P63: 0 | Q63: 0 | R63: 0 | S63: 0 | T63: 0 | U63: 0 | V63: 0 | W63: 0 | X63: 0 | Y63: 0 | Z63: 0 | AA63: 0 | AB63: 0 | AC63: 0 | AD63: 0 | AE63: 0 | AF63: 0 | AG63: 0 | AH63: =SUM(C63:AG63) -> 0
A65: Marketing | B65: =AH65/$AH$10 -> 0.031600958 | C65: =sum(C66:C75) -> 0 | D65: =sum(D66:D75) -> 0 | E65: =sum(E66:E75) -> 58245 | F65: =sum(F66:F75) -> 0 | G65: =sum(G66:G75) -> 0 | H65: =sum(H66:H75) -> 109955 | I65: =sum(I66:I75) -> 0 | J65: =sum(J66:J75) -> 0 | ... Z65: =sum(Z66:Z75) -> 110828 | AA65: =SUM(AA66:AA76) -> 121087 | AB65: =sum(AB66:AB75) -> 0 | AC65: =sum(AC66:AC75) -> 100203 | AD65: =sum(AD66:AD75) -> 0 | AE65: =sum(AE66:AE75) -> 0 | AF65: =sum(AF66:AF75) -> 0 | AG65: =sum(AG66:AG75) -> 600000 | AH65: =SUM(AH66:AH76) -> 1220997
A66: Mercat | B66: =AH66/$AH$10 -> 0.0085765366 | C66: 0 | D66: 0 | E66: 0 | F66: 0 | G66: 0 | H66: 109955 | I66: 0 | J66: 0 | K66: 0 | L66: 0 | M66: 0 | N66: 0 | O66: 0 | P66: 0 | Q66: 0 | R66: 0 | S66: 0 | T66: 0 | U66: 0 | V66: 0 | W66: 0 | X66: 0 | Y66: 0 | Z66: 110828 | AA66: 110597 | AB66: 0 | AC66: 0 | AD66: 0 | AE66: 0 | AF66: 0 | AG66: 0 | AH66: =SUM(C66:AG66) -> 331380
A67: Brevo | B67: =AH67/$AH$10 -> 0.0015074548 | C67: 0 | D67: 0 | E67: 58245 | F67: 0 | G67: 0 | H67: 0 | I67: 0 | J67: 0 | K67: 0 | L67: 0 | M67: 0 | N67: 0 | O67: 0 | P67: 0 | Q67: 0 | R67: 0 | S67: 0 | T67: 0 | U67: 0 | V67: 0 | W67: 0 | X67: 0 | Y67: 0 | Z67: 0 | AA67: 0 | AB67: 0 | AC67: 0 | AD67: 0 | AE67: 0 | AF67: 0 | AG67: 0 | AH67: =SUM(C67:AG67) -> 58245
A68: Fiweex | B68: =AH68/$AH$10 -> 0.0012319487 | C68: 0 | D68: 0 | E68: 0 | F68: 0 | G68: 0 | H68: 0 | I68: 0 | J68: 0 | K68: 0 | L68: 0 | M68: 0 | N68: 0 | O68: 0 | P68: 0 | Q68: 0 | R68: 0 | S68: 0 | T68: 0 | U68: 47600 | V68: 0 | W68: 0 | X68: 0 | Y68: 0 | Z68: 0 | AA68: 0 | AB68: 0 | AC68: 0 | AD68: 0 | AE68: 0 | AF68: 0 | AG68: 0 | AH68: =SUM(C68:AG68) -> 47600
A69: Fujifilm instax | B69: =AH69/$AH$10 -> 0.0018913776 | C69: 0 | D69: 0 | E69: 0 | F69: 0 | G69: 0 | H69: 0 | I69: 0 | J69: 0 | K69: =57279+7900+7900 -> 73079 | L69: 0 | M69: 0 | N69: 0 | O69: 0 | P69: 0 | Q69: 0 | R69: 0 | S69: 0 | T69: 0 | U69: 0 | V69: 0 | W69: 0 | X69: 0 | Y69: 0 | Z69: 0 | AA69: 0 | AB69: 0 | AC69: 0 | AD69: 0 | AE69: 0 | AF69: 0 | AG69: 0 | AH69: =SUM(C69:AG69) -> 73079
A70: Resos | B70: =AH70/$AH$10 -> 0.0025933813 | C70: 0 | D70: 0 | E70: 0 | F70: 0 | G70: 0 | H70: 0 | I70: 0 | J70: 0 | K70: 0 | L70: 0 | M70: 0 | N70: 0 | O70: 0 | P70: 0 | Q70: 0 | R70: 0 | S70: 0 | T70: 0 | U70: 0 | V70: 0 | W70: 0 | X70: 0 | Y70: 0 | Z70: 0 | AA70: 0 | AB70: 0 | AC70: 100203 | AD70: 0 | AE70: 0 | AF70: 0 | AG70: 0 | AH70: =SUM(C70:AG70) -> 100203
A71: HappyCow | B71: =AH71/$AH$10 -> 0 | C71: 0 | D71: 0 | E71: 0 | F71: 0 | G71: 0 | H71: 0 | I71: 0 | J71: 0 | K71: 0 | L71: 0 | M71: 0 | N71: 0 | O71: 0 | P71: 0 | Q71: 0 | R71: 0 | S71: 0 | T71: 0 | U71: 0 | V71: 0 | W71: 0 | X71: 0 | Y71: 0 | Z71: 0 | AA71: 0 | AB71: 0 | AC71: 0 | AD71: 0 | AE71: 0 | AF71: 0 | AG71: 0 | AH71: =SUM(C71:AG71) -> 0
A72: Meta Ads | B72: =AH72/$AH$10 -> 0 | C72: 0 | D72: 0 | E72: 0 | F72: 0 | G72: 0 | H72: 0 | I72: 0 | J72: 0 | K72: 0 | L72: 0 | M72: 0 | N72: 0 | O72: 0 | P72: 0 | Q72: 0 | R72: 0 | S72: 0 | T72: 0 | U72: 0 | V72: 0 | W72: 0 | X72: 0 | Y72: 0 | Z72: 0 | AA72: 0 | AB72: 0 | AC72: 0 | AD72: 0 | AE72: 0 | AF72: 0 | AG72: 0 | AH72: =SUM(C72:AG72) -> 0
A73: Influencers | B73: =AH73/$AH$10 -> 0 | C73: 0 | D73: 0 | E73: 0 | F73: 0 | G73: 0 | H73: 0 | I73: 0 | J73: 0 | K73: 0 | L73: 0 | M73: 0 | N73: 0 | O73: 0 | P73: 0 | Q73: 0 | R73: 0 | S73: 0 | T73: 0 | U73: 0 | V73: 0 | W73: 0 | X73: 0 | Y73: 0 | Z73: 0 | AA73: 0 | AB73: 0 | AC73: 0 | AD73: 0 | AE73: 0 | AF73: 0 | AG73: 0 | AH73: =SUM(C73:AG73) -> 0
A74: Chatfuel | B74: =AH74/$AH$10 -> 0 | C74: 0 | D74: 0 | E74: 0 | F74: 0 | G74: 0 | H74: 0 | I74: 0 | J74: 0 | K74: 0 | L74: 0 | M74: 0 | N74: 0 | O74: 0 | P74: 0 | Q74: 0 | R74: 0 | S74: 0 | T74: 0 | U74: 0 | V74: 0 | W74: 0 | X74: 0 | Y74: 0 | Z74: 0 | AA74: 0 | AB74: 0 | AC74: 0 | AD74: 0 | AE74: 0 | AF74: 0 | AG74: 0 | AH74: =SUM(C74:AG74) -> 0
A75: Community manager | B75: =AH75/$AH$10 -> 0.015528765 | C75: 0 | D75: 0 | E75: 0 | F75: 0 | G75: 0 | H75: 0 | I75: 0 | J75: 0 | K75: 0 | L75: 0 | M75: 0 | N75: 0 | O75: 0 | P75: 0 | Q75: 0 | R75: 0 | S75: 0 | T75: 0 | U75: 0 | V75: 0 | W75: 0 | X75: 0 | Y75: 0 | Z75: 0 | AA75: 0 | AB75: 0 | AC75: 0 | AD75: 0 | AE75: 0 | AF75: 0 | AG75: 600000 | AH75: =SUM(C75:AG75) -> 600000
A76: Microsoft | B76: =AH76/$AH$10 -> 0.00027149457 | C76: 0 | D76: 0 | E76: 0 | F76: 0 | G76: 0 | H76: 0 | I76: 0 | J76: 0 | K76: 0 | L76: 0 | M76: 0 | N76: 0 | O76: 0 | P76: 0 | Q76: 0 | R76: 0 | S76: 0 | T76: 0 | U76: 0 | V76: 0 | W76: 0 | X76: 0 | Y76: 0 | Z76: 0 | AA76: 10490 | AB76: 0 | AC76: 0 | AD76: 0 | AE76: 0 | AF76: 0 | AG76: 0 | AH76: =SUM(C76:AG76) -> 10490
A78: Inversiones activos | B78: =AH78/$AH$10 -> 0.10018147 | C78: =sum(C79:C81) -> 0 | D78: =SUM(D79:D82) -> 109171 | E78: =SUM(E79:E82) -> 0 | F78: =SUM(F79:F82) -> 0 | G78: =SUM(G79:G82) -> 0 | H78: =SUM(H79:H82) -> 998000 | I78: =SUM(I79:I82) -> 0 | J78: =SUM(J79:J82) -> 123609 | K78: =SUM(K79:K82) -> 0 | ... AG78: =SUM(AG79:AG82) -> 0 | AH78: =sum(AH79:AH82) -> 3870809
A79: Nuevas maquinaria | B79: =AH79/$AH$10 -> 0 | C79: 0 | D79: 0 | E79: 0 | F79: 0 | G79: 0 | H79: 0 | I79: 0 | J79: 0 | K79: 0 | L79: 0 | M79: 0 | N79: 0 | O79: 0 | P79: 0 | Q79: 0 | R79: 0 | S79: 0 | T79: 0 | U79: 0 | V79: 0 | W79: 0 | X79: 0 | Y79: 0 | Z79: 0 | AA79: 0 | AB79: 0 | AC79: 0 | AD79: 0 | AE79: 0 | AF79: 0 | AG79: 0 | AH79: =SUM(C79:AG79) -> 0
A80: Nueva decoración y muebles | B80: =AH80/$AH$10 -> 0 | C80: 0 | D80: 0 | E80: 0 | F80: 0 | G80: 0 | H80: 0 | I80: 0 | J80: 0 | K80: 0 | L80: 0 | M80: 0 | N80: 0 | O80: 0 | P80: 0 | Q80: 0 | R80: 0 | S80: 0 | T80: 0 | U80: 0 | V80: 0 | W80: 0 | X80: 0 | Y80: 0 | Z80: 0 | AA80: 0 | AB80: 0 | AC80: 0 | AD80: 0 | AE80: 0 | AF80: 0 | AG80: 0 | AH80: =SUM(C80:AG80) -> 0
A81: Remodelaciones | B81: =AH81/$AH$10 -> 0 | C81: 0 | D81: 0 | E81: 0 | F81: 0 | G81: 0 | H81: 0 | I81: 0 | J81: 0 | K81: 0 | L81: 0 | M81: 0 | N81: 0 | O81: 0 | P81: 0 | Q81: 0 | R81: 0 | S81: 0 | T81: 0 | U81: 0 | V81: 0 | W81: 0 | X81: 0 | Y81: 0 | Z81: 0 | AA81: 0 | AB81: 0 | AC81: 0 | AD81: 0 | AE81: 0 | AF81: 0 | AG81: 0 | AH81: =SUM(C81:AG81) -> 0
A82: Kojo | B82: =AH82/$AH$10 -> 0.10018147 | C82: 0 | D82: 109171 | E82: 0 | F82: 0 | G82: 0 | H82: 998000 | I82: 0 | J82: 123609 | K82: 0 | L82: 381500 | M82: 0 | N82: 0 | O82: 0 | P82: 0 | Q82: 497500 | R82: =247306+16800 -> 264106 | S82: 0 | T82: 0 | U82: 0 | V82: 0 | W82: 0 | X82: 79147 | Y82: 257776 | Z82: 0 | AA82: 0 | AB82: 0 | AC82: 0 | AD82: 110000 | AE82: 0 | AF82: 1050000 | AG82: 0 | AH82: =SUM(C82:AG82) -> 3870809
A84: Dinero temporal | B84: =AH84/$AH$10 -> 0.11692997 | C84: =sum(C85:C88) -> 560784 | D84: =sum(D85:D88) -> 0 | E84: =sum(E85:E88) -> 0 | F84: =sum(F85:F88) -> 394889 | G84: =sum(G85:G88) -> 0 | H84: =sum(H85:H88) -> 0 | I84: =sum(I85:I88) -> 0 | J84: =sum(J85:J88) -> 642190 | ... AH84: =sum(AH85:AH88) -> 4517937
A85: Delifast | B85: =AH85/$AH$10 -> 0.068781686 | C85: 560784 | D85: 0 | E85: 0 | F85: 0 | G85: 0 | H85: 0 | I85: 0 | J85: 642190 | K85: 0 | L85: 0 | M85: 0 | N85: 0 | O85: 0 | P85: 0 | Q85: 0 | R85: 427978 | S85: 0 | T85: 0 | U85: 0 | V85: 0 | W85: 0 | X85: 545199 | Y85: 0 | Z85: 0 | AA85: 0 | AB85: 0 | AC85: 0 | AD85: 0 | AE85: 481434 | AF85: 0 | AG85: 0 | AH85: =SUM(C85:AG85) -> 2657585
A86: Uber direct | B86: =AH86/$AH$10 -> 0 | C86: 0 | D86: 0 | E86: 0 | F86: 0 | G86: 0 | H86: 0 | I86: 0 | J86: 0 | K86: 0 | L86: 0 | M86: 0 | N86: 0 | O86: 0 | P86: 0 | Q86: 0 | R86: 0 | S86: 0 | T86: 0 | U86: 0 | V86: 0 | W86: 0 | X86: 0 | Y86: 0 | Z86: 0 | AA86: 0 | AB86: 0 | AC86: 0 | AD86: 0 | AE86: 0 | AF86: 0 | AG86: 0 | AH86: =SUM(C86:AG86) -> 0
A87: Monto delivery | B87: =AH87/$AH$10 -> 0.0012721164 | C87: 0 | D87: 0 | E87: 0 | F87: 0 | G87: 0 | H87: 0 | I87: 0 | J87: 0 | K87: 0 | L87: 0 | M87: 0 | N87: 0 | O87: 0 | P87: 0 | Q87: 9080 | R87: 3794 | S87: 0 | T87: 0 | U87: 0 | V87: 0 | W87: 0 | X87: 2596 | Y87: 0 | Z87: 0 | AA87: 0 | AB87: 0 | AC87: =7881+6094 -> 13975 | AD87: 0 | AE87: =8596+3595 -> 12191 | AF87: 0 | AG87: 7516 | AH87: =SUM(C87:AG87) -> 49152
A88: Propina personal | B88: =AH88/$AH$10 -> 0.046876164 | C88: 0 | D88: 0 | E88: 0 | F88: 394889 | G88: 0 | H88: 0 | I88: 0 | J88: 0 | K88: 0 | L88: 0 | M88: 508610 | N88: 0 | O88: 0 | P88: 0 | Q88: 0 | R88: 0 | S88: 0 | T88: 525379 | U88: 0 | V88: 0 | W88: 0 | X88: 0 | Y88: 0 | Z88: 0 | AA88: 382322 | AB88: 0 | AC88: 0 | AD88: 0 | AE88: 0 | AF88: 0 | AG88: 0 | AH88: =SUM(C88:AG88) -> 1811200
A90: RRHH | B90: =AH90/$AH$10 -> 0.29232343 | C90: =sum(C91:C99) -> 115650 | D90: =sum(D91:D99) -> 0 | E90: =sum(E91:E99) -> 20000 | F90: =sum(F91:F99) -> 0 | G90: =sum(G91:G99) -> 0 | H90: =sum(H91:H99) -> 221732 | I90: =sum(I91:I99) -> 0 | J90: =sum(J91:J99) -> 350000 | ... AG90: =sum(AG91:AG99) -> 6642934 | AH90: =SUM(AH91:AH99) -> 11294785
A91: Turnos feriados | B91: =AH91/$AH$10 -> 0 | C91: 0 | D91: 0 | E91: 0 | F91: 0 | G91: 0 | H91: 0 | I91: 0 | J91: 0 | K91: 0 | L91: 0 | M91: 0 | N91: 0 | O91: 0 | P91: 0 | Q91: 0 | R91: 0 | S91: 0 | T91: 0 | U91: 0 | V91: 0 | W91: 0 | X91: 0 | Y91: 0 | Z91: 0 | AA91: 0 | AB91: 0 | AC91: 0 | AD91: 0 | AE91: 0 | AF91: 0 | AG91: 0 | AH91: =SUM(C91:AG91) -> 0
A92: Sueldo personal | B92: =AH92/$AH$10 -> 0.22008359 | C92: 0 | D92: 0 | E92: 0 | F92: 0 | G92: 0 | H92: 0 | I92: 0 | J92: 0 | K92: 0 | L92: 0 | M92: 0 | N92: 0 | O92: 0 | P92: 0 | Q92: =270000+300000+400000+260000+630650 -> 1860650 | R92: 0 | S92: 0 | T92: 0 | U92: 0 | V92: 0 | W92: 0 | X92: 0 | Y92: 0 | Z92: 0 | AA92: 0 | AB92: 0 | AC92: 0 | AD92: 0 | AE92: 0 | AF92: 0 | AG92: =3442117+810467+445000+1013539+560449+510449+460913-600000 -> 6642934 | AH92: =SUM(C92:AG92) -> 8503584
A93: Traslados personal | B93: =AH93/$AH$10 -> 0.00049394412 | C93: 5650 | D93: 0 | E93: 0 | F93: 0 | G93: 0 | H93: 13435 | I93: 0 | J93: 0 | K93: 0 | L93: 0 | M93: 0 | N93: 0 | O93: 0 | P93: 0 | Q93: 0 | R93: 0 | S93: 0 | T93: 0 | U93: 0 | V93: 0 | W93: 0 | X93: 0 | Y93: 0 | Z93: 0 | AA93: 0 | AB93: 0 | AC93: 0 | AD93: 0 | AE93: 0 | AF93: 0 | AG93: 0 | AH93: =SUM(C93:AG93) -> 19085
A94: Turnos extras | B94: =AH94/$AH$10 -> 0.0068585377 | C94: =40000+30000+40000 -> 110000 | D94: 0 | E94: 20000 | F94: 0 | G94: 0 | H94: 0 | I94: 0 | J94: 0 | K94: 0 | L94: =25000+70000 -> 95000 | M94: 0 | N94: 0 | O94: 0 | P94: 0 | Q94: 0 | R94: 0 | S94: 0 | T94: 0 | U94: 0 | V94: 0 | W94: 0 | X94: 0 | Y94: 40000 | Z94: 0 | AA94: 0 | AB94: 0 | AC94: 0 | AD94: 0 | AE94: 0 | AF94: 0 | AG94: 0 | AH94: =SUM(C94:AG94) -> 265000
A95: Bonos | B95: =AH95/$AH$10 -> 0.0053909918 | C95: 0 | D95: 0 | E95: 0 | F95: 0 | G95: 0 | H95: =50917+50917+27773+27773+50917 -> 208297 | I95: 0 | J95: 0 | K95: 0 | L95: 0 | M95: 0 | N95: 0 | O95: 0 | P95: 0 | Q95: 0 | R95: 0 | S95: 0 | T95: 0 | U95: 0 | V95: 0 | W95: 0 | X95: 0 | Y95: 0 | Z95: 0 | AA95: 0 | AB95: 0 | AC95: 0 | AD95: 0 | AE95: 0 | AF95: 0 | AG95: 0 | AH95: =SUM(C95:AG95) -> 208297
A96: Previred | B96: =AH96/$AH$10 -> 0.048498376 | C96: 0 | D96: 0 | E96: 0 | F96: 0 | G96: 0 | H96: 0 | I96: 0 | J96: 0 | K96: 0 | L96: 0 | M96: 0 | N96: 0 | O96: 1873879 | P96: 0 | Q96: 0 | R96: 0 | S96: 0 | T96: 0 | U96: 0 | V96: 0 | W96: 0 | X96: 0 | Y96: 0 | Z96: 0 | AA96: 0 | AB96: 0 | AC96: 0 | AD96: 0 | AE96: 0 | AF96: 0 | AG96: 0 | AH96: =SUM(C96:AG96) -> 1873879
A97: Uniforme pesonal | B97: =AH97/$AH$10 -> 0 | C97: 0 | D97: 0 | E97: 0 | F97: 0 | G97: 0 | H97: 0 | I97: 0 | J97: 0 | K97: 0 | L97: 0 | M97: 0 | N97: 0 | O97: 0 | P97: 0 | Q97: 0 | R97: 0 | S97: 0 | T97: 0 | U97: 0 | V97: 0 | W97: 0 | X97: 0 | Y97: 0 | Z97: 0 | AA97: 0 | AB97: 0 | AC97: 0 | AD97: 0 | AE97: 0 | AF97: 0 | AG97: 0 | AH97: =SUM(C97:AG97) -> 0
A98: Finiquitos | B98: =AH98/$AH$10 -> 0.009058446 | C98: 0 | D98: 0 | E98: 0 | F98: 0 | G98: 0 | H98: 0 | I98: 0 | J98: 350000 | K98: 0 | L98: 0 | M98: 0 | N98: 0 | O98: 0 | P98: 0 | Q98: 0 | R98: 0 | S98: 0 | T98: 0 | U98: 0 | V98: 0 | W98: 0 | X98: 0 | Y98: 0 | Z98: 0 | AA98: 0 | AB98: 0 | AC98: 0 | AD98: 0 | AE98: 0 | AF98: 0 | AG98: 0 | AH98: =SUM(C98:AG98) -> 350000
A99: Recreación | B99: =AH99/$AH$10 -> 0.0019395427 | C99: 0 | D99: 0 | E99: 0 | F99: 0 | G99: 0 | H99: 0 | I99: 0 | J99: 0 | K99: 0 | L99: 0 | M99: 0 | N99: 0 | O99: 0 | P99: 0 | Q99: 0 | R99: 0 | S99: 0 | T99: 0 | U99: 0 | V99: 0 | W99: 24980 | X99: 0 | Y99: 24980 | Z99: 0 | AA99: 0 | AB99: 24980 | AC99: 0 | AD99: 0 | AE99: 0 | AF99: 0 | AG99: 0 | AH99: =SUM(C99:AG99) -> 74940
A101: Impuestos fiscales | B101: =AH101/$AH$10 -> 0.093416699 | C101: =SUM(C102:C103) -> 0 | D101: =SUM(D102:D103) -> 0 | E101: =SUM(E102:E103) -> 0 | F101: =SUM(F102:F103) -> 0 | G101: =SUM(G102:G103) -> 0 | H101: =SUM(H102:H103) -> 0 | I101: =SUM(I102:I103) -> 0 | J101: =SUM(J102:J103) -> 0 | ... AH101: =SUM(AH102:AH103) -> 3609432
A102: Impuesto sobre la renta | B102: =AH102/$AH$10 -> 0 | C102: 0 | D102: 0 | E102: 0 | F102: 0 | G102: 0 | H102: 0 | I102: 0 | J102: 0 | K102: 0 | L102: 0 | M102: 0 | N102: 0 | O102: 0 | P102: 0 | Q102: 0 | R102: 0 | S102: 0 | T102: 0 | U102: 0 | V102: 0 | W102: 0 | X102: 0 | Y102: 0 | Z102: 0 | AA102: 0 | AB102: 0 | AC102: 0 | AD102: 0 | AE102: 0 | AF102: 0 | AG102: 0 | AH102: =SUM(C102:AG102) -> 0
A103: IVA | B103: =AH103/$AH$10 -> 0.093416699 | C103: 0 | D103: 0 | E103: 0 | F103: 0 | G103: 0 | H103: 0 | I103: 0 | J103: 0 | K103: 0 | L103: 0 | M103: 0 | N103: 0 | O103: 0 | P103: 0 | Q103: 0 | R103: 0 | S103: 0 | T103: 0 | U103: 3609432 | V103: 0 | W103: 0 | X103: 0 | Y103: 0 | Z103: 0 | AA103: 0 | AB103: 0 | AC103: 0 | AD103: 0 | AE103: 0 | AF103: 0 | AG103: 0 | AH103: =SUM(C103:AG103) -> 3609432
A105: Amortizaciones | AH105: =AH106+AH107 -> 0
A106: Préstamo | C106: 0 | D106: 0 | E106: 0 | F106: 0 | G106: 0 | H106: 0 | I106: 0 | J106: 0 | K106: 0 | L106: 0 | M106: 0 | N106: 0 | O106: 0 | P106: 0 | Q106: 0 | R106: 0 | S106: 0 | T106: 0 | U106: 0 | V106: 0 | W106: 0 | X106: 0 | Y106: 0 | Z106: 0 | AA106: 0 | AB106: 0 | AC106: 0 | AD106: 0 | AE106: 0 | AF106: 0 | AG106: 0 | AH106: =sum(C106:AG106) -> 0
C107: 0 | D107: 0 | E107: 0 | F107: 0 | G107: 0 | H107: 0 | I107: 0 | J107: 0 | K107: 0 | L107: 0 | M107: 0 | N107: 0 | O107: 0 | P107: 0 | Q107: 0 | R107: 0 | S107: 0 | T107: 0 | U107: 0 | V107: 0 | W107: 0 | X107: 0 | Y107: 0 | Z107: 0 | AA107: 0 | AB107: 0 | AC107: 0 | AD107: 0 | AE107: 0 | AF107: 0 | AG107: 0 | AH107: =sum(C107:AG107) -> 0
A109: Total egresos conciliación | C109: =C101+C90+C84+C34+C78+C12+C106+C107 -> 774034 | D109: =D101+D90+D84+D34+D78+D12+D106+D107 -> 109171 | E109: =E101+E90+E84+E34+E78+E12+E106+E107 -> 521148 | F109: =F101+F90+F84+F34+F78+F12+F106+F107 -> 483845 | G109: =G101+G90+G84+G34+G78+G12+G106+G107 -> 1950765 | H109: =H101+H90+H84+H34+H78+H12+H106+H107 -> 1954972 | I109: =I101+I90+I84+I34+I78+I12+I106+I107 -> 2473644 | J109: =J101+J90+J84+J34+J78+J12+J106+J107 -> 1274640 | ... AG109: =AG101+AG90+AG84+AG34+AG78+AG12+AG106+AG107 -> 7250450 | AH109: =sum(C109:AF109) -> 36047799
A110: Total egresos operativos | C110: =C101+C90+C34+C78+C12 -> 213250 | D110: =D101+D90+D34+D78+D12 -> 109171 | E110: =E101+E90+E34+E78+E12 -> 521148 | F110: =F101+F90+F34+F78+F12 -> 88956 | G110: =G101+G90+G34+G78+G12 -> 1950765 | H110: =H101+H90+H34+H78+H12 -> 1954972 | I110: =I101+I90+I34+I78+I12 -> 2473644 | J110: =J101+J90+J34+J78+J12 -> 632450 | ... AG110: =AG101+AG90+AG34+AG78+AG12 -> 7242934 | AH110: =sum(C110:AG110) -> 38780312
A112: Rentabilidad | B112: =AH112/$AH$10 -> -0.0036838888 | C112: =C9-C110 -> 1398524 | D112: =D9-D110 -> 1613974 | E112: =E9-E110 -> 1946221 | F112: =F9-F110 -> 1095613 | G112: =G9-G110 -> -782484 | H112: =H9-H110 -> -1133581 | I112: =I9-I110 -> -1311147 | J112: =J9-J110 -> 353147 | ... AG112: =AG9-AG110 -> -4850697 | AH112: =AH10-AH110 -> -142338

Sheet Junio
C1: 46143 | D1: 46144 | E1: 46145 | F1: 46146 | G1: 46147 | H1: 46148 | I1: 46149 | J1: 46150 | K1: 46151 | L1: 46152 | M1: 46153 | N1: 46154 | O1: 46155 | P1: 46156 | Q1: 46157 | R1: 46158 | S1: 46159 | T1: 46160 | U1: 46161 | V1: 46162 | W1: 46163 | X1: 46164 | Y1: 46165 | Z1: 46166 | AA1: 46167 | AB1: 46168 | AC1: 46169 | AD1: 46170 | AE1: 46171 | AF1: 46172 | AG1: 46173 | AH1: Totales
A4: Ingresos
A5: Transbank | C5: =551524+1271774 -> 1823298 | D5: =158558+22656+15157 -> 196371 | E5: =556461+654757+15644 -> 1226862 | F5: =10017+327416+637367+71444 -> 1046244 | G5: =1023279+58262+649176+35573 -> 1766290 | H5: =475578+575771+113700 -> 1165049 | I5: =538597+982570+58391+108212 -> 1687770 | J5: =27203+652602+227186 -> 906991 | K5: =375184++27202 -> 402386 | L5: =340161+539055+30493+96355 -> 1006064 | M5: =607443+14367+428669+93864 -> 1144343 | N5: =363148+344988+50194+23806+89081 -> 871217 | O5: =72951+821972+671088+31188+87189+45032 -> 1729420 | P5: =1619468+473505+83903+39021+38662+134319 -> 2388878 | Q5: =688640+48326+268537 -> 1005503 | R5: =271080+52435 -> 323515 | S5: =13876+424181+49921+683282+41611+70049 -> 1282920 | T5: =402877+290632+40976+392385 -> 1126870 | U5: =2104799+142800+590409+79730+76127 -> 2993865 | V5: =36270+27816+31088+56299+741841+1004454 -> 1897768 | W5: =18832+619580+1116932+137309 -> 1892653 | X5: =117380+1023672+24717 -> 1165769 | Y5: =203471 -> 203471 | Z5: =98747+27292+100800+711568+41158 -> 979565 | AA5: =318787+382909+26871+123059 -> 851626 | AB5: =521830+44790+623592+42490 -> 1232702 | AC5: =886994+603282+78818 -> 1569094 | AD5: =747167+45337+1331509+38063+83102 -> 2245178 | AE5: =1207826+330873 -> 1538699 | AF5: =416169+9122+27900+8868 -> 462059 | AG5: 0 | AH5: =SUM(C5:AG5) -> 38132440
A6: Transferencias | C6: 0 | D6: 0 | E6: 30300 | F6: 22900 | G6: 0 | H6: 28480 | I6: 0 | J6: 24900 | K6: =19715+23750 -> 43465 | L6: 0 | M6: 25100 | N6: 53200 | O6: 0 | P6: 0 | Q6: 0 | R6: 25900 | S6: 0 | T6: 2250 | U6: 25900 | V6: 0 | W6: 0 | X6: 26600 | Y6: 0 | Z6: 0 | AA6: 0 | AB6: 0 | AC6: 53200 | AD6: 0 | AE6: 0 | AF6: 0 | AG6: 0 | AH6: =SUM(C6:AG6) -> 362195
A7: Efectivo | C7: 0 | D7: 0 | E7: 0 | F7: 0 | G7: 0 | H7: 0 | I7: 0 | J7: 0 | K7: 0 | L7: 0 | M7: 0 | N7: 0 | O7: 0 | P7: 0 | Q7: 0 | R7: 0 | S7: 0 | T7: 0 | U7: 0 | V7: 0 | W7: 0 | X7: 0 | Y7: 0 | Z7: 240000 | AA7: 0 | AB7: 0 | AC7: 0 | AD7: 0 | AE7: 0 | AF7: 0 | AG7: 0 | AH7: =SUM(C7:AG7) -> 240000
A8: Uber | C8: 0 | D8: =140294+611860 -> 752154 | E8: 0 | F8: 0 | G8: 0 | H8: 0 | I8: 0 | J8: 0 | K8: =205643+466211 -> 671854 | L8: 0 | M8: 0 | N8: 0 | O8: 0 | P8: 0 | Q8: 0 | R8: =272531+313497 -> 586028 | S8: 0 | T8: 0 | U8: 0 | V8: 0 | W8: 0 | X8: 0 | Y8: =402802+262746 -> 665548 | Z8: 0 | AA8: 0 | AB8: 0 | AC8: 0 | AD8: 0 | AE8: 0 | AF8: =694787+360794 -> 1055581 | AG8: 0 | AH8: =SUM(C8:AG8) -> 3731165
A9: Total bruto | C9: =SUM(C5:C8) -> 1823298 | D9: =SUM(D5:D8) -> 948525 | E9: =SUM(E5:E8) -> 1257162 | F9: =SUM(F5:F8) -> 1069144 | G9: =SUM(G5:G8) -> 1766290 | H9: =SUM(H5:H8) -> 1193529 | I9: =SUM(I5:I8) -> 1687770 | J9: =SUM(J5:J8) -> 931891 | ... AH9: =SUM(AH5:AH8) -> 42465800
A10: Total neto | AH10: =AH9-AH84 -> 37749452
A12: Materia prima | B12: =AH12/$AH$10 -> 0.35266631 | C12: =sum(C13:C32) -> 887001 | D12: =sum(D13:D32) -> 398620 | E12: =sum(E13:E32) -> 100000 | F12: =sum(F13:F32) -> 561664 | G12: =sum(G13:G32) -> 644791 | H12: =sum(H13:H32) -> 0 | I12: =sum(I13:I32) -> 250000 | J12: =sum(J13:J32) -> 0 | ... AH12: =sum(AH13:AH32) -> 13312960
A13: MP | B13: =AH13/$AH$10 -> 0.10631709 | C13: =83257+100000 -> 183257 | D13: 0 | E13: 100000 | F13: 100000 | G13: =114000+200000 -> 314000 | H13: 0 | I13: 250000 | J13: 0 | K13: 0 | L13: 100000 | M13: 400000 | N13: =100000+300000+50000 -> 450000 | O13: 0 | P13: 0 | Q13: 50000 | R13: =18600+94000 -> 112600 | S13: 100000 | T13: =24500+77350 -> 101850 | U13: 350000 | V13: 50000 | W13: 250000 | X13: =50000 -> 50000 | Y13: 100000 | Z13: =100000+100000 -> 200000 | AA13: =200000+201705 -> 401705 | AB13: 0 | AC13: 150000 | AD13: 100000 | AE13: 100000 | AF13: 0 | AG13: 0 | AH13: =SUM(C13:AG13) -> 4013412
A14: Arroz | B14: =AH14/$AH$10 -> 0.0063153235 | C14: 0 | D14: 0 | E14: 0 | F14: 0 | G14: 0 | H14: 0 | I14: 0 | J14: 0 | K14: 0 | L14: 119200 | M14: 0 | N14: 0 | O14: 0 | P14: 0 | Q14: 0 | R14: 0 | S14: 0 | T14: 0 | U14: 0 | V14: 0 | W14: 0 | X14: 119200 | Y14: 0 | Z14: 0 | AA14: 0 | AB14: 0 | AC14: 0 | AD14: 0 | AE14: 0 | AF14: 0 | AG14: 0 | AH14: =SUM(C14:AG14) -> 238400
A15: Hod Food | B15: =AH15/$AH$10 -> 0.080970341 | C15: 587124 | D15: 0 | E15: 0 | F15: 0 | G15: 0 | H15: 0 | I15: 0 | J15: 0 | K15: 618671 | L15: 0 | M15: 0 | N15: 0 | O15: 0 | P15: 0 | Q15: 0 | R15: 577150 | S15: 0 | T15: 0 | U15: 0 | V15: 0 | W15: 0 | X15: 0 | Y15: 645348 | Z15: 0 | AA15: 0 | AB15: 0 | AC15: 0 | AD15: 0 | AE15: 0 | AF15: 628293 | AG15: 0 | AH15: =SUM(C15:AG15) -> 3056586
A16: Seitan | B16: =AH16/$AH$10 -> 0.0081583171 | C16: 0 | D16: 0 | E16: 0 | F16: 0 | G16: 0 | H16: 0 | I16: 0 | J16: 0 | K16: 0 | L16: 0 | M16: 0 | N16: 0 | O16: 0 | P16: 0 | Q16: 0 | R16: 0 | S16: 0 | T16: 153986 | U16: 0 | V16: 0 | W16: 0 | X16: 0 | Y16: 0 | Z16: 0 | AA16: 0 | AB16: 153986 | AC16: 0 | AD16: 0 | AE16: 0 | AF16: 0 | AG16: 0 | AH16: =SUM(C16:AG16) -> 307972
A17: Palta | B17: =AH17/$AH$10 -> 0.020026781 | C17: 0 | D17: 0 | E17: 0 | F17: 336000 | G17: 0 | H17: 0 | I17: 0 | J17: 0 | K17: 0 | L17: 0 | M17: 0 | N17: 0 | O17: 0 | P17: 0 | Q17: 0 | R17: 0 | S17: 420000 | T17: 0 | U17: 0 | V17: 0 | W17: 0 | X17: 0 | Y17: 0 | Z17: 0 | AA17: 0 | AB17: 0 | AC17: 0 | AD17: 0 | AE17: 0 | AF17: 0 | AG17: 0 | AH17: =SUM(C17:AG17) -> 756000
A18: Champiñon | B18: =AH18/$AH$10 -> 0.014028018 | C18: 0 | D18: 0 | E18: 0 | F18: 0 | G18: 0 | H18: 0 | I18: 0 | J18: 0 | K18: 0 | L18: 190400 | M18: 0 | N18: 0 | O18: 0 | P18: 0 | Q18: 0 | R18: 0 | S18: 0 | T18: 0 | U18: 0 | V18: 0 | W18: 0 | X18: 0 | Y18: 0 | Z18: 339150 | AA18: 0 | AB18: 0 | AC18: 0 | AD18: 0 | AE18: 0 | AF18: 0 | AG18: 0 | AH18: =SUM(C18:AG18) -> 529550
A19: Verduras | B19: =AH19/$AH$10 -> 0.04617418 | C19: 0 | D19: 398620 | E19: 0 | F19: 0 | G19: 0 | H19: 0 | I19: 0 | J19: 0 | K19: 0 | L19: 507990 | M19: 0 | N19: 0 | O19: 0 | P19: 0 | Q19: 0 | R19: 0 | S19: 403890 | T19: 0 | U19: 0 | V19: 0 | W19: 0 | X19: 0 | Y19: 0 | Z19: 432550 | AA19: 0 | AB19: 0 | AC19: 0 | AD19: 0 | AE19: 0 | AF19: 0 | AG19: 0 | AH19: =SUM(C19:AG19) -> 1743050
A20: Tofu | B20: =AH20/$AH$10 -> 0.013351187 | C20: 0 | D20: 0 | E20: 0 | F20: 0 | G20: 84000 | H20: 0 | I20: 0 | J20: 0 | K20: 0 | L20: 84000 | M20: 0 | N20: 0 | O20: 0 | P20: 0 | Q20: 84000 | R20: 0 | S20: 0 | T20: 0 | U20: 84000 | V20: 0 | W20: 0 | X20: 0 | Y20: 84000 | Z20: 0 | AA20: 84000 | AB20: 0 | AC20: 0 | AD20: 0 | AE20: 0 | AF20: 0 | AG20: 0 | AH20: =SUM(C20:AG20) -> 504000
A21: shen | B21: =AH21/$AH$10 -> 0.0080070037 | C21: 116620 | D21: 0 | E21: 0 | F21: 0 | G21: 0 | H21: 0 | I21: 0 | J21: 0 | K21: 0 | L21: 0 | M21: 0 | N21: 0 | O21: 0 | P21: 0 | Q21: 0 | R21: 0 | S21: 0 | T21: =80920+104720 -> 185640 | U21: 0 | V21: 0 | W21: 0 | X21: 0 | Y21: 0 | Z21: 0 | AA21: 0 | AB21: 0 | AC21: 0 | AD21: 0 | AE21: 0 | AF21: 0 | AG21: 0 | AH21: =SUM(C21:AG21) -> 302260
A22: Mozzen | B22: =AH22/$AH$10 -> 0.0046182127 | C22: 0 | D22: 0 | E22: 0 | F22: 0 | G22: 0 | H22: 0 | I22: 0 | J22: 0 | K22: 0 | L22: 0 | M22: 0 | N22: 0 | O22: 0 | P22: 0 | Q22: 0 | R22: 174335 | S22: 0 | T22: 0 | U22: 0 | V22: 0 | W22: 0 | X22: 0 | Y22: 0 | Z22: 0 | AA22: 0 | AB22: 0 | AC22: 0 | AD22: 0 | AE22: 0 | AF22: 0 | AG22: 0 | AH22: =SUM(C22:AG22) -> 174335
A23: Café y Té | B23: =AH23/$AH$10 -> 0 | C23: 0 | D23: 0 | E23: 0 | F23: 0 | G23: 0 | H23: 0 | I23: 0 | J23: 0 | K23: 0 | L23: 0 | M23: 0 | N23: 0 | O23: 0 | P23: 0 | Q23: 0 | R23: 0 | S23: 0 | T23: 0 | U23: 0 | V23: 0 | W23: 0 | X23: 0 | Y23: 0 | Z23: 0 | AA23: 0 | AB23: 0 | AC23: 0 | AD23: 0 | AE23: 0 | AF23: 0 | AG23: 0 | AH23: =SUM(C23:AG23) -> 0
A24: Leche de soya | B24: =AH24/$AH$10 -> 0.0059012247 | C24: 0 | D24: 0 | E24: 0 | F24: 0 | G24: 0 | H24: 0 | I24: 0 | J24: 0 | K24: 111384 | L24: 0 | M24: 0 | N24: 0 | O24: 0 | P24: 0 | Q24: 0 | R24: 0 | S24: 0 | T24: 0 | U24: 0 | V24: 0 | W24: 0 | X24: 0 | Y24: 111384 | Z24: 0 | AA24: 0 | AB24: 0 | AC24: 0 | AD24: 0 | AE24: 0 | AF24: 0 | AG24: 0 | AH24: =SUM(C24:AG24) -> 222768
A25: Bebestibles | B25: =AH25/$AH$10 -> 0.0018441327 | C25: 0 | D25: 0 | E25: 0 | F25: 0 | G25: 0 | H25: 0 | I25: 0 | J25: 0 | K25: 0 | L25: 0 | M25: 23205 | N25: 0 | O25: 0 | P25: 0 | Q25: 0 | R25: 0 | S25: 0 | T25: 23205 | U25: 0 | V25: 0 | W25: 0 | X25: 0 | Y25: 0 | Z25: 0 | AA25: 0 | AB25: 0 | AC25: 0 | AD25: 0 | AE25: 0 | AF25: 23205 | AG25: 0 | AH25: =SUM(C25:AG25) -> 69615
A26: Brugga | B26: =AH26/$AH$10 -> 0.015881608 | C26: 0 | D26: 0 | E26: 0 | F26: 125664 | G26: 0 | H26: 0 | I26: 0 | J26: 0 | K26: 157080 | L26: 0 | M26: 0 | N26: 0 | O26: 0 | P26: 0 | Q26: 0 | R26: 157080 | S26: 0 | T26: 0 | U26: 0 | V26: 0 | W26: 0 | X26: 0 | Y26: 0 | Z26: 0 | AA26: 0 | AB26: 159698 | AC26: 0 | AD26: 0 | AE26: 0 | AF26: 0 | AG26: 0 | AH26: =SUM(C26:AG26) -> 599522
A27: Colación | B27: =AH27/$AH$10 -> 0 | C27: 0 | D27: 0 | E27: 0 | F27: 0 | G27: 0 | H27: 0 | I27: 0 | J27: 0 | K27: 0 | L27: 0 | M27: 0 | N27: 0 | O27: 0 | P27: 0 | Q27: 0 | R27: 0 | S27: 0 | T27: 0 | U27: 0 | V27: 0 | W27: 0 | X27: 0 | Y27: 0 | Z27: 0 | AA27: 0 | AB27: 0 | AC27: 0 | AD27: 0 | AE27: 0 | AF27: 0 | AG27: 0 | AH27: =SUM(C27:AG27) -> 0
A28: Empaques y desechables | B28: =AH28/$AH$10 -> 0.01021334 | C28: 0 | D28: 0 | E28: 0 | F28: 0 | G28: 156794 | H28: 0 | I28: 0 | J28: 0 | K28: 0 | L28: 0 | M28: 0 | N28: 0 | O28: 0 | P28: 0 | Q28: 0 | R28: 0 | S28: 0 | T28: 156794 | U28: 0 | V28: 0 | W28: 0 | X28: 0 | Y28: 0 | Z28: 0 | AA28: 0 | AB28: 0 | AC28: 0 | AD28: 0 | AE28: 71960 | AF28: 0 | AG28: 0 | AH28: =SUM(C28:AG28) -> 385548
A29: Soyas sachet | B29: =AH29/$AH$10 -> 0.0023840611 | C29: 0 | D29: 0 | E29: 0 | F29: 0 | G29: 89997 | H29: 0 | I29: 0 | J29: 0 | K29: 0 | L29: 0 | M29: 0 | N29: 0 | O29: 0 | P29: 0 | Q29: 0 | R29: 0 | S29: 0 | T29: 0 | U29: 0 | V29: 0 | W29: 0 | X29: 0 | Y29: 0 | Z29: 0 | AA29: 0 | AB29: 0 | AC29: 0 | AD29: 0 | AE29: 0 | AF29: 0 | AG29: 0 | AH29: =SUM(C29:AG29) -> 89997
A30: Servilletas | B30: =AH30/$AH$10 -> 0.0021940451 | C30: 0 | D30: 0 | E30: 0 | F30: 0 | G30: 0 | H30: 0 | I30: 0 | J30: 0 | K30: 0 | L30: 0 | M30: 82824 | N30: 0 | O30: 0 | P30: 0 | Q30: 0 | R30: 0 | S30: 0 | T30: 0 | U30: 0 | V30: 0 | W30: 0 | X30: 0 | Y30: 0 | Z30: 0 | AA30: 0 | AB30: 0 | AC30: 0 | AD30: 0 | AE30: 0 | AF30: 0 | AG30: 0 | AH30: =SUM(C30:AG30) -> 82824
A31: Limpieza e higiene | B31: =AH31/$AH$10 -> 0.00010066371 | C31: 0 | D31: 0 | E31: 0 | F31: 0 | G31: 0 | H31: 0 | I31: 0 | J31: 0 | K31: 0 | L31: 0 | M31: 0 | N31: 0 | O31: 0 | P31: 0 | Q31: 0 | R31: 0 | S31: 0 | T31: 0 | U31: 0 | V31: 0 | W31: 0 | X31: 0 | Y31: 3800 | Z31: 0 | AA31: 0 | AB31: 0 | AC31: 0 | AD31: 0 | AE31: 0 | AF31: 0 | AG31: 0 | AH31: =SUM(C31:AG31) -> 3800
A32: Postres | B32: =AH32/$AH$10 -> 0.0061807785 | C32: 0 | D32: 0 | E32: 0 | F32: 0 | G32: 0 | H32: 0 | I32: 0 | J32: 0 | K32: 0 | L32: 0 | M32: 78000 | N32: 0 | O32: 0 | P32: 0 | Q32: 0 | R32: 0 | S32: 0 | T32: 0 | U32: 0 | V32: 0 | W32: 0 | X32: 0 | Y32: 77321 | Z32: 78000 | AA32: 0 | AB32: 0 | AC32: 0 | AD32: 0 | AE32: 0 | AF32: 0 | AG32: 0 | AH32: =SUM(C32:AG32) -> 233321
A34: Gastos FV | B34: =AH34/$AH$10 -> 0.10135517 | C34: =sum(C35+C55+C65) -> 0 | D34: =sum(D35+D55+D65) -> 100000 | E34: =sum(E35+E55+E65) -> 58245 | F34: =sum(F35+F55+F65) -> 0 | G34: =sum(G35+G55+G65) -> 747239 | H34: =sum(H35+H55+H65) -> 0 | I34: =sum(I35+I55+I65) -> 0 | J34: =sum(J35+J55+J65) -> 4041 | ... AH34: =sum(AH35+AH55+AH65) -> 3826102
A35: Operaciones | B35: =AH35/$AH$10 -> 0.081291326 | C35: =sum(C36:C54) -> 0 | D35: =sum(D36:D54) -> 100000 | E35: =sum(E36:E54) -> 0 | F35: =sum(F36:F54) -> 0 | G35: =sum(G36:G54) -> 575903 | H35: =sum(H36:H54) -> 0 | I35: =sum(I36:I54) -> 0 | J35: =sum(J36:J54) -> 0 | ... AH35: =sum(AH36:AH54) -> 3068703
A36: Electricidad | B36: =AH36/$AH$10 -> 0.0061864209 | C36: 0 | D36: 0 | E36: 0 | F36: 0 | G36: 0 | H36: 0 | I36: 0 | J36: 0 | K36: 0 | L36: 0 | M36: 0 | N36: 0 | O36: 0 | P36: 0 | Q36: 0 | R36: 0 | S36: 0 | T36: 0 | U36: =100687+132847 -> 233534 | V36: 0 | W36: 0 | X36: 0 | Y36: 0 | Z36: 0 | AA36: 0 | AB36: 0 | AC36: 0 | AD36: 0 | AE36: 0 | AF36: 0 | AG36: 0 | AH36: =SUM(C36:AG36) -> 233534
A37: Agua | B37: =AH37/$AH$10 -> 0.0020050622 | C37: 0 | D37: 0 | E37: 0 | F37: 0 | G37: 0 | H37: 0 | I37: 0 | J37: 0 | K37: 0 | L37: 0 | M37: 0 | N37: 0 | O37: 0 | P37: 0 | Q37: 0 | R37: 0 | S37: 0 | T37: 0 | U37: 75690 | V37: 0 | W37: 0 | X37: 0 | Y37: 0 | Z37: 0 | AA37: 0 | AB37: 0 | AC37: 0 | AD37: 0 | AE37: 0 | AF37: 0 | AG37: 0 | AH37: =SUM(C37:AG37) -> 75690
A38: Gas | B38: =AH38/$AH$10 -> 0.0030093152 | C38: 0 | D38: 0 | E38: 0 | F38: 0 | G38: 0 | H38: 0 | I38: 0 | J38: 0 | K38: 0 | L38: 0 | M38: 0 | N38: 0 | O38: 0 | P38: 0 | Q38: 0 | R38: 0 | S38: 0 | T38: 0 | U38: 113600 | V38: 0 | W38: 0 | X38: 0 | Y38: 0 | Z38: 0 | AA38: 0 | AB38: 0 | AC38: 0 | AD38: 0 | AE38: 0 | AF38: 0 | AG38: 0 | AH38: =SUM(C38:AG38) -> 113600
A39: Restaurantpe | B39: =AH39/$AH$10 -> 0 | C39: 0 | D39: 0 | E39: 0 | F39: 0 | G39: 0 | H39: 0 | I39: 0 | J39: 0 | K39: 0 | L39: 0 | M39: 0 | N39: 0 | O39: 0 | P39: 0 | Q39: 0 | R39: 0 | S39: 0 | T39: 0 | U39: 0 | V39: 0 | W39: 0 | X39: 0 | Y39: 0 | Z39: 0 | AA39: 0 | AB39: 0 | AC39: 0 | AD39: 0 | AE39: 0 | AF39: 0 | AG39: 0 | AH39: =SUM(C39:AG39) -> 0
A40: Toteat | B40: =AH40/$AH$10 -> 0.0059842723 | C40: 0 | D40: 0 | E40: 0 | F40: 0 | G40: =125603+100300 -> 225903 | H40: 0 | I40: 0 | J40: 0 | K40: 0 | L40: 0 | M40: 0 | N40: 0 | O40: 0 | P40: 0 | Q40: 0 | R40: 0 | S40: 0 | T40: 0 | U40: 0 | V40: 0 | W40: 0 | X40: 0 | Y40: 0 | Z40: 0 | AA40: 0 | AB40: 0 | AC40: 0 | AD40: 0 | AE40: 0 | AF40: 0 | AG40: 0 | AH40: =SUM(C40:AG40) -> 225903
A41: Alarma | B41: =AH41/$AH$10 -> 0 | C41: 0 | D41: 0 | E41: 0 | F41: 0 | G41: 0 | H41: 0 | I41: 0 | J41: 0 | K41: 0 | L41: 0 | M41: 0 | N41: 0 | O41: 0 | P41: 0 | Q41: 0 | R41: 0 | S41: 0 | T41: 0 | U41: 0 | V41: 0 | W41: 0 | X41: 0 | Y41: 0 | Z41: 0 | AA41: 0 | AB41: 0 | AC41: 0 | AD41: 0 | AE41: 0 | AF41: 0 | AG41: 0 | AH41: =SUM(C41:AG41) -> 0
A42: VTR | B42: =AH42/$AH$10 -> 0.00031287871 | C42: 0 | D42: 0 | E42: 0 | F42: 0 | G42: 0 | H42: 0 | I42: 0 | J42: 0 | K42: 0 | L42: 0 | M42: 0 | N42: 11811 | O42: 0 | P42: 0 | Q42: 0 | R42: 0 | S42: 0 | T42: 0 | U42: 0 | V42: 0 | W42: 0 | X42: 0 | Y42: 0 | Z42: 0 | AA42: 0 | AB42: 0 | AC42: 0 | AD42: 0 | AE42: 0 | AF42: 0 | AG42: 0 | AH42: =SUM(C42:AG42) -> 11811
A43: Bodega | B43: =AH43/$AH$10 -> 0.0092716578 | C43: 0 | D43: 0 | E43: 0 | F43: 0 | G43: 350000 | H43: 0 | I43: 0 | J43: 0 | K43: 0 | L43: 0 | M43: 0 | N43: 0 | O43: 0 | P43: 0 | Q43: 0 | R43: 0 | S43: 0 | T43: 0 | U43: 0 | V43: 0 | W43: 0 | X43: 0 | Y43: 0 | Z43: 0 | AA43: 0 | AB43: 0 | AC43: 0 | AD43: 0 | AE43: 0 | AF43: 0 | AG43: 0 | AH43: =SUM(C43:AG43) -> 350000
A44: Arriendo | B44: =AH44/$AH$10 -> 0.049507235 | C44: 0 | D44: 0 | E44: 0 | F44: 0 | G44: 0 | H44: 0 | I44: 0 | J44: 0 | K44: 1868871 | L44: 0 | M44: 0 | N44: 0 | O44: 0 | P44: 0 | Q44: 0 | R44: 0 | S44: 0 | T44: 0 | U44: 0 | V44: 0 | W44: 0 | X44: 0 | Y44: 0 | Z44: 0 | AA44: 0 | AB44: 0 | AC44: 0 | AD44: 0 | AE44: 0 | AF44: 0 | AG44: 0 | AH44: =SUM(C44:AG44) -> 1868871
A45: Funmigacion | B45: =AH45/$AH$10 -> 0.0026490451 | C45: 0 | D45: 100000 | E45: 0 | F45: 0 | G45: 0 | H45: 0 | I45: 0 | J45: 0 | K45: 0 | L45: 0 | M45: 0 | N45: 0 | O45: 0 | P45: 0 | Q45: 0 | R45: 0 | S45: 0 | T45: 0 | U45: 0 | V45: 0 | W45: 0 | X45: 0 | Y45: 0 | Z45: 0 | AA45: 0 | AB45: 0 | AC45: 0 | AD45: 0 | AE45: 0 | AF45: 0 | AG45: 0 | AH45: =SUM(C45:AG45) -> 100000
A46: Aroclean | B46: =AH46/$AH$10 -> 0.0020480827 | C46: 0 | D46: 0 | E46: 0 | F46: 0 | G46: 0 | H46: 0 | I46: 0 | J46: 0 | K46: 0 | L46: 0 | M46: 0 | N46: 0 | O46: 0 | P46: 0 | Q46: 0 | R46: 0 | S46: 0 | T46: 0 | U46: 0 | V46: 0 | W46: 0 | X46: 0 | Y46: 0 | Z46: 0 | AA46: 0 | AB46: 0 | AC46: 0 | AD46: 0 | AE46: 0 | AF46: 77314 | AG46: 0 | AH46: =SUM(C46:AG46) -> 77314
A47: Reposición de vasos | B47: =AH47/$AH$10 -> 0 | C47: 0 | D47: 0 | E47: 0 | F47: 0 | G47: 0 | H47: 0 | I47: 0 | J47: 0 | K47: 0 | L47: 0 | M47: 0 | N47: 0 | O47: 0 | P47: 0 | Q47: 0 | R47: 0 | S47: 0 | T47: 0 | U47: 0 | V47: 0 | W47: 0 | X47: 0 | Y47: 0 | Z47: 0 | AA47: 0 | AB47: 0 | AC47: 0 | AD47: 0 | AE47: 0 | AF47: 0 | AG47: 0 | AH47: =SUM(C47:AG47) -> 0
A48: Reposición Articulos cocina | B48: =AH48/$AH$10 -> 0 | C48: 0 | D48: 0 | E48: 0 | F48: 0 | G48: 0 | H48: 0 | I48: 0 | J48: 0 | K48: 0 | L48: 0 | M48: 0 | N48: 0 | O48: 0 | P48: 0 | Q48: 0 | R48: 0 | S48: 0 | T48: 0 | U48: 0 | V48: 0 | W48: 0 | X48: 0 | Y48: 0 | Z48: 0 | AA48: 0 | AB48: 0 | AC48: 0 | AD48: 0 | AE48: 0 | AF48: 0 | AG48: 0 | AH48: =SUM(C48:AG48) -> 0
A49: Reposición articulos salón | B49: =AH49/$AH$10 -> 0 | C49: 0 | D49: 0 | E49: 0 | F49: 0 | G49: 0 | H49: 0 | I49: 0 | J49: 0 | K49: 0 | L49: 0 | M49: 0 | N49: 0 | O49: 0 | P49: 0 | Q49: 0 | R49: 0 | S49: 0 | T49: 0 | U49: 0 | V49: 0 | W49: 0 | X49: 0 | Y49: 0 | Z49: 0 | AA49: 0 | AB49: 0 | AC49: 0 | AD49: 0 | AE49: 0 | AF49: 0 | AG49: 0 | AH49: =SUM(C49:AG49) -> 0
